Workbook

Sheet 읽는 법
A1: 2일차 엑셀 검산본 — 실습 확인표를 엑셀 수식으로 다시 계산
A3: 무엇 | B3: 실습 A 확인표(슬라이드 d2-70) 여섯 줄을 사람이 엑셀만으로 계산했다면 어떻게 나오는지 보여 주는 완성본입니다. 확인표_B 시트는 실습 B 확인표(d2-73)의 30일 창 · 바이어 수를 같은 방법으로 셉니다.
A4: 왜 | B4: AI(Claude Code)가 스크립트로 만든 d2_buyers_clean.csv · d2_end_features.csv의 숫자를 코드가 아닌 다른 길로 한 번 더 확인하는 기준입니다. 정답지가 아닙니다 — 다르면 어느 규칙에서 갈렸는지 찾는 것이 실습입니다. 엑셀을 직접 만들 필요는 없습니다.
A5: 칸 색 | B5: 노란 칸 = 수식(칸을 누르면 수식 막대에 수식이 보입니다) · 회색 칸 = d2_start.xlsx의 원래 값 그대로 · 흰 칸 = 내가 적는 칸(선택).
A6: 어떻게 만들었나 | B6: buyers_원본 · 환율_기준일 · 뉴스_앞100행 시트에 공개 파일(d2_start.xlsx · d2_news.csv)의 값을 고치지 않고 옮기고, 나머지는 모두 수식입니다. 기준일 2026-08-31, 환율은 그날 값(엔화는 100엔당 값이라 ÷100). 검산에 쓰지 않는 열(결제방식 · 국가 · 연령 구간 일부 · 재무 외 열)은 옮기지 않았습니다.
A7: 시트 | B7: B001_손계산 — 인쇄 단계 05의 'B001 손계산'을 수식으로 · B009(글자 섞인 칸) · B072(단위 의심)도 확인표_A — 실습 A 확인표 여섯 줄 + 통화 표기 9가지 → 표준 4종 확인표_B — 실습 B의 30일 창 (2026-08-01, 2026-08-31] 기사 · 바이어 수 buyers_원본 · 환율_기준일 · 뉴스_앞100행 — 원래 값과 보조 열(노란 칸)
A8: 엑셀이 못 하는 것 | B8: 글자가 섞인 금액 13칸(' 195900 ' · 'CNY 317,000' · '47.0k' …)은 수식으로 숫자를 만들지 않고 '글자 섞임'으로만 표시합니다. 엑셀로는 이 칸을 사람이 하나씩 고쳐야 합니다 — 그래서 규칙을 문서로 정하고 스크립트로 고칩니다.
A9: 주의 | B9: 이 파일은 고치지 말고 읽기만 합니다(필요하면 사본을 만들어 씁니다). 숫자가 내 결과와 다르면 '어느 규칙에서 갈렸나'를 AI에게 먼저 묻습니다.
A10: 데이터 | B10: (가상) 한빛정밀(주)의 합성 데이터 · CC BY 4.0. 환율은 미국 연준 H.10 환율(FRED 제공) · Public Domain: Citation Requested.

Sheet B001_손계산
A1: B001 손계산 — 인쇄 단계 05의 'B001 손계산'을 대신하는 완성본
A2: 노란 칸을 눌러 수식을 봅니다. 원하면 흰 칸(B13)에 =18100*1589.5/1368.25 를 한 번 직접 쳐 봅니다(1분).
A4: 항목 | B4: 값 | C4: 어디서 · 수식 | D4: 메모
A5: B001 잔액(원래 통화) | B5: ='buyers_원본'!C2 -> 18100 | C5: buyers_원본 C2 | D5: ='buyers_원본'!B2 -> EUR
A6: 기준일 EUR 환율(원) | B6: ='환율_기준일'!E5 -> 1589.5 | C6: 환율_기준일 E5(2026-08-31)
A7: 기준일 USD 환율(원) | B7: ='환율_기준일'!E4 -> 1368.25 | C7: 환율_기준일 E4(2026-08-31)
A8: B001 ar_balance_usd | B8: =ROUND(B5*B6/B7,2) -> 21026.82 | C8: 수식: ROUND(잔액 × EUR ÷ USD, 2) | D8: 확인표: 21,026.82
A9: 확인표 기대값(인쇄 d2-70) | B9: 21026.82
A10: 같음? | B10: =IF(ABS(B8-B9)<0.005,"같음","다름") -> 같음
A12: 내 CSV의 B001 ar_balance_usd(직접 적기 · 선택) | C12: =IF(B12="","",IF(ABS(B12-B8)<0.005,"엑셀과 같음","엑셀과 다름 — 어느 규칙에서 갈렸나?"))
A13: 직접 쳐 보기(선택 · 1분) | C13: 이 행의 흰 칸 B13에 =18100*1589.5/1368.25 를 칩니다
A15: B009 — 글자가 섞인 칸
A16: 원래 칸(글자) | B16: ='buyers_원본'!C10 -> CNY 317,000 | C16: buyers_원본 C10 — 수식으로는 숫자가 되지 않는다
A17: 사람이 읽은 숫자 | B17: 317000 | C17: 규칙 2칸: 통화 글자 · 쉼표를 지우고 숫자로(사람이 정한 규칙)
A18: 기준일 CNY 환율(원) | B18: ='환율_기준일'!E6 -> 203.62 | C18: 환율_기준일 E6
A19: B009 ar_balance_usd | B19: =ROUND(B17*B18/B7,2) -> 47175.25 | C19: 수식: ROUND(숫자 × CNY ÷ USD, 2) | D19: 47,175.25
A21: B072 — 단위 의심(잔액 > 신용한도 × 10)
A22: 원래 잔액 | B22: ='buyers_원본'!C73 -> 8320000 | C22: buyers_원본 C73 | D22: ='buyers_원본'!B73 -> euro
A23: 신용한도(USD) | B23: ='buyers_원본'!F73 -> 10000 | C23: buyers_원본 F73
A24: USD 환산(그대로) | B24: =ROUND(B22*B6/B7,2) -> 9665368.2 | C24: 수식: ROUND(잔액 × EUR ÷ USD, 2)
A25: 한도 × 10 | B25: =B23*10 -> 100000 | C25: 규칙 4칸의 기준
A26: 단위 의심? | B26: =IF(B24>B25,"단위 의심 → ÷1,000","정상") -> 단위 의심 → ÷1,000 | C26: 환산한 뒤 한도와 비교(통화가 다르면 환산 먼저)
A27: ÷1,000 후 ar_balance_usd | B27: =ROUND(B24/1000,2) -> 9665.37 | C27: 확인표: 9,665.37

Sheet 확인표_A
A1: 실습 A 확인표(슬라이드 d2-70)를 엑셀 수식으로
A2: 노란 칸 = 수식 · 회색 칸 = 인쇄된 기대값 · 흰 칸 = 내 CSV 값을 적는 칸(선택). 엑셀 값은 대체(채우기) 전 150행 기준입니다.
A4: 1. 통화 표기 9가지 → 표준 4종(대응표 = buyers_원본 N열의 VLOOKUP이 쓰는 표)
A5: 원래 표기 | B5: 표준 코드 | C5: 칸 수(대소문자 구분 — EXACT)
A6: USD | B6: USD | C6: =SUMPRODUCT(--EXACT('buyers_원본'!$B$2:$B$151,A6)) -> 81
A7: US$ | B7: USD | C7: =SUMPRODUCT(--EXACT('buyers_원본'!$B$2:$B$151,A7)) -> 15
A8: usd | B8: USD | C8: =SUMPRODUCT(--EXACT('buyers_원본'!$B$2:$B$151,A8)) -> 14
A9: EUR | B9: EUR | C9: =SUMPRODUCT(--EXACT('buyers_원본'!$B$2:$B$151,A9)) -> 18
A10: euro | B10: EUR | C10: =SUMPRODUCT(--EXACT('buyers_원본'!$B$2:$B$151,A10)) -> 5
A11: JPY | B11: JPY | C11: =SUMPRODUCT(--EXACT('buyers_원본'!$B$2:$B$151,A11)) -> 8
A12: yen | B12: JPY | C12: =SUMPRODUCT(--EXACT('buyers_원본'!$B$2:$B$151,A12)) -> 2
A13: CNY | B13: CNY | C13: =SUMPRODUCT(--EXACT('buyers_원본'!$B$2:$B$151,A13)) -> 5
A14: RMB | B14: CNY | C14: =SUMPRODUCT(--EXACT('buyers_원본'!$B$2:$B$151,A14)) -> 2
A15: 합계 | C15: =SUM(C6:C14) -> 150
A16: 표준 4종이 아닌 칸(정제 전) | C16: =C15-(C6+C9+C11+C13) -> 38
A18: 표준 코드 | B18: 바이어 수(수식) | C18: 확인표 기대값 | D18: 같음?
A19: USD | B19: =COUNTIF('buyers_원본'!$N$2:$N$151,A19) -> 110 | C19: 110 | D19: =IF(B19=C19,"같음","다름") -> 같음
A20: EUR | B20: =COUNTIF('buyers_원본'!$N$2:$N$151,A20) -> 23 | C20: 23 | D20: =IF(B20=C20,"같음","다름") -> 같음
A21: JPY | B21: =COUNTIF('buyers_원본'!$N$2:$N$151,A21) -> 10 | C21: 10 | D21: =IF(B21=C21,"같음","다름") -> 같음
A22: CNY | B22: =COUNTIF('buyers_원본'!$N$2:$N$151,A22) -> 7 | C22: 7 | D22: =IF(B22=C22,"같음","다름") -> 같음
A24: 2. 확인표 여섯 줄
A25: # | B25: 확인 | C25: 확인표 기대값(인쇄) | D25: 엑셀 검산(수식) | E25: 같음? | F25: 내 CSV 값(직접 적기 · 선택) | G25: 엑셀이 쓴 규칙
A26: 1 | B26: 통화 정리 | C26: USD 110 · EUR 23 · JPY 10 · CNY 7 | D26: ="USD "&B19&" · EUR "&B20&" · JPY "&B21&" · CNY "&B22 -> USD 110 · EUR 23 · JPY 10 · CNY 7 | E26: =IF(D26=C26,"같음","다름") -> 같음 | G26: 9가지 표기 → 4종(위 대응표)
A27: 2 | B27: B001 잔액(USD) | C27: 21026.82 | D27: ='B001_손계산'!B8 -> 21026.82 | E27: =IF(ABS(D27-C27)<0.005,"같음","다름") -> 같음 | G27: 기준일 2026-08-31 환율로 환산
A28: 3 | B28: 단위 의심 — 바이어 | C28: B072 | D28: =INDEX('buyers_원본'!$A$2:$A$151,MATCH(1,'buyers_원본'!$W$2:$W$151,0)) -> B072 | E28: =IF(D28=C28,"같음","다름") -> 같음 | G28: USD 환산 뒤 잔액 > 한도 × 10(글자 섞인 칸은 판정 안 함)
A29: 3 | B29: 단위 의심 — 곳 수(숫자 칸) | C29: 1 | D29: =SUM('buyers_원본'!$W$2:$W$151) -> 1 | E29: =IF(ABS(D29-C29)<0.5,"같음","다름") -> 같음
A30: 3 | B30: 단위 의심 — ÷1,000 후 USD | C30: 9665.37 | D30: ='B001_손계산'!B27 -> 9665.37 | E30: =IF(ABS(D30-C30)<0.005,"같음","다름") -> 같음
A31: 4 | B31: 자본잠식 — 곳 수 | C31: 2 | D31: =SUM('buyers_원본'!$Q$2:$Q$151) -> 2 | E31: =IF(ABS(D31-C31)<0.5,"같음","다름") -> 같음 | G31: 자기자본 ≤ 0 → 부채비율 빈칸
A32: 4 | B32: 자본잠식 — 첫째 | C32: B013 | D32: =INDEX('buyers_원본'!$A$2:$A$151,MATCH(1,'buyers_원본'!$X$2:$X$151,0)) -> B013 | E32: =IF(D32=C32,"같음","다름") -> 같음
A33: 4 | B33: 자본잠식 — 둘째 | C33: B048 | D33: =INDEX('buyers_원본'!$A$2:$A$151,MATCH(2,'buyers_원본'!$X$2:$X$151,0)) -> B048 | E33: =IF(D33=C33,"같음","다름") -> 같음
A34: 5 | B34: 결측 플래그 fin_missing | C34: 47 | D34: =SUM('buyers_원본'!$P$2:$P$151) -> 47 | E34: =IF(ABS(D34-C34)<0.5,"같음","다름") -> 같음 | G34: 유동자산·유동부채·총부채·자기자본·매출 중 하나라도 빈칸
A35: 5 | B35: 중앙값 current_ratio | C35: 1.4218 | D35: =ROUND(MEDIAN('buyers_원본'!$R$2:$R$151),4) -> 1.4218 | E35: =IF(ABS(D35-C35)<5e-05,"같음","다름") -> 같음 | G35: 대체 전 150행 · 빈칸 제외
A36: 5 | B36: 중앙값 debt_to_equity | C36: 1.4579 | D36: =ROUND(MEDIAN('buyers_원본'!$S$2:$S$151),4) -> 1.4579 | E36: =IF(ABS(D36-C36)<5e-05,"같음","다름") -> 같음 | G36: 자본잠식 2곳은 빈칸
A37: 5 | B37: 중앙값 dso_buyer | C37: 66.44 | D37: =ROUND(MEDIAN('buyers_원본'!$T$2:$T$151),2) -> 66.44 | E37: =IF(ABS(D37-C37)<0.005,"같음","다름") -> 같음 | G37: 매출채권 ÷ 매출 × 365
A38: 5 | B38: 중앙값 op_margin | C38: 0.0654 | D38: =ROUND(MEDIAN('buyers_원본'!$U$2:$U$151),4) -> 0.0654 | E38: =IF(ABS(D38-C38)<5e-05,"같음","다름") -> 같음 | G38: 영업이익 ÷ 매출
A39: 6 | B39: 기록 | C39: 테스트 통과 · 스케일 비교 표 · 커밋 2개+ · PR 1개(Closes #n) | D39: 엑셀로 보지 않는다 | G39: 터미널 uv run pytest -q · GitHub PR에서 확인
A41: 덧 | B41: 글자가 섞인 금액 칸(정제 전) | C41: 13 | D41: =SUM('buyers_원본'!$O$2:$O$151) -> 13 | E41: =IF(ABS(D41-C41)<0.5,"같음","다름") -> 같음 | G41: ar_balance 9 · ar_current 2 · ar_1_30 2 — 엑셀로는 사람이 하나씩 고쳐야 한다
B42: B009 ar_balance_usd(CNY 317,000) | C42: 47175.25 | D42: ='B001_손계산'!B19 -> 47175.25 | E42: =IF(ABS(D42-C42)<0.005,"같음","다름") -> 같음 | G42: 글자 섞인 칸 — 사람이 읽은 숫자로 계산(B001_손계산 시트)

Sheet 확인표_B
A1: 실습 B 확인표(슬라이드 d2-73) — 30일 창 (2026-08-01, 2026-08-31]의 기사 · 바이어 수
A2: d2_news.csv 앞 100행(실습 B가 채점하는 행)의 날짜로 셉니다. 점수 평균 · 평가 숫자는 사람마다 달라 엑셀로 보지 않습니다.
A4: 확인 | B4: 엑셀 검산(수식) | C4: 확인표 기대값 | D4: 같음? | E4: 내 결과(직접 적기 · 선택) | F4: 엑셀이 쓴 규칙
A5: 앞 100행의 가장 이른 날짜 | B5: =MIN('뉴스_앞100행'!$C$2:$C$101) -> 46195 | C5: 2026-06-22 | F5: 최신순 파일의 100번째 행
A6: 앞 100행의 가장 늦은 날짜 | B6: =MAX('뉴스_앞100행'!$C$2:$C$101) -> 46295 | C6: 2026-09-30
A7: 창 안 기사 수 | B7: =SUM('뉴스_앞100행'!$E$2:$E$101) -> 46 | C7: 46 | D7: =IF(ABS(B7-C7)<0.5,"같음","다름") -> 같음 | F7: date > 2026-08-01 이고 date ≤ 2026-08-31(8월 1일 빼고 31일 넣고)
A8: 창 안 바이어 수 | B8: =SUM('뉴스_앞100행'!$F$2:$F$101) -> 37 | C8: 37 | D8: =IF(ABS(B8-C8)<0.5,"같음","다름") -> 같음 | F8: 창 안 기사의 buyer_id 첫 등장만 센다
A9: 9월 기사(창 밖 — 특성에 들어가면 안 된다) | B9: =SUM('뉴스_앞100행'!$G$2:$G$101) -> 40 | C9: 40 | D9: =IF(ABS(B9-C9)<0.5,"같음","다름") -> 같음 | F9: 기준일 뒤 정보 — 특성표에는 0건이어야 한다
A10: 10월 이후 기사 | B10: =COUNTIF('뉴스_앞100행'!$C$2:$C$101,">"&DATE(2026,9,30)) -> 0 | C10: 0 | D10: =IF(ABS(B10-C10)<0.5,"같음","다름") -> 같음
A11: 뉴스 없는 바이어(150 − 창 안 바이어) | B11: =150-B8 -> 113 | C11: 113 | D11: =IF(ABS(B11-C11)<0.5,"같음","다름") -> 같음 | F11: LEFT JOIN 뒤 평균 5 + no_news_flag=1로 채운다
A12: B001 창 안 기사 수 | B12: =COUNTIFS('뉴스_앞100행'!$B$2:$B$101,"B001",'뉴스_앞100행'!$E$2:$E$101,1) -> 0 | C12: 0 | D12: =IF(ABS(B12-C12)<0.5,"같음","다름") -> 같음 | F12: 0건 → 평균 5.0 · no_news_flag 1
A14: 결합 뒤 행 수 | B14: 150(LEFT JOIN — 왼쪽 표 그대로) | F14: 150이 아니면 뉴스를 바이어별로 먼저 집계하지 않고 붙인 것(1:N)

Sheet buyers_원본
A1: buyer_id | B1: currency | C1: ar_balance | D1: ar_current | E1: ar_1_30 | F1: credit_limit_usd | G1: current_assets | H1: current_liabilities | I1: total_liabilities | J1: equity | K1: accounts_receivable | L1: revenue | M1: operating_income | N1: 통화_표준 | O1: 글자칸_수 | P1: fin_missing | Q1: neg_equity | R1: current_ratio | S1: debt_to_equity | T1: dso_buyer | U1: op_margin | V1: ar_balance_usd | W1: unit_flag | X1: neg_순번
A2: B001 | B2: EUR | C2: 18100 | D2: 18100 | E2: 0 | F2: 20000 | G2: 1618000 | H2: 992000 | I2: 1226000 | J2: 2041000 | K2: 652000 | L2: 6846000 | M2: 810000 | N2: =IFERROR(VLOOKUP(TRIM(B2),'확인표_A'!$A$6:$B$14,2,FALSE),"확인 필요") -> EUR | O2: =SUMPRODUCT(--ISTEXT(C2:E2)) -> 0 | P2: =IF(OR(G2="",H2="",I2="",J2="",L2=""),1,0) -> 0 | Q2: =IF(AND(J2<>"",J2<=0),1,0) -> 0 | R2: =IF(OR(G2="",H2=""),"",G2/H2) -> 1.6310484 | S2: =IF(OR(I2="",J2="",Q2=1),"",I2/J2) -> 0.60068594 | T2: =IF(OR(K2="",L2=""),"",K2/L2*365) -> 34.761905 | U2: =IF(OR(M2="",L2=""),"",M2/L2) -> 0.11831727 | V2: =IF(ISTEXT(C2),"글자 섞임",ROUND(C2*VLOOKUP(N2,'환율_기준일'!$A$4:$E$7,5,FALSE)/'환율_기준일'!$E$4,2)) -> 21026.82 | W2: =IF(ISNUMBER(V2),IF(V2>F2*10,1,0),"") -> 0 | X2: =IF(Q2=1,COUNTIF($Q$2:Q2,1),"")
A3: B002 | B3: usd | C3: 9170 | D3: 9170 | E3: 0 | F3: 20000 | G3: 2591000 | H3: 1462000 | I3: 2419000 | J3: 2364000 | K3: 935000 | L3: 8185000 | M3: 550000 | N3: =IFERROR(VLOOKUP(TRIM(B3),'확인표_A'!$A$6:$B$14,2,FALSE),"확인 필요") -> USD | O3: =SUMPRODUCT(--ISTEXT(C3:E3)) -> 0 | P3: =IF(OR(G3="",H3="",I3="",J3="",L3=""),1,0) -> 0 | Q3: =IF(AND(J3<>"",J3<=0),1,0) -> 0 | R3: =IF(OR(G3="",H3=""),"",G3/H3) -> 1.7722298 | S3: =IF(OR(I3="",J3="",Q3=1),"",I3/J3) -> 1.0232657 | T3: =IF(OR(K3="",L3=""),"",K3/L3*365) -> 41.695174 | U3: =IF(OR(M3="",L3=""),"",M3/L3) -> 0.06719609 | V3: =IF(ISTEXT(C3),"글자 섞임",ROUND(C3*VLOOKUP(N3,'환율_기준일'!$A$4:$E$7,5,FALSE)/'환율_기준일'!$E$4,2)) -> 9170 | W3: =IF(ISNUMBER(V3),IF(V3>F3*10,1,0),"") -> 0 | X3: =IF(Q3=1,COUNTIF($Q$2:Q3,1),"")
A4: B003 | B4: USD | C4: 0 | D4: 0 | E4: 0 | F4: 20000 | G4: 2451000 | H4: 1695000 | I4: 3638000 | K4: 1181000 | L4: 5343000 | M4: -278000 | N4: =IFERROR(VLOOKUP(TRIM(B4),'확인표_A'!$A$6:$B$14,2,FALSE),"확인 필요") -> USD | O4: =SUMPRODUCT(--ISTEXT(C4:E4)) -> 0 | P4: =IF(OR(G4="",H4="",I4="",J4="",L4=""),1,0) -> 1 | Q4: =IF(AND(J4<>"",J4<=0),1,0) -> 0 | R4: =IF(OR(G4="",H4=""),"",G4/H4) -> 1.4460177 | S4: =IF(OR(I4="",J4="",Q4=1),"",I4/J4) | T4: =IF(OR(K4="",L4=""),"",K4/L4*365) -> 80.678458 | U4: =IF(OR(M4="",L4=""),"",M4/L4) -> -0.052030694 | V4: =IF(ISTEXT(C4),"글자 섞임",ROUND(C4*VLOOKUP(N4,'환율_기준일'!$A$4:$E$7,5,FALSE)/'환율_기준일'!$E$4,2)) -> 0 | W4: =IF(ISNUMBER(V4),IF(V4>F4*10,1,0),"") -> 0 | X4: =IF(Q4=1,COUNTIF($Q$2:Q4,1),"")
A5: B004 | B5: USD | C5: 0 | D5: 0 | E5: 0 | F5: 10000 | G5: 18128000 | H5: 8321000 | I5: 15234000 | J5: 11515000 | K5: 6139000 | L5: 73932000 | M5: 5344000 | N5: =IFERROR(VLOOKUP(TRIM(B5),'확인표_A'!$A$6:$B$14,2,FALSE),"확인 필요") -> USD | O5: =SUMPRODUCT(--ISTEXT(C5:E5)) -> 0 | P5: =IF(OR(G5="",H5="",I5="",J5="",L5=""),1,0) -> 0 | Q5: =IF(AND(J5<>"",J5<=0),1,0) -> 0 | R5: =IF(OR(G5="",H5=""),"",G5/H5) -> 2.1785843 | S5: =IF(OR(I5="",J5="",Q5=1),"",I5/J5) -> 1.32297 | T5: =IF(OR(K5="",L5=""),"",K5/L5*365) -> 30.308053 | U5: =IF(OR(M5="",L5=""),"",M5/L5) -> 0.072282638 | V5: =IF(ISTEXT(C5),"글자 섞임",ROUND(C5*VLOOKUP(N5,'환율_기준일'!$A$4:$E$7,5,FALSE)/'환율_기준일'!$E$4,2)) -> 0 | W5: =IF(ISNUMBER(V5),IF(V5>F5*10,1,0),"") -> 0 | X5: =IF(Q5=1,COUNTIF($Q$2:Q5,1),"")
A6: B005 | B6: USD | C6: 195900 | D6: 173020 | E6: 22880 | F6: 200000 | G6: 51211000 | I6: 39364000 | J6: 40519000 | K6: 17583000 | L6: 204875000 | M6: 27396000 | N6: =IFERROR(VLOOKUP(TRIM(B6),'확인표_A'!$A$6:$B$14,2,FALSE),"확인 필요") -> USD | O6: =SUMPRODUCT(--ISTEXT(C6:E6)) -> 1 | P6: =IF(OR(G6="",H6="",I6="",J6="",L6=""),1,0) -> 1 | Q6: =IF(AND(J6<>"",J6<=0),1,0) -> 0 | R6: =IF(OR(G6="",H6=""),"",G6/H6) | S6: =IF(OR(I6="",J6="",Q6=1),"",I6/J6) -> 0.97149485 | T6: =IF(OR(K6="",L6=""),"",K6/L6*365) -> 31.325418 | U6: =IF(OR(M6="",L6=""),"",M6/L6) -> 0.13372056 | V6: =IF(ISTEXT(C6),"글자 섞임",ROUND(C6*VLOOKUP(N6,'환율_기준일'!$A$4:$E$7,5,FALSE)/'환율_기준일'!$E$4,2)) -> 글자 섞임 | W6: =IF(ISNUMBER(V6),IF(V6>F6*10,1,0),"") | X6: =IF(Q6=1,COUNTIF($Q$2:Q6,1),"")
A7: B006 | B7: USD | C7: 0 | D7: 0 | E7: 0 | F7: 10000 | N7: =IFERROR(VLOOKUP(TRIM(B7),'확인표_A'!$A$6:$B$14,2,FALSE),"확인 필요") -> USD | O7: =SUMPRODUCT(--ISTEXT(C7:E7)) -> 0 | P7: =IF(OR(G7="",H7="",I7="",J7="",L7=""),1,0) -> 1 | Q7: =IF(AND(J7<>"",J7<=0),1,0) -> 0 | R7: =IF(OR(G7="",H7=""),"",G7/H7) | S7: =IF(OR(I7="",J7="",Q7=1),"",I7/J7) | T7: =IF(OR(K7="",L7=""),"",K7/L7*365) | U7: =IF(OR(M7="",L7=""),"",M7/L7) | V7: =IF(ISTEXT(C7),"글자 섞임",ROUND(C7*VLOOKUP(N7,'환율_기준일'!$A$4:$E$7,5,FALSE)/'환율_기준일'!$E$4,2)) -> 0 | W7: =IF(ISNUMBER(V7),IF(V7>F7*10,1,0),"") -> 0 | X7: =IF(Q7=1,COUNTIF($Q$2:Q7,1),"")
A8: B007 | B8: EUR | C8: 2650 | D8: 2650 | E8: 0 | F8: 20000 | G8: 12383000 | H8: 5217000 | I8: 7416000 | J8: 15094000 | K8: 4161000 | L8: 27528000 | M8: 1737000 | N8: =IFERROR(VLOOKUP(TRIM(B8),'확인표_A'!$A$6:$B$14,2,FALSE),"확인 필요") -> EUR | O8: =SUMPRODUCT(--ISTEXT(C8:E8)) -> 0 | P8: =IF(OR(G8="",H8="",I8="",J8="",L8=""),1,0) -> 0 | Q8: =IF(AND(J8<>"",J8<=0),1,0) -> 0 | R8: =IF(OR(G8="",H8=""),"",G8/H8) -> 2.3735864 | S8: =IF(OR(I8="",J8="",Q8=1),"",I8/J8) -> 0.49132105 | T8: =IF(OR(K8="",L8=""),"",K8/L8*365) -> 55.171643 | U8: =IF(OR(M8="",L8=""),"",M8/L8) -> 0.06309939 | V8: =IF(ISTEXT(C8),"글자 섞임",ROUND(C8*VLOOKUP(N8,'환율_기준일'!$A$4:$E$7,5,FALSE)/'환율_기준일'!$E$4,2)) -> 3078.51 | W8: =IF(ISNUMBER(V8),IF(V8>F8*10,1,0),"") -> 0 | X8: =IF(Q8=1,COUNTIF($Q$2:Q8,1),"")
A9: B008 | B9: EUR | C9: 8080 | D9: 1230 | E9: 6,850 | F9: 10000 | G9: 4257000 | H9: 3189000 | I9: 5300000 | J9: 3217000 | K9: 2183000 | L9: 14083000 | M9: 1177000 | N9: =IFERROR(VLOOKUP(TRIM(B9),'확인표_A'!$A$6:$B$14,2,FALSE),"확인 필요") -> EUR | O9: =SUMPRODUCT(--ISTEXT(C9:E9)) -> 1 | P9: =IF(OR(G9="",H9="",I9="",J9="",L9=""),1,0) -> 0 | Q9: =IF(AND(J9<>"",J9<=0),1,0) -> 0 | R9: =IF(OR(G9="",H9=""),"",G9/H9) -> 1.3349012 | S9: =IF(OR(I9="",J9="",Q9=1),"",I9/J9) -> 1.6474977 | T9: =IF(OR(K9="",L9=""),"",K9/L9*365) -> 56.578499 | U9: =IF(OR(M9="",L9=""),"",M9/L9) -> 0.083575943 | V9: =IF(ISTEXT(C9),"글자 섞임",ROUND(C9*VLOOKUP(N9,'환율_기준일'!$A$4:$E$7,5,FALSE)/'환율_기준일'!$E$4,2)) -> 9386.56 | W9: =IF(ISNUMBER(V9),IF(V9>F9*10,1,0),"") -> 0 | X9: =IF(Q9=1,COUNTIF($Q$2:Q9,1),"")
A10: B009 | B10: CNY | C10: CNY 317,000 | D10: 317000 | E10: 0 | F10: 60000 | G10: 10718000 | H10: 10331000 | I10: 17835000 | J10: 3095000 | K10: 5644000 | L10: 25116000 | M10: 593000 | N10: =IFERROR(VLOOKUP(TRIM(B10),'확인표_A'!$A$6:$B$14,2,FALSE),"확인 필요") -> CNY | O10: =SUMPRODUCT(--ISTEXT(C10:E10)) -> 1 | P10: =IF(OR(G10="",H10="",I10="",J10="",L10=""),1,0) -> 0 | Q10: =IF(AND(J10<>"",J10<=0),1,0) -> 0 | R10: =IF(OR(G10="",H10=""),"",G10/H10) -> 1.0374601 | S10: =IF(OR(I10="",J10="",Q10=1),"",I10/J10) -> 5.7625202 | T10: =IF(OR(K10="",L10=""),"",K10/L10*365) -> 82.021819 | U10: =IF(OR(M10="",L10=""),"",M10/L10) -> 0.023610448 | V10: =IF(ISTEXT(C10),"글자 섞임",ROUND(C10*VLOOKUP(N10,'환율_기준일'!$A$4:$E$7,5,FALSE)/'환율_기준일'!$E$4,2)) -> 글자 섞임 | W10: =IF(ISNUMBER(V10),IF(V10>F10*10,1,0),"") | X10: =IF(Q10=1,COUNTIF($Q$2:Q10,1),"")
A11: B010 | B11: EUR | C11: 0 | D11: 0 | E11: 0 | F11: 10000 | G11: 2497000 | H11: 2165000 | I11: 3623000 | J11: 1311000 | K11: 1151000 | L11: 5926000 | M11: 21000 | N11: =IFERROR(VLOOKUP(TRIM(B11),'확인표_A'!$A$6:$B$14,2,FALSE),"확인 필요") -> EUR | O11: =SUMPRODUCT(--ISTEXT(C11:E11)) -> 0 | P11: =IF(OR(G11="",H11="",I11="",J11="",L11=""),1,0) -> 0 | Q11: =IF(AND(J11<>"",J11<=0),1,0) -> 0 | R11: =IF(OR(G11="",H11=""),"",G11/H11) -> 1.1533487 | S11: =IF(OR(I11="",J11="",Q11=1),"",I11/J11) -> 2.7635393 | T11: =IF(OR(K11="",L11=""),"",K11/L11*365) -> 70.89352 | U11: =IF(OR(M11="",L11=""),"",M11/L11) -> 0.0035437057 | V11: =IF(ISTEXT(C11),"글자 섞임",ROUND(C11*VLOOKUP(N11,'환율_기준일'!$A$4:$E$7,5,FALSE)/'환율_기준일'!$E$4,2)) -> 0 | W11: =IF(ISNUMBER(V11),IF(V11>F11*10,1,0),"") -> 0 | X11: =IF(Q11=1,COUNTIF($Q$2:Q11,1),"")
A12: B011 | B12: USD | C12: 0 | D12: 0 | E12: 0 | F12: 10000 | G12: 5142000 | H12: 4346000 | I12: 5716000 | J12: 1183000 | L12: 7731000 | N12: =IFERROR(VLOOKUP(TRIM(B12),'확인표_A'!$A$6:$B$14,2,FALSE),"확인 필요") -> USD | O12: =SUMPRODUCT(--ISTEXT(C12:E12)) -> 0 | P12: =IF(OR(G12="",H12="",I12="",J12="",L12=""),1,0) -> 0 | Q12: =IF(AND(J12<>"",J12<=0),1,0) -> 0 | R12: =IF(OR(G12="",H12=""),"",G12/H12) -> 1.1831569 | S12: =IF(OR(I12="",J12="",Q12=1),"",I12/J12) -> 4.8317836 | T12: =IF(OR(K12="",L12=""),"",K12/L12*365) | U12: =IF(OR(M12="",L12=""),"",M12/L12) | V12: =IF(ISTEXT(C12),"글자 섞임",ROUND(C12*VLOOKUP(N12,'환율_기준일'!$A$4:$E$7,5,FALSE)/'환율_기준일'!$E$4,2)) -> 0 | W12: =IF(ISNUMBER(V12),IF(V12>F12*10,1,0),"") -> 0 | X12: =IF(Q12=1,COUNTIF($Q$2:Q12,1),"")
A13: B012 | B13: USD | C13: 0 | D13: 0 | E13: 0 | F13: 10000 | G13: 11541000 | H13: 12002000 | I13: 19711000 | J13: 7448000 | L13: 10451000 | M13: -1021000 | N13: =IFERROR(VLOOKUP(TRIM(B13),'확인표_A'!$A$6:$B$14,2,FALSE),"확인 필요") -> USD | O13: =SUMPRODUCT(--ISTEXT(C13:E13)) -> 0 | P13: =IF(OR(G13="",H13="",I13="",J13="",L13=""),1,0) -> 0 | Q13: =IF(AND(J13<>"",J13<=0),1,0) -> 0 | R13: =IF(OR(G13="",H13=""),"",G13/H13) -> 0.96158974 | S13: =IF(OR(I13="",J13="",Q13=1),"",I13/J13) -> 2.6464823 | T13: =IF(OR(K13="",L13=""),"",K13/L13*365) | U13: =IF(OR(M13="",L13=""),"",M13/L13) -> -0.097694001 | V13: =IF(ISTEXT(C13),"글자 섞임",ROUND(C13*VLOOKUP(N13,'환율_기준일'!$A$4:$E$7,5,FALSE)/'환율_기준일'!$E$4,2)) -> 0 | W13: =IF(ISNUMBER(V13),IF(V13>F13*10,1,0),"") -> 0 | X13: =IF(Q13=1,COUNTIF($Q$2:Q13,1),"")
A14: B013 | B14: USD | C14: 0 | D14: 0 | E14: 0 | F14: 20000 | G14: 22496000 | H14: 62489000 | I14: 109262000 | J14: -15126000 | K14: 10957000 | L14: 46504000 | M14: -11565000 | N14: =IFERROR(VLOOKUP(TRIM(B14),'확인표_A'!$A$6:$B$14,2,FALSE),"확인 필요") -> USD | O14: =SUMPRODUCT(--ISTEXT(C14:E14)) -> 0 | P14: =IF(OR(G14="",H14="",I14="",J14="",L14=""),1,0) -> 0 | Q14: =IF(AND(J14<>"",J14<=0),1,0) -> 1 | R14: =IF(OR(G14="",H14=""),"",G14/H14) -> 0.35999936 | S14: =IF(OR(I14="",J14="",Q14=1),"",I14/J14) | T14: =IF(OR(K14="",L14=""),"",K14/L14*365) -> 85.999161 | U14: =IF(OR(M14="",L14=""),"",M14/L14) -> -0.24868828 | V14: =IF(ISTEXT(C14),"글자 섞임",ROUND(C14*VLOOKUP(N14,'환율_기준일'!$A$4:$E$7,5,FALSE)/'환율_기준일'!$E$4,2)) -> 0 | W14: =IF(ISNUMBER(V14),IF(V14>F14*10,1,0),"") -> 0 | X14: =IF(Q14=1,COUNTIF($Q$2:Q14,1),"") -> 1
A15: B014 | B15: USD | C15: 29910 | D15: 29910 | E15: 0 | F15: 50000 | G15: 47876000 | H15: 28567000 | I15: 39898000 | J15: 71277000 | K15: 20957000 | L15: 148025000 | M15: 11168000 | N15: =IFERROR(VLOOKUP(TRIM(B15),'확인표_A'!$A$6:$B$14,2,FALSE),"확인 필요") -> USD | O15: =SUMPRODUCT(--ISTEXT(C15:E15)) -> 0 | P15: =IF(OR(G15="",H15="",I15="",J15="",L15=""),1,0) -> 0 | Q15: =IF(AND(J15<>"",J15<=0),1,0) -> 0 | R15: =IF(OR(G15="",H15=""),"",G15/H15) -> 1.6759198 | S15: =IF(OR(I15="",J15="",Q15=1),"",I15/J15) -> 0.55975981 | T15: =IF(OR(K15="",L15=""),"",K15/L15*365) -> 51.675764 | U15: =IF(OR(M15="",L15=""),"",M15/L15) -> 0.075446715 | V15: =IF(ISTEXT(C15),"글자 섞임",ROUND(C15*VLOOKUP(N15,'환율_기준일'!$A$4:$E$7,5,FALSE)/'환율_기준일'!$E$4,2)) -> 29910 | W15: =IF(ISNUMBER(V15),IF(V15>F15*10,1,0),"") -> 0 | X15: =IF(Q15=1,COUNTIF($Q$2:Q15,1),"")
A16: B015 | B16: USD | C16: 7,680 | D16: 7680 | E16: 0 | F16: 20000 | G16: 5353000 | H16: 3765000 | I16: 8130000 | J16: 8104000 | K16: 2203000 | L16: 16500000 | M16: 564000 | N16: =IFERROR(VLOOKUP(TRIM(B16),'확인표_A'!$A$6:$B$14,2,FALSE),"확인 필요") -> USD | O16: =SUMPRODUCT(--ISTEXT(C16:E16)) -> 1 | P16: =IF(OR(G16="",H16="",I16="",J16="",L16=""),1,0) -> 0 | Q16: =IF(AND(J16<>"",J16<=0),1,0) -> 0 | R16: =IF(OR(G16="",H16=""),"",G16/H16) -> 1.4217795 | S16: =IF(OR(I16="",J16="",Q16=1),"",I16/J16) -> 1.0032083 | T16: =IF(OR(K16="",L16=""),"",K16/L16*365) -> 48.73303 | U16: =IF(OR(M16="",L16=""),"",M16/L16) -> 0.034181818 | V16: =IF(ISTEXT(C16),"글자 섞임",ROUND(C16*VLOOKUP(N16,'환율_기준일'!$A$4:$E$7,5,FALSE)/'환율_기준일'!$E$4,2)) -> 글자 섞임 | W16: =IF(ISNUMBER(V16),IF(V16>F16*10,1,0),"") | X16: =IF(Q16=1,COUNTIF($Q$2:Q16,1),"")
A17: B016 | B17: USD | C17: 0 | D17: 0 | E17: 0 | F17: 10000 | N17: =IFERROR(VLOOKUP(TRIM(B17),'확인표_A'!$A$6:$B$14,2,FALSE),"확인 필요") -> USD | O17: =SUMPRODUCT(--ISTEXT(C17:E17)) -> 0 | P17: =IF(OR(G17="",H17="",I17="",J17="",L17=""),1,0) -> 1 | Q17: =IF(AND(J17<>"",J17<=0),1,0) -> 0 | R17: =IF(OR(G17="",H17=""),"",G17/H17) | S17: =IF(OR(I17="",J17="",Q17=1),"",I17/J17) | T17: =IF(OR(K17="",L17=""),"",K17/L17*365) | U17: =IF(OR(M17="",L17=""),"",M17/L17) | V17: =IF(ISTEXT(C17),"글자 섞임",ROUND(C17*VLOOKUP(N17,'환율_기준일'!$A$4:$E$7,5,FALSE)/'환율_기준일'!$E$4,2)) -> 0 | W17: =IF(ISNUMBER(V17),IF(V17>F17*10,1,0),"") -> 0 | X17: =IF(Q17=1,COUNTIF($Q$2:Q17,1),"")
A18: B017 | B18: USD | C18: 0 | D18: 0 | E18: 0 | F18: 10000 | G18: 2309000 | H18: 1979000 | I18: 4148000 | J18: 4861000 | K18: 996000 | L18: 5495000 | N18: =IFERROR(VLOOKUP(TRIM(B18),'확인표_A'!$A$6:$B$14,2,FALSE),"확인 필요") -> USD | O18: =SUMPRODUCT(--ISTEXT(C18:E18)) -> 0 | P18: =IF(OR(G18="",H18="",I18="",J18="",L18=""),1,0) -> 0 | Q18: =IF(AND(J18<>"",J18<=0),1,0) -> 0 | R18: =IF(OR(G18="",H18=""),"",G18/H18) -> 1.1667509 | S18: =IF(OR(I18="",J18="",Q18=1),"",I18/J18) -> 0.85332236 | T18: =IF(OR(K18="",L18=""),"",K18/L18*365) -> 66.158326 | U18: =IF(OR(M18="",L18=""),"",M18/L18) | V18: =IF(ISTEXT(C18),"글자 섞임",ROUND(C18*VLOOKUP(N18,'환율_기준일'!$A$4:$E$7,5,FALSE)/'환율_기준일'!$E$4,2)) -> 0 | W18: =IF(ISNUMBER(V18),IF(V18>F18*10,1,0),"") -> 0 | X18: =IF(Q18=1,COUNTIF($Q$2:Q18,1),"")
A19: B018 | B19: EUR | C19: 0 | D19: 0 | E19: 0 | F19: 20000 | G19: 17484000 | H19: 11417000 | I19: 24384000 | J19: 13466000 | K19: 6098000 | L19: 31866000 | M19: -634000 | N19: =IFERROR(VLOOKUP(TRIM(B19),'확인표_A'!$A$6:$B$14,2,FALSE),"확인 필요") -> EUR | O19: =SUMPRODUCT(--ISTEXT(C19:E19)) -> 0 | P19: =IF(OR(G19="",H19="",I19="",J19="",L19=""),1,0) -> 0 | Q19: =IF(AND(J19<>"",J19<=0),1,0) -> 0 | R19: =IF(OR(G19="",H19=""),"",G19/H19) -> 1.5314005 | S19: =IF(OR(I19="",J19="",Q19=1),"",I19/J19) -> 1.8107827 | T19: =IF(OR(K19="",L19=""),"",K19/L19*365) -> 69.8478 | U19: =IF(OR(M19="",L19=""),"",M19/L19) -> -0.019895814 | V19: =IF(ISTEXT(C19),"글자 섞임",ROUND(C19*VLOOKUP(N19,'환율_기준일'!$A$4:$E$7,5,FALSE)/'환율_기준일'!$E$4,2)) -> 0 | W19: =IF(ISNUMBER(V19),IF(V19>F19*10,1,0),"") -> 0 | X19: =IF(Q19=1,COUNTIF($Q$2:Q19,1),"")
A20: B019 | B20: USD | C20: 12250 | D20: 12250 | E20: 0 | F20: 20000 | G20: 4111000 | H20: 2178000 | I20: 3133000 | J20: 2524000 | L20: 13268000 | M20: 1653000 | N20: =IFERROR(VLOOKUP(TRIM(B20),'확인표_A'!$A$6:$B$14,2,FALSE),"확인 필요") -> USD | O20: =SUMPRODUCT(--ISTEXT(C20:E20)) -> 0 | P20: =IF(OR(G20="",H20="",I20="",J20="",L20=""),1,0) -> 0 | Q20: =IF(AND(J20<>"",J20<=0),1,0) -> 0 | R20: =IF(OR(G20="",H20=""),"",G20/H20) -> 1.8875115 | S20: =IF(OR(I20="",J20="",Q20=1),"",I20/J20) -> 1.2412837 | T20: =IF(OR(K20="",L20=""),"",K20/L20*365) | U20: =IF(OR(M20="",L20=""),"",M20/L20) -> 0.12458547 | V20: =IF(ISTEXT(C20),"글자 섞임",ROUND(C20*VLOOKUP(N20,'환율_기준일'!$A$4:$E$7,5,FALSE)/'환율_기준일'!$E$4,2)) -> 12250 | W20: =IF(ISNUMBER(V20),IF(V20>F20*10,1,0),"") -> 0 | X20: =IF(Q20=1,COUNTIF($Q$2:Q20,1),"")
A21: B020 | B21: USD | C21: 0 | D21: 0 | E21: 0 | F21: 10000 | G21: 10263000 | H21: 8905000 | I21: 17416000 | J21: 3369000 | K21: 4723000 | L21: 16153000 | M21: -1021000 | N21: =IFERROR(VLOOKUP(TRIM(B21),'확인표_A'!$A$6:$B$14,2,FALSE),"확인 필요") -> USD | O21: =SUMPRODUCT(--ISTEXT(C21:E21)) -> 0 | P21: =IF(OR(G21="",H21="",I21="",J21="",L21=""),1,0) -> 0 | Q21: =IF(AND(J21<>"",J21<=0),1,0) -> 0 | R21: =IF(OR(G21="",H21=""),"",G21/H21) -> 1.1524986 | S21: =IF(OR(I21="",J21="",Q21=1),"",I21/J21) -> 5.1694865 | T21: =IF(OR(K21="",L21=""),"",K21/L21*365) -> 106.7229 | U21: =IF(OR(M21="",L21=""),"",M21/L21) -> -0.063208073 | V21: =IF(ISTEXT(C21),"글자 섞임",ROUND(C21*VLOOKUP(N21,'환율_기준일'!$A$4:$E$7,5,FALSE)/'환율_기준일'!$E$4,2)) -> 0 | W21: =IF(ISNUMBER(V21),IF(V21>F21*10,1,0),"") -> 0 | X21: =IF(Q21=1,COUNTIF($Q$2:Q21,1),"")
A22: B021 | B22: CNY | C22: 427100 | D22: 427100 | E22: 0 | F22: 30000 | G22: 21871000 | H22: 17090000 | I22: 25868000 | J22: 31185000 | L22: 49384000 | M22: 2135000 | N22: =IFERROR(VLOOKUP(TRIM(B22),'확인표_A'!$A$6:$B$14,2,FALSE),"확인 필요") -> CNY | O22: =SUMPRODUCT(--ISTEXT(C22:E22)) -> 0 | P22: =IF(OR(G22="",H22="",I22="",J22="",L22=""),1,0) -> 0 | Q22: =IF(AND(J22<>"",J22<=0),1,0) -> 0 | R22: =IF(OR(G22="",H22=""),"",G22/H22) -> 1.2797542 | S22: =IF(OR(I22="",J22="",Q22=1),"",I22/J22) -> 0.82950136 | T22: =IF(OR(K22="",L22=""),"",K22/L22*365) | U22: =IF(OR(M22="",L22=""),"",M22/L22) -> 0.043232626 | V22: =IF(ISTEXT(C22),"글자 섞임",ROUND(C22*VLOOKUP(N22,'환율_기준일'!$A$4:$E$7,5,FALSE)/'환율_기준일'!$E$4,2)) -> 63560.1 | W22: =IF(ISNUMBER(V22),IF(V22>F22*10,1,0),"") -> 0 | X22: =IF(Q22=1,COUNTIF($Q$2:Q22,1),"")
A23: B022 | B23: US$ | C23: 95880 | D23: 91550 | E23: 4330 | F23: 50000 | G23: 36497000 | H23: 26854000 | I23: 32891000 | J23: 26270000 | K23: 16634000 | L23: 169300000 | M23: 14692000 | N23: =IFERROR(VLOOKUP(TRIM(B23),'확인표_A'!$A$6:$B$14,2,FALSE),"확인 필요") -> USD | O23: =SUMPRODUCT(--ISTEXT(C23:E23)) -> 0 | P23: =IF(OR(G23="",H23="",I23="",J23="",L23=""),1,0) -> 0 | Q23: =IF(AND(J23<>"",J23<=0),1,0) -> 0 | R23: =IF(OR(G23="",H23=""),"",G23/H23) -> 1.3590899 | S23: =IF(OR(I23="",J23="",Q23=1),"",I23/J23) -> 1.2520365 | T23: =IF(OR(K23="",L23=""),"",K23/L23*365) -> 35.861843 | U23: =IF(OR(M23="",L23=""),"",M23/L23) -> 0.086780862 | V23: =IF(ISTEXT(C23),"글자 섞임",ROUND(C23*VLOOKUP(N23,'환율_기준일'!$A$4:$E$7,5,FALSE)/'환율_기준일'!$E$4,2)) -> 95880 | W23: =IF(ISNUMBER(V23),IF(V23>F23*10,1,0),"") -> 0 | X23: =IF(Q23=1,COUNTIF($Q$2:Q23,1),"")
A24: B023 | B24: USD | C24: 26500 | D24: 22410 | E24: 4090 | F24: 50000 | N24: =IFERROR(VLOOKUP(TRIM(B24),'확인표_A'!$A$6:$B$14,2,FALSE),"확인 필요") -> USD | O24: =SUMPRODUCT(--ISTEXT(C24:E24)) -> 0 | P24: =IF(OR(G24="",H24="",I24="",J24="",L24=""),1,0) -> 1 | Q24: =IF(AND(J24<>"",J24<=0),1,0) -> 0 | R24: =IF(OR(G24="",H24=""),"",G24/H24) | S24: =IF(OR(I24="",J24="",Q24=1),"",I24/J24) | T24: =IF(OR(K24="",L24=""),"",K24/L24*365) | U24: =IF(OR(M24="",L24=""),"",M24/L24) | V24: =IF(ISTEXT(C24),"글자 섞임",ROUND(C24*VLOOKUP(N24,'환율_기준일'!$A$4:$E$7,5,FALSE)/'환율_기준일'!$E$4,2)) -> 26500 | W24: =IF(ISNUMBER(V24),IF(V24>F24*10,1,0),"") -> 0 | X24: =IF(Q24=1,COUNTIF($Q$2:Q24,1),"")
A25: B024 | B25: usd | C25: 10080 | D25: 10080 | E25: 0 | F25: 10000 | G25: 5546000 | H25: 4851000 | I25: 9481000 | J25: 3648000 | K25: 2394000 | L25: 10854000 | M25: 940000 | N25: =IFERROR(VLOOKUP(TRIM(B25),'확인표_A'!$A$6:$B$14,2,FALSE),"확인 필요") -> USD | O25: =SUMPRODUCT(--ISTEXT(C25:E25)) -> 0 | P25: =IF(OR(G25="",H25="",I25="",J25="",L25=""),1,0) -> 0 | Q25: =IF(AND(J25<>"",J25<=0),1,0) -> 0 | R25: =IF(OR(G25="",H25=""),"",G25/H25) -> 1.1432694 | S25: =IF(OR(I25="",J25="",Q25=1),"",I25/J25) -> 2.5989583 | T25: =IF(OR(K25="",L25=""),"",K25/L25*365) -> 80.505804 | U25: =IF(OR(M25="",L25=""),"",M25/L25) -> 0.086604017 | V25: =IF(ISTEXT(C25),"글자 섞임",ROUND(C25*VLOOKUP(N25,'환율_기준일'!$A$4:$E$7,5,FALSE)/'환율_기준일'!$E$4,2)) -> 10080 | W25: =IF(ISNUMBER(V25),IF(V25>F25*10,1,0),"") -> 0 | X25: =IF(Q25=1,COUNTIF($Q$2:Q25,1),"")
A26: B025 | B26: EUR | C26: 1370 | D26: 1370 | E26: 0 | F26: 10000 | G26: 1880000 | H26: 886000 | I26: 1657000 | J26: 2343000 | K26: 872000 | L26: 5387000 | N26: =IFERROR(VLOOKUP(TRIM(B26),'확인표_A'!$A$6:$B$14,2,FALSE),"확인 필요") -> EUR | O26: =SUMPRODUCT(--ISTEXT(C26:E26)) -> 0 | P26: =IF(OR(G26="",H26="",I26="",J26="",L26=""),1,0) -> 0 | Q26: =IF(AND(J26<>"",J26<=0),1,0) -> 0 | R26: =IF(OR(G26="",H26=""),"",G26/H26) -> 2.1218962 | S26: =IF(OR(I26="",J26="",Q26=1),"",I26/J26) -> 0.70721297 | T26: =IF(OR(K26="",L26=""),"",K26/L26*365) -> 59.082978 | U26: =IF(OR(M26="",L26=""),"",M26/L26) | V26: =IF(ISTEXT(C26),"글자 섞임",ROUND(C26*VLOOKUP(N26,'환율_기준일'!$A$4:$E$7,5,FALSE)/'환율_기준일'!$E$4,2)) -> 1591.53 | W26: =IF(ISNUMBER(V26),IF(V26>F26*10,1,0),"") -> 0 | X26: =IF(Q26=1,COUNTIF($Q$2:Q26,1),"")
A27: B026 | B27: US$ | C27: 50120 | D27: 50120 | E27: 0 | F27: 60000 | N27: =IFERROR(VLOOKUP(TRIM(B27),'확인표_A'!$A$6:$B$14,2,FALSE),"확인 필요") -> USD | O27: =SUMPRODUCT(--ISTEXT(C27:E27)) -> 0 | P27: =IF(OR(G27="",H27="",I27="",J27="",L27=""),1,0) -> 1 | Q27: =IF(AND(J27<>"",J27<=0),1,0) -> 0 | R27: =IF(OR(G27="",H27=""),"",G27/H27) | S27: =IF(OR(I27="",J27="",Q27=1),"",I27/J27) | T27: =IF(OR(K27="",L27=""),"",K27/L27*365) | U27: =IF(OR(M27="",L27=""),"",M27/L27) | V27: =IF(ISTEXT(C27),"글자 섞임",ROUND(C27*VLOOKUP(N27,'환율_기준일'!$A$4:$E$7,5,FALSE)/'환율_기준일'!$E$4,2)) -> 50120 | W27: =IF(ISNUMBER(V27),IF(V27>F27*10,1,0),"") -> 0 | X27: =IF(Q27=1,COUNTIF($Q$2:Q27,1),"")
A28: B027 | B28: USD | C28: 0 | D28: 0 | E28: 0 | F28: 10000 | N28: =IFERROR(VLOOKUP(TRIM(B28),'확인표_A'!$A$6:$B$14,2,FALSE),"확인 필요") -> USD | O28: =SUMPRODUCT(--ISTEXT(C28:E28)) -> 0 | P28: =IF(OR(G28="",H28="",I28="",J28="",L28=""),1,0) -> 1 | Q28: =IF(AND(J28<>"",J28<=0),1,0) -> 0 | R28: =IF(OR(G28="",H28=""),"",G28/H28) | S28: =IF(OR(I28="",J28="",Q28=1),"",I28/J28) | T28: =IF(OR(K28="",L28=""),"",K28/L28*365) | U28: =IF(OR(M28="",L28=""),"",M28/L28) | V28: =IF(ISTEXT(C28),"글자 섞임",ROUND(C28*VLOOKUP(N28,'환율_기준일'!$A$4:$E$7,5,FALSE)/'환율_기준일'!$E$4,2)) -> 0 | W28: =IF(ISNUMBER(V28),IF(V28>F28*10,1,0),"") -> 0 | X28: =IF(Q28=1,COUNTIF($Q$2:Q28,1),"")
A29: B028 | B29: JPY | C29: 32072000 | D29: 32072000 | E29: 0 | F29: 170000 | G29: 48811000 | H29: 28084000 | I29: 38949000 | J29: 69738000 | K29: 16800000 | L29: 160688000 | M29: 22088000 | N29: =IFERROR(VLOOKUP(TRIM(B29),'확인표_A'!$A$6:$B$14,2,FALSE),"확인 필요") -> JPY | O29: =SUMPRODUCT(--ISTEXT(C29:E29)) -> 0 | P29: =IF(OR(G29="",H29="",I29="",J29="",L29=""),1,0) -> 0 | Q29: =IF(AND(J29<>"",J29<=0),1,0) -> 0 | R29: =IF(OR(G29="",H29=""),"",G29/H29) -> 1.7380359 | S29: =IF(OR(I29="",J29="",Q29=1),"",I29/J29) -> 0.55850469 | T29: =IF(OR(K29="",L29=""),"",K29/L29*365) -> 38.160908 | U29: =IF(OR(M29="",L29=""),"",M29/L29) -> 0.13745893 | V29: =IF(ISTEXT(C29),"글자 섞임",ROUND(C29*VLOOKUP(N29,'환율_기준일'!$A$4:$E$7,5,FALSE)/'환율_기준일'!$E$4,2)) -> 200776.7 | W29: =IF(ISNUMBER(V29),IF(V29>F29*10,1,0),"") -> 0 | X29: =IF(Q29=1,COUNTIF($Q$2:Q29,1),"")
A30: B029 | B30: usd | C30: 60187.68 | D30: 34010 | E30: 5170 | F30: 100000 | G30: 289083000 | H30: 232878000 | I30: 327268000 | J30: 150008000 | K30: 103981000 | L30: 437297000 | M30: 44755000 | N30: =IFERROR(VLOOKUP(TRIM(B30),'확인표_A'!$A$6:$B$14,2,FALSE),"확인 필요") -> USD | O30: =SUMPRODUCT(--ISTEXT(C30:E30)) -> 0 | P30: =IF(OR(G30="",H30="",I30="",J30="",L30=""),1,0) -> 0 | Q30: =IF(AND(J30<>"",J30<=0),1,0) -> 0 | R30: =IF(OR(G30="",H30=""),"",G30/H30) -> 1.2413495 | S30: =IF(OR(I30="",J30="",Q30=1),"",I30/J30) -> 2.1816703 | T30: =IF(OR(K30="",L30=""),"",K30/L30*365) -> 86.790133 | U30: =IF(OR(M30="",L30=""),"",M30/L30) -> 0.10234463 | V30: =IF(ISTEXT(C30),"글자 섞임",ROUND(C30*VLOOKUP(N30,'환율_기준일'!$A$4:$E$7,5,FALSE)/'환율_기준일'!$E$4,2)) -> 60187.68 | W30: =IF(ISNUMBER(V30),IF(V30>F30*10,1,0),"") -> 0 | X30: =IF(Q30=1,COUNTIF($Q$2:Q30,1),"")
A31: B030 | B31: USD | C31: 21030 | D31: 21030 | E31: 0 | F31: 40000 | G31: 31198000 | H31: 42853000 | I31: 81042000 | K31: 12859000 | L31: 45005000 | M31: -3711000 | N31: =IFERROR(VLOOKUP(TRIM(B31),'확인표_A'!$A$6:$B$14,2,FALSE),"확인 필요") -> USD | O31: =SUMPRODUCT(--ISTEXT(C31:E31)) -> 0 | P31: =IF(OR(G31="",H31="",I31="",J31="",L31=""),1,0) -> 1 | Q31: =IF(AND(J31<>"",J31<=0),1,0) -> 0 | R31: =IF(OR(G31="",H31=""),"",G31/H31) -> 0.72802371 | S31: =IF(OR(I31="",J31="",Q31=1),"",I31/J31) | T31: =IF(OR(K31="",L31=""),"",K31/L31*365) -> 104.28919 | U31: =IF(OR(M31="",L31=""),"",M31/L31) -> -0.082457505 | V31: =IF(ISTEXT(C31),"글자 섞임",ROUND(C31*VLOOKUP(N31,'환율_기준일'!$A$4:$E$7,5,FALSE)/'환율_기준일'!$E$4,2)) -> 21030 | W31: =IF(ISNUMBER(V31),IF(V31>F31*10,1,0),"") -> 0 | X31: =IF(Q31=1,COUNTIF($Q$2:Q31,1),"")
A32: B031 | B32: USD | C32: 59690 | D32: 40490 | E32: 14930 | F32: 50000 | G32: 116791000 | I32: 112408000 | K32: 40333000 | L32: 243199000 | M32: 18357000 | N32: =IFERROR(VLOOKUP(TRIM(B32),'확인표_A'!$A$6:$B$14,2,FALSE),"확인 필요") -> USD | O32: =SUMPRODUCT(--ISTEXT(C32:E32)) -> 0 | P32: =IF(OR(G32="",H32="",I32="",J32="",L32=""),1,0) -> 1 | Q32: =IF(AND(J32<>"",J32<=0),1,0) -> 0 | R32: =IF(OR(G32="",H32=""),"",G32/H32) | S32: =IF(OR(I32="",J32="",Q32=1),"",I32/J32) | T32: =IF(OR(K32="",L32=""),"",K32/L32*365) -> 60.532917 | U32: =IF(OR(M32="",L32=""),"",M32/L32) -> 0.075481396 | V32: =IF(ISTEXT(C32),"글자 섞임",ROUND(C32*VLOOKUP(N32,'환율_기준일'!$A$4:$E$7,5,FALSE)/'환율_기준일'!$E$4,2)) -> 59690 | W32: =IF(ISNUMBER(V32),IF(V32>F32*10,1,0),"") -> 0 | X32: =IF(Q32=1,COUNTIF($Q$2:Q32,1),"")
A33: B032 | B33: USD | C33: 18070 | D33: 18070 | E33: 0 | F33: 10000 | G33: 90449000 | I33: 108506000 | J33: 57139000 | L33: 138829000 | N33: =IFERROR(VLOOKUP(TRIM(B33),'확인표_A'!$A$6:$B$14,2,FALSE),"확인 필요") -> USD | O33: =SUMPRODUCT(--ISTEXT(C33:E33)) -> 0 | P33: =IF(OR(G33="",H33="",I33="",J33="",L33=""),1,0) -> 1 | Q33: =IF(AND(J33<>"",J33<=0),1,0) -> 0 | R33: =IF(OR(G33="",H33=""),"",G33/H33) | S33: =IF(OR(I33="",J33="",Q33=1),"",I33/J33) -> 1.8989832 | T33: =IF(OR(K33="",L33=""),"",K33/L33*365) | U33: =IF(OR(M33="",L33=""),"",M33/L33) | V33: =IF(ISTEXT(C33),"글자 섞임",ROUND(C33*VLOOKUP(N33,'환율_기준일'!$A$4:$E$7,5,FALSE)/'환율_기준일'!$E$4,2)) -> 18070 | W33: =IF(ISNUMBER(V33),IF(V33>F33*10,1,0),"") -> 0 | X33: =IF(Q33=1,COUNTIF($Q$2:Q33,1),"")
A34: B033 | B34: USD | C34: 0 | D34: 0 | E34: 0 | F34: 10000 | G34: 8449000 | H34: 3981000 | I34: 4962000 | L34: 21381000 | N34: =IFERROR(VLOOKUP(TRIM(B34),'확인표_A'!$A$6:$B$14,2,FALSE),"확인 필요") -> USD | O34: =SUMPRODUCT(--ISTEXT(C34:E34)) -> 0 | P34: =IF(OR(G34="",H34="",I34="",J34="",L34=""),1,0) -> 1 | Q34: =IF(AND(J34<>"",J34<=0),1,0) -> 0 | R34: =IF(OR(G34="",H34=""),"",G34/H34) -> 2.1223311 | S34: =IF(OR(I34="",J34="",Q34=1),"",I34/J34) | T34: =IF(OR(K34="",L34=""),"",K34/L34*365) | U34: =IF(OR(M34="",L34=""),"",M34/L34) | V34: =IF(ISTEXT(C34),"글자 섞임",ROUND(C34*VLOOKUP(N34,'환율_기준일'!$A$4:$E$7,5,FALSE)/'환율_기준일'!$E$4,2)) -> 0 | W34: =IF(ISNUMBER(V34),IF(V34>F34*10,1,0),"") -> 0 | X34: =IF(Q34=1,COUNTIF($Q$2:Q34,1),"")
A35: B034 | B35: EUR | C35: 200,520 | D35: 200520 | E35: 0 | F35: 40000 | G35: 88454000 | H35: 40560000 | I35: 71233000 | J35: 174567000 | K35: 42666000 | L35: 359145000 | M35: 42510000 | N35: =IFERROR(VLOOKUP(TRIM(B35),'확인표_A'!$A$6:$B$14,2,FALSE),"확인 필요") -> EUR | O35: =SUMPRODUCT(--ISTEXT(C35:E35)) -> 1 | P35: =IF(OR(G35="",H35="",I35="",J35="",L35=""),1,0) -> 0 | Q35: =IF(AND(J35<>"",J35<=0),1,0) -> 0 | R35: =IF(OR(G35="",H35=""),"",G35/H35) -> 2.1808185 | S35: =IF(OR(I35="",J35="",Q35=1),"",I35/J35) -> 0.40805536 | T35: =IF(OR(K35="",L35=""),"",K35/L35*365) -> 43.361567 | U35: =IF(OR(M35="",L35=""),"",M35/L35) -> 0.11836445 | V35: =IF(ISTEXT(C35),"글자 섞임",ROUND(C35*VLOOKUP(N35,'환율_기준일'!$A$4:$E$7,5,FALSE)/'환율_기준일'!$E$4,2)) -> 글자 섞임 | W35: =IF(ISNUMBER(V35),IF(V35>F35*10,1,0),"") | X35: =IF(Q35=1,COUNTIF($Q$2:Q35,1),"")
A36: B035 | B36: US$ | C36: 0 | D36: 0 | E36: 0 | F36: 10000 | G36: 8791000 | I36: 10013000 | J36: 4693000 | K36: 3684000 | L36: 17999000 | M36: -313000 | N36: =IFERROR(VLOOKUP(TRIM(B36),'확인표_A'!$A$6:$B$14,2,FALSE),"확인 필요") -> USD | O36: =SUMPRODUCT(--ISTEXT(C36:E36)) -> 0 | P36: =IF(OR(G36="",H36="",I36="",J36="",L36=""),1,0) -> 1 | Q36: =IF(AND(J36<>"",J36<=0),1,0) -> 0 | R36: =IF(OR(G36="",H36=""),"",G36/H36) | S36: =IF(OR(I36="",J36="",Q36=1),"",I36/J36) -> 2.1336032 | T36: =IF(OR(K36="",L36=""),"",K36/L36*365) -> 74.707484 | U36: =IF(OR(M36="",L36=""),"",M36/L36) -> -0.017389855 | V36: =IF(ISTEXT(C36),"글자 섞임",ROUND(C36*VLOOKUP(N36,'환율_기준일'!$A$4:$E$7,5,FALSE)/'환율_기준일'!$E$4,2)) -> 0 | W36: =IF(ISNUMBER(V36),IF(V36>F36*10,1,0),"") -> 0 | X36: =IF(Q36=1,COUNTIF($Q$2:Q36,1),"")
A37: B036 | B37: usd | C37: 0 | D37: 0 | E37: 0 | F37: 10000 | N37: =IFERROR(VLOOKUP(TRIM(B37),'확인표_A'!$A$6:$B$14,2,FALSE),"확인 필요") -> USD | O37: =SUMPRODUCT(--ISTEXT(C37:E37)) -> 0 | P37: =IF(OR(G37="",H37="",I37="",J37="",L37=""),1,0) -> 1 | Q37: =IF(AND(J37<>"",J37<=0),1,0) -> 0 | R37: =IF(OR(G37="",H37=""),"",G37/H37) | S37: =IF(OR(I37="",J37="",Q37=1),"",I37/J37) | T37: =IF(OR(K37="",L37=""),"",K37/L37*365) | U37: =IF(OR(M37="",L37=""),"",M37/L37) | V37: =IF(ISTEXT(C37),"글자 섞임",ROUND(C37*VLOOKUP(N37,'환율_기준일'!$A$4:$E$7,5,FALSE)/'환율_기준일'!$E$4,2)) -> 0 | W37: =IF(ISNUMBER(V37),IF(V37>F37*10,1,0),"") -> 0 | X37: =IF(Q37=1,COUNTIF($Q$2:Q37,1),"")
A38: B037 | B38: USD | C38: 8690 | D38: 8690 | E38: 0 | F38: 40000 | G38: 17218000 | H38: 23499000 | I38: 38705000 | J38: 39854000 | K38: 6499000 | L38: 47961000 | M38: 3790000 | N38: =IFERROR(VLOOKUP(TRIM(B38),'확인표_A'!$A$6:$B$14,2,FALSE),"확인 필요") -> USD | O38: =SUMPRODUCT(--ISTEXT(C38:E38)) -> 0 | P38: =IF(OR(G38="",H38="",I38="",J38="",L38=""),1,0) -> 0 | Q38: =IF(AND(J38<>"",J38<=0),1,0) -> 0 | R38: =IF(OR(G38="",H38=""),"",G38/H38) -> 0.73271203 | S38: =IF(OR(I38="",J38="",Q38=1),"",I38/J38) -> 0.97116977 | T38: =IF(OR(K38="",L38=""),"",K38/L38*365) -> 49.459665 | U38: =IF(OR(M38="",L38=""),"",M38/L38) -> 0.079022539 | V38: =IF(ISTEXT(C38),"글자 섞임",ROUND(C38*VLOOKUP(N38,'환율_기준일'!$A$4:$E$7,5,FALSE)/'환율_기준일'!$E$4,2)) -> 8690 | W38: =IF(ISNUMBER(V38),IF(V38>F38*10,1,0),"") -> 0 | X38: =IF(Q38=1,COUNTIF($Q$2:Q38,1),"")
A39: B038 | B39: EUR | C39: 0 | D39: 0 | E39: 0 | F39: 10000 | G39: 4526000 | H39: 4302000 | I39: 5205000 | J39: 1129000 | K39: 1761000 | L39: 6552000 | M39: -350000 | N39: =IFERROR(VLOOKUP(TRIM(B39),'확인표_A'!$A$6:$B$14,2,FALSE),"확인 필요") -> EUR | O39: =SUMPRODUCT(--ISTEXT(C39:E39)) -> 0 | P39: =IF(OR(G39="",H39="",I39="",J39="",L39=""),1,0) -> 0 | Q39: =IF(AND(J39<>"",J39<=0),1,0) -> 0 | R39: =IF(OR(G39="",H39=""),"",G39/H39) -> 1.0520688 | S39: =IF(OR(I39="",J39="",Q39=1),"",I39/J39) -> 4.6102746 | T39: =IF(OR(K39="",L39=""),"",K39/L39*365) -> 98.102106 | U39: =IF(OR(M39="",L39=""),"",M39/L39) -> -0.053418803 | V39: =IF(ISTEXT(C39),"글자 섞임",ROUND(C39*VLOOKUP(N39,'환율_기준일'!$A$4:$E$7,5,FALSE)/'환율_기준일'!$E$4,2)) -> 0 | W39: =IF(ISNUMBER(V39),IF(V39>F39*10,1,0),"") -> 0 | X39: =IF(Q39=1,COUNTIF($Q$2:Q39,1),"")
A40: B039 | B40: USD | C40: 0 | D40: 0 | E40: 0 | F40: 10000 | G40: 3344000 | H40: 2615000 | I40: 4125000 | J40: 2017000 | L40: 7402000 | M40: 500000 | N40: =IFERROR(VLOOKUP(TRIM(B40),'확인표_A'!$A$6:$B$14,2,FALSE),"확인 필요") -> USD | O40: =SUMPRODUCT(--ISTEXT(C40:E40)) -> 0 | P40: =IF(OR(G40="",H40="",I40="",J40="",L40=""),1,0) -> 0 | Q40: =IF(AND(J40<>"",J40<=0),1,0) -> 0 | R40: =IF(OR(G40="",H40=""),"",G40/H40) -> 1.2787763 | S40: =IF(OR(I40="",J40="",Q40=1),"",I40/J40) -> 2.0451165 | T40: =IF(OR(K40="",L40=""),"",K40/L40*365) | U40: =IF(OR(M40="",L40=""),"",M40/L40) -> 0.067549311 | V40: =IF(ISTEXT(C40),"글자 섞임",ROUND(C40*VLOOKUP(N40,'환율_기준일'!$A$4:$E$7,5,FALSE)/'환율_기준일'!$E$4,2)) -> 0 | W40: =IF(ISNUMBER(V40),IF(V40>F40*10,1,0),"") -> 0 | X40: =IF(Q40=1,COUNTIF($Q$2:Q40,1),"")
A41: B040 | B41: USD | C41: 77190 | D41: 77190 | E41: 0 | F41: 70000 | G41: 46470000 | H41: 31790000 | I41: 48613000 | J41: 19932000 | K41: 16638000 | L41: 64727000 | N41: =IFERROR(VLOOKUP(TRIM(B41),'확인표_A'!$A$6:$B$14,2,FALSE),"확인 필요") -> USD | O41: =SUMPRODUCT(--ISTEXT(C41:E41)) -> 0 | P41: =IF(OR(G41="",H41="",I41="",J41="",L41=""),1,0) -> 0 | Q41: =IF(AND(J41<>"",J41<=0),1,0) -> 0 | R41: =IF(OR(G41="",H41=""),"",G41/H41) -> 1.4617804 | S41: =IF(OR(I41="",J41="",Q41=1),"",I41/J41) -> 2.4389424 | T41: =IF(OR(K41="",L41=""),"",K41/L41*365) -> 93.822825 | U41: =IF(OR(M41="",L41=""),"",M41/L41) | V41: =IF(ISTEXT(C41),"글자 섞임",ROUND(C41*VLOOKUP(N41,'환율_기준일'!$A$4:$E$7,5,FALSE)/'환율_기준일'!$E$4,2)) -> 77190 | W41: =IF(ISNUMBER(V41),IF(V41>F41*10,1,0),"") -> 0 | X41: =IF(Q41=1,COUNTIF($Q$2:Q41,1),"")
A42: B041 | B42: USD | C42: 25090 | D42: 25090 | E42: 0 | F42: 30000 | G42: 24375000 | H42: 18080000 | I42: 38834000 | J42: 7664000 | K42: 9640000 | L42: 48147000 | M42: 1402000 | N42: =IFERROR(VLOOKUP(TRIM(B42),'확인표_A'!$A$6:$B$14,2,FALSE),"확인 필요") -> USD | O42: =SUMPRODUCT(--ISTEXT(C42:E42)) -> 0 | P42: =IF(OR(G42="",H42="",I42="",J42="",L42=""),1,0) -> 0 | Q42: =IF(AND(J42<>"",J42<=0),1,0) -> 0 | R42: =IF(OR(G42="",H42=""),"",G42/H42) -> 1.3481748 | S42: =IF(OR(I42="",J42="",Q42=1),"",I42/J42) -> 5.0670668 | T42: =IF(OR(K42="",L42=""),"",K42/L42*365) -> 73.080358 | U42: =IF(OR(M42="",L42=""),"",M42/L42) -> 0.029119156 | V42: =IF(ISTEXT(C42),"글자 섞임",ROUND(C42*VLOOKUP(N42,'환율_기준일'!$A$4:$E$7,5,FALSE)/'환율_기준일'!$E$4,2)) -> 25090 | W42: =IF(ISNUMBER(V42),IF(V42>F42*10,1,0),"") -> 0 | X42: =IF(Q42=1,COUNTIF($Q$2:Q42,1),"")
A43: B042 | B43: USD | C43: 0 | D43: 0 | E43: 0 | F43: 10000 | G43: 4274000 | I43: 6545000 | K43: 1458000 | L43: 5456000 | N43: =IFERROR(VLOOKUP(TRIM(B43),'확인표_A'!$A$6:$B$14,2,FALSE),"확인 필요") -> USD | O43: =SUMPRODUCT(--ISTEXT(C43:E43)) -> 0 | P43: =IF(OR(G43="",H43="",I43="",J43="",L43=""),1,0) -> 1 | Q43: =IF(AND(J43<>"",J43<=0),1,0) -> 0 | R43: =IF(OR(G43="",H43=""),"",G43/H43) | S43: =IF(OR(I43="",J43="",Q43=1),"",I43/J43) | T43: =IF(OR(K43="",L43=""),"",K43/L43*365) -> 97.53849 | U43: =IF(OR(M43="",L43=""),"",M43/L43) | V43: =IF(ISTEXT(C43),"글자 섞임",ROUND(C43*VLOOKUP(N43,'환율_기준일'!$A$4:$E$7,5,FALSE)/'환율_기준일'!$E$4,2)) -> 0 | W43: =IF(ISNUMBER(V43),IF(V43>F43*10,1,0),"") -> 0 | X43: =IF(Q43=1,COUNTIF($Q$2:Q43,1),"")
A44: B043 | B44: CNY | C44: 155,200 CNY | D44: 155200 | E44: 0 | F44: 30000 | G44: 2730000 | H44: 2022000 | I44: 3876000 | J44: 5166000 | K44: 1383000 | L44: 7825000 | M44: 517000 | N44: =IFERROR(VLOOKUP(TRIM(B44),'확인표_A'!$A$6:$B$14,2,FALSE),"확인 필요") -> CNY | O44: =SUMPRODUCT(--ISTEXT(C44:E44)) -> 1 | P44: =IF(OR(G44="",H44="",I44="",J44="",L44=""),1,0) -> 0 | Q44: =IF(AND(J44<>"",J44<=0),1,0) -> 0 | R44: =IF(OR(G44="",H44=""),"",G44/H44) -> 1.3501484 | S44: =IF(OR(I44="",J44="",Q44=1),"",I44/J44) -> 0.75029036 | T44: =IF(OR(K44="",L44=""),"",K44/L44*365) -> 64.510543 | U44: =IF(OR(M44="",L44=""),"",M44/L44) -> 0.066070288 | V44: =IF(ISTEXT(C44),"글자 섞임",ROUND(C44*VLOOKUP(N44,'환율_기준일'!$A$4:$E$7,5,FALSE)/'환율_기준일'!$E$4,2)) -> 글자 섞임 | W44: =IF(ISNUMBER(V44),IF(V44>F44*10,1,0),"") | X44: =IF(Q44=1,COUNTIF($Q$2:Q44,1),"")
A45: B044 | B45: USD | C45: 13330 | D45: 0 | E45: 0 | F45: 10000 | G45: 8357000 | I45: 16194000 | K45: 4377000 | L45: 12956000 | M45: 5000 | N45: =IFERROR(VLOOKUP(TRIM(B45),'확인표_A'!$A$6:$B$14,2,FALSE),"확인 필요") -> USD | O45: =SUMPRODUCT(--ISTEXT(C45:E45)) -> 0 | P45: =IF(OR(G45="",H45="",I45="",J45="",L45=""),1,0) -> 1 | Q45: =IF(AND(J45<>"",J45<=0),1,0) -> 0 | R45: =IF(OR(G45="",H45=""),"",G45/H45) | S45: =IF(OR(I45="",J45="",Q45=1),"",I45/J45) | T45: =IF(OR(K45="",L45=""),"",K45/L45*365) -> 123.31005 | U45: =IF(OR(M45="",L45=""),"",M45/L45) -> 0.00038592158 | V45: =IF(ISTEXT(C45),"글자 섞임",ROUND(C45*VLOOKUP(N45,'환율_기준일'!$A$4:$E$7,5,FALSE)/'환율_기준일'!$E$4,2)) -> 13330 | W45: =IF(ISNUMBER(V45),IF(V45>F45*10,1,0),"") -> 0 | X45: =IF(Q45=1,COUNTIF($Q$2:Q45,1),"")
A46: B045 | B46: USD | C46: 11050 | D46: 11050 | E46: 0 | F46: 10000 | G46: 5869000 | H46: 4961000 | I46: 7032000 | J46: 6331000 | K46: 2418000 | L46: 14928000 | N46: =IFERROR(VLOOKUP(TRIM(B46),'확인표_A'!$A$6:$B$14,2,FALSE),"확인 필요") -> USD | O46: =SUMPRODUCT(--ISTEXT(C46:E46)) -> 0 | P46: =IF(OR(G46="",H46="",I46="",J46="",L46=""),1,0) -> 0 | Q46: =IF(AND(J46<>"",J46<=0),1,0) -> 0 | R46: =IF(OR(G46="",H46=""),"",G46/H46) -> 1.1830276 | S46: =IF(OR(I46="",J46="",Q46=1),"",I46/J46) -> 1.110725 | T46: =IF(OR(K46="",L46=""),"",K46/L46*365) -> 59.121785 | U46: =IF(OR(M46="",L46=""),"",M46/L46) | V46: =IF(ISTEXT(C46),"글자 섞임",ROUND(C46*VLOOKUP(N46,'환율_기준일'!$A$4:$E$7,5,FALSE)/'환율_기준일'!$E$4,2)) -> 11050 | W46: =IF(ISNUMBER(V46),IF(V46>F46*10,1,0),"") -> 0 | X46: =IF(Q46=1,COUNTIF($Q$2:Q46,1),"")
A47: B046 | B47: US$ | C47: 0 | D47: 0 | E47: 0 | F47: 20000 | G47: 65302000 | H47: 43040000 | I47: 85553000 | J47: 224995000 | K47: 26061000 | L47: 256707000 | M47: 24498000 | N47: =IFERROR(VLOOKUP(TRIM(B47),'확인표_A'!$A$6:$B$14,2,FALSE),"확인 필요") -> USD | O47: =SUMPRODUCT(--ISTEXT(C47:E47)) -> 0 | P47: =IF(OR(G47="",H47="",I47="",J47="",L47=""),1,0) -> 0 | Q47: =IF(AND(J47<>"",J47<=0),1,0) -> 0 | R47: =IF(OR(G47="",H47=""),"",G47/H47) -> 1.5172398 | S47: =IF(OR(I47="",J47="",Q47=1),"",I47/J47) -> 0.38024401 | T47: =IF(OR(K47="",L47=""),"",K47/L47*365) -> 37.05495 | U47: =IF(OR(M47="",L47=""),"",M47/L47) -> 0.095431757 | V47: =IF(ISTEXT(C47),"글자 섞임",ROUND(C47*VLOOKUP(N47,'환율_기준일'!$A$4:$E$7,5,FALSE)/'환율_기준일'!$E$4,2)) -> 0 | W47: =IF(ISNUMBER(V47),IF(V47>F47*10,1,0),"") -> 0 | X47: =IF(Q47=1,COUNTIF($Q$2:Q47,1),"")
A48: B047 | B48: usd | C48: 51270 | D48: 31470 | E48: 19800 | F48: 50000 | N48: =IFERROR(VLOOKUP(TRIM(B48),'확인표_A'!$A$6:$B$14,2,FALSE),"확인 필요") -> USD | O48: =SUMPRODUCT(--ISTEXT(C48:E48)) -> 0 | P48: =IF(OR(G48="",H48="",I48="",J48="",L48=""),1,0) -> 1 | Q48: =IF(AND(J48<>"",J48<=0),1,0) -> 0 | R48: =IF(OR(G48="",H48=""),"",G48/H48) | S48: =IF(OR(I48="",J48="",Q48=1),"",I48/J48) | T48: =IF(OR(K48="",L48=""),"",K48/L48*365) | U48: =IF(OR(M48="",L48=""),"",M48/L48) | V48: =IF(ISTEXT(C48),"글자 섞임",ROUND(C48*VLOOKUP(N48,'환율_기준일'!$A$4:$E$7,5,FALSE)/'환율_기준일'!$E$4,2)) -> 51270 | W48: =IF(ISNUMBER(V48),IF(V48>F48*10,1,0),"") -> 0 | X48: =IF(Q48=1,COUNTIF($Q$2:Q48,1),"")
A49: B048 | B49: US$ | C49: 24530 | D49: 0 | E49: 15810 | F49: 10000 | G49: 34935000 | H49: 97042000 | I49: 160609000 | J49: -37662000 | K49: 13733000 | L49: 58284000 | M49: -13770000 | N49: =IFERROR(VLOOKUP(TRIM(B49),'확인표_A'!$A$6:$B$14,2,FALSE),"확인 필요") -> USD | O49: =SUMPRODUCT(--ISTEXT(C49:E49)) -> 0 | P49: =IF(OR(G49="",H49="",I49="",J49="",L49=""),1,0) -> 0 | Q49: =IF(AND(J49<>"",J49<=0),1,0) -> 1 | R49: =IF(OR(G49="",H49=""),"",G49/H49) -> 0.35999876 | S49: =IF(OR(I49="",J49="",Q49=1),"",I49/J49) | T49: =IF(OR(K49="",L49=""),"",K49/L49*365) -> 86.002076 | U49: =IF(OR(M49="",L49=""),"",M49/L49) -> -0.23625695 | V49: =IF(ISTEXT(C49),"글자 섞임",ROUND(C49*VLOOKUP(N49,'환율_기준일'!$A$4:$E$7,5,FALSE)/'환율_기준일'!$E$4,2)) -> 24530 | W49: =IF(ISNUMBER(V49),IF(V49>F49*10,1,0),"") -> 0 | X49: =IF(Q49=1,COUNTIF($Q$2:Q49,1),"") -> 2
A50: B049 | B50: USD | C50: 42030 | D50: 32390 | E50: 0 | F50: 70000 | G50: 127186000 | H50: 97231000 | I50: 196502000 | J50: 67789000 | K50: 52832000 | L50: 290244000 | M50: 11244000 | N50: =IFERROR(VLOOKUP(TRIM(B50),'확인표_A'!$A$6:$B$14,2,FALSE),"확인 필요") -> USD | O50: =SUMPRODUCT(--ISTEXT(C50:E50)) -> 0 | P50: =IF(OR(G50="",H50="",I50="",J50="",L50=""),1,0) -> 0 | Q50: =IF(AND(J50<>"",J50<=0),1,0) -> 0 | R50: =IF(OR(G50="",H50=""),"",G50/H50) -> 1.3080808 | S50: =IF(OR(I50="",J50="",Q50=1),"",I50/J50) -> 2.8987299 | T50: =IF(OR(K50="",L50=""),"",K50/L50*365) -> 66.439547 | U50: =IF(OR(M50="",L50=""),"",M50/L50) -> 0.038739819 | V50: =IF(ISTEXT(C50),"글자 섞임",ROUND(C50*VLOOKUP(N50,'환율_기준일'!$A$4:$E$7,5,FALSE)/'환율_기준일'!$E$4,2)) -> 42030 | W50: =IF(ISNUMBER(V50),IF(V50>F50*10,1,0),"") -> 0 | X50: =IF(Q50=1,COUNTIF($Q$2:Q50,1),"")
A51: B050 | B51: USD | C51: 101210 | D51: 101210 | E51: 0 | F51: 80000 | G51: 17668000 | H51: 9162000 | I51: 14251000 | J51: 10072000 | K51: 6208000 | L51: 36022000 | M51: 2538000 | N51: =IFERROR(VLOOKUP(TRIM(B51),'확인표_A'!$A$6:$B$14,2,FALSE),"확인 필요") -> USD | O51: =SUMPRODUCT(--ISTEXT(C51:E51)) -> 0 | P51: =IF(OR(G51="",H51="",I51="",J51="",L51=""),1,0) -> 0 | Q51: =IF(AND(J51<>"",J51<=0),1,0) -> 0 | R51: =IF(OR(G51="",H51=""),"",G51/H51) -> 1.9283999 | S51: =IF(OR(I51="",J51="",Q51=1),"",I51/J51) -> 1.4149126 | T51: =IF(OR(K51="",L51=""),"",K51/L51*365) -> 62.903781 | U51: =IF(OR(M51="",L51=""),"",M51/L51) -> 0.070456943 | V51: =IF(ISTEXT(C51),"글자 섞임",ROUND(C51*VLOOKUP(N51,'환율_기준일'!$A$4:$E$7,5,FALSE)/'환율_기준일'!$E$4,2)) -> 101210 | W51: =IF(ISNUMBER(V51),IF(V51>F51*10,1,0),"") -> 0 | X51: =IF(Q51=1,COUNTIF($Q$2:Q51,1),"")
A52: B051 | B52: usd | C52: 14310 | D52: 14310 | E52: 0 | F52: 60000 | G52: 35902000 | H52: 23801000 | I52: 34426000 | J52: 25533000 | K52: 18314000 | L52: 102155000 | M52: 7875000 | N52: =IFERROR(VLOOKUP(TRIM(B52),'확인표_A'!$A$6:$B$14,2,FALSE),"확인 필요") -> USD | O52: =SUMPRODUCT(--ISTEXT(C52:E52)) -> 0 | P52: =IF(OR(G52="",H52="",I52="",J52="",L52=""),1,0) -> 0 | Q52: =IF(AND(J52<>"",J52<=0),1,0) -> 0 | R52: =IF(OR(G52="",H52=""),"",G52/H52) -> 1.508424 | S52: =IF(OR(I52="",J52="",Q52=1),"",I52/J52) -> 1.3482944 | T52: =IF(OR(K52="",L52=""),"",K52/L52*365) -> 65.435955 | U52: =IF(OR(M52="",L52=""),"",M52/L52) -> 0.077088738 | V52: =IF(ISTEXT(C52),"글자 섞임",ROUND(C52*VLOOKUP(N52,'환율_기준일'!$A$4:$E$7,5,FALSE)/'환율_기준일'!$E$4,2)) -> 14310 | W52: =IF(ISNUMBER(V52),IF(V52>F52*10,1,0),"") -> 0 | X52: =IF(Q52=1,COUNTIF($Q$2:Q52,1),"")
A53: B052 | B53: US$ | C53: 0 | D53: 0 | E53: 0 | F53: 10000 | G53: 77572000 | H53: 57868000 | I53: 87706000 | J53: 38837000 | K53: 27946000 | L53: 167235000 | M53: 17161000 | N53: =IFERROR(VLOOKUP(TRIM(B53),'확인표_A'!$A$6:$B$14,2,FALSE),"확인 필요") -> USD | O53: =SUMPRODUCT(--ISTEXT(C53:E53)) -> 0 | P53: =IF(OR(G53="",H53="",I53="",J53="",L53=""),1,0) -> 0 | Q53: =IF(AND(J53<>"",J53<=0),1,0) -> 0 | R53: =IF(OR(G53="",H53=""),"",G53/H53) -> 1.3404991 | S53: =IF(OR(I53="",J53="",Q53=1),"",I53/J53) -> 2.2583104 | T53: =IF(OR(K53="",L53=""),"",K53/L53*365) -> 60.993751 | U53: =IF(OR(M53="",L53=""),"",M53/L53) -> 0.10261608 | V53: =IF(ISTEXT(C53),"글자 섞임",ROUND(C53*VLOOKUP(N53,'환율_기준일'!$A$4:$E$7,5,FALSE)/'환율_기준일'!$E$4,2)) -> 0 | W53: =IF(ISNUMBER(V53),IF(V53>F53*10,1,0),"") -> 0 | X53: =IF(Q53=1,COUNTIF($Q$2:Q53,1),"")
A54: B053 | B54: EUR | C54: 18450 | D54: 18450 | E54: 0 | F54: 40000 | G54: 113245000 | H54: 77473000 | I54: 96619000 | J54: 37613000 | K54: 57614000 | L54: 258078000 | M54: 8990000 | N54: =IFERROR(VLOOKUP(TRIM(B54),'확인표_A'!$A$6:$B$14,2,FALSE),"확인 필요") -> EUR | O54: =SUMPRODUCT(--ISTEXT(C54:E54)) -> 0 | P54: =IF(OR(G54="",H54="",I54="",J54="",L54=""),1,0) -> 0 | Q54: =IF(AND(J54<>"",J54<=0),1,0) -> 0 | R54: =IF(OR(G54="",H54=""),"",G54/H54) -> 1.4617351 | S54: =IF(OR(I54="",J54="",Q54=1),"",I54/J54) -> 2.5687661 | T54: =IF(OR(K54="",L54=""),"",K54/L54*365) -> 81.483544 | U54: =IF(OR(M54="",L54=""),"",M54/L54) -> 0.03483443 | V54: =IF(ISTEXT(C54),"글자 섞임",ROUND(C54*VLOOKUP(N54,'환율_기준일'!$A$4:$E$7,5,FALSE)/'환율_기준일'!$E$4,2)) -> 21433.42 | W54: =IF(ISNUMBER(V54),IF(V54>F54*10,1,0),"") -> 0 | X54: =IF(Q54=1,COUNTIF($Q$2:Q54,1),"")
A55: B054 | B55: euro | C55: 0 | D55: 0 | E55: 0 | F55: 40000 | G55: 106332000 | H55: 63671000 | I55: 84315000 | J55: 223416000 | K55: 35676000 | L55: 411694000 | M55: 53117000 | N55: =IFERROR(VLOOKUP(TRIM(B55),'확인표_A'!$A$6:$B$14,2,FALSE),"확인 필요") -> EUR | O55: =SUMPRODUCT(--ISTEXT(C55:E55)) -> 0 | P55: =IF(OR(G55="",H55="",I55="",J55="",L55=""),1,0) -> 0 | Q55: =IF(AND(J55<>"",J55<=0),1,0) -> 0 | R55: =IF(OR(G55="",H55=""),"",G55/H55) -> 1.6700225 | S55: =IF(OR(I55="",J55="",Q55=1),"",I55/J55) -> 0.37739016 | T55: =IF(OR(K55="",L55=""),"",K55/L55*365) -> 31.629657 | U55: =IF(OR(M55="",L55=""),"",M55/L55) -> 0.12902058 | V55: =IF(ISTEXT(C55),"글자 섞임",ROUND(C55*VLOOKUP(N55,'환율_기준일'!$A$4:$E$7,5,FALSE)/'환율_기준일'!$E$4,2)) -> 0 | W55: =IF(ISNUMBER(V55),IF(V55>F55*10,1,0),"") -> 0 | X55: =IF(Q55=1,COUNTIF($Q$2:Q55,1),"")
A56: B055 | B56: USD | C56: 0 | D56: 0 | E56: 0 | F56: 10000 | N56: =IFERROR(VLOOKUP(TRIM(B56),'확인표_A'!$A$6:$B$14,2,FALSE),"확인 필요") -> USD | O56: =SUMPRODUCT(--ISTEXT(C56:E56)) -> 0 | P56: =IF(OR(G56="",H56="",I56="",J56="",L56=""),1,0) -> 1 | Q56: =IF(AND(J56<>"",J56<=0),1,0) -> 0 | R56: =IF(OR(G56="",H56=""),"",G56/H56) | S56: =IF(OR(I56="",J56="",Q56=1),"",I56/J56) | T56: =IF(OR(K56="",L56=""),"",K56/L56*365) | U56: =IF(OR(M56="",L56=""),"",M56/L56) | V56: =IF(ISTEXT(C56),"글자 섞임",ROUND(C56*VLOOKUP(N56,'환율_기준일'!$A$4:$E$7,5,FALSE)/'환율_기준일'!$E$4,2)) -> 0 | W56: =IF(ISNUMBER(V56),IF(V56>F56*10,1,0),"") -> 0 | X56: =IF(Q56=1,COUNTIF($Q$2:Q56,1),"")
A57: B056 | B57: USD | C57: 63690 | D57: 63690 | E57: 0 | F57: 30000 | G57: 3255000 | H57: 2579000 | I57: 4321000 | J57: 5972000 | K57: 1224000 | L57: 8052000 | M57: 805000 | N57: =IFERROR(VLOOKUP(TRIM(B57),'확인표_A'!$A$6:$B$14,2,FALSE),"확인 필요") -> USD | O57: =SUMPRODUCT(--ISTEXT(C57:E57)) -> 0 | P57: =IF(OR(G57="",H57="",I57="",J57="",L57=""),1,0) -> 0 | Q57: =IF(AND(J57<>"",J57<=0),1,0) -> 0 | R57: =IF(OR(G57="",H57=""),"",G57/H57) -> 1.2621171 | S57: =IF(OR(I57="",J57="",Q57=1),"",I57/J57) -> 0.7235432 | T57: =IF(OR(K57="",L57=""),"",K57/L57*365) -> 55.484352 | U57: =IF(OR(M57="",L57=""),"",M57/L57) -> 0.099975161 | V57: =IF(ISTEXT(C57),"글자 섞임",ROUND(C57*VLOOKUP(N57,'환율_기준일'!$A$4:$E$7,5,FALSE)/'환율_기준일'!$E$4,2)) -> 63690 | W57: =IF(ISNUMBER(V57),IF(V57>F57*10,1,0),"") -> 0 | X57: =IF(Q57=1,COUNTIF($Q$2:Q57,1),"")
A58: B057 | B58: USD | C58: 141190 | D58: 138790 | E58: 2400 | F58: 160000 | G58: 22594000 | H58: 21473000 | I58: 45418000 | J58: 30871000 | K58: 9245000 | L58: 46739000 | M58: 3198000 | N58: =IFERROR(VLOOKUP(TRIM(B58),'확인표_A'!$A$6:$B$14,2,FALSE),"확인 필요") -> USD | O58: =SUMPRODUCT(--ISTEXT(C58:E58)) -> 0 | P58: =IF(OR(G58="",H58="",I58="",J58="",L58=""),1,0) -> 0 | Q58: =IF(AND(J58<>"",J58<=0),1,0) -> 0 | R58: =IF(OR(G58="",H58=""),"",G58/H58) -> 1.0522051 | S58: =IF(OR(I58="",J58="",Q58=1),"",I58/J58) -> 1.4712189 | T58: =IF(OR(K58="",L58=""),"",K58/L58*365) -> 72.197201 | U58: =IF(OR(M58="",L58=""),"",M58/L58) -> 0.068422517 | V58: =IF(ISTEXT(C58),"글자 섞임",ROUND(C58*VLOOKUP(N58,'환율_기준일'!$A$4:$E$7,5,FALSE)/'환율_기준일'!$E$4,2)) -> 141190 | W58: =IF(ISNUMBER(V58),IF(V58>F58*10,1,0),"") -> 0 | X58: =IF(Q58=1,COUNTIF($Q$2:Q58,1),"")
A59: B058 | B59: USD | C59: 22060 | D59: 22060 | E59: 0 | F59: 30000 | N59: =IFERROR(VLOOKUP(TRIM(B59),'확인표_A'!$A$6:$B$14,2,FALSE),"확인 필요") -> USD | O59: =SUMPRODUCT(--ISTEXT(C59:E59)) -> 0 | P59: =IF(OR(G59="",H59="",I59="",J59="",L59=""),1,0) -> 1 | Q59: =IF(AND(J59<>"",J59<=0),1,0) -> 0 | R59: =IF(OR(G59="",H59=""),"",G59/H59) | S59: =IF(OR(I59="",J59="",Q59=1),"",I59/J59) | T59: =IF(OR(K59="",L59=""),"",K59/L59*365) | U59: =IF(OR(M59="",L59=""),"",M59/L59) | V59: =IF(ISTEXT(C59),"글자 섞임",ROUND(C59*VLOOKUP(N59,'환율_기준일'!$A$4:$E$7,5,FALSE)/'환율_기준일'!$E$4,2)) -> 22060 | W59: =IF(ISNUMBER(V59),IF(V59>F59*10,1,0),"") -> 0 | X59: =IF(Q59=1,COUNTIF($Q$2:Q59,1),"")
A60: B059 | B60: USD | C60: 4980 | D60: 0 | E60: 1400 | F60: 40000 | G60: 28938000 | H60: 37260000 | I60: 52596000 | J60: 22576000 | K60: 10230000 | L60: 48891000 | M60: -2468000 | N60: =IFERROR(VLOOKUP(TRIM(B60),'확인표_A'!$A$6:$B$14,2,FALSE),"확인 필요") -> USD | O60: =SUMPRODUCT(--ISTEXT(C60:E60)) -> 0 | P60: =IF(OR(G60="",H60="",I60="",J60="",L60=""),1,0) -> 0 | Q60: =IF(AND(J60<>"",J60<=0),1,0) -> 0 | R60: =IF(OR(G60="",H60=""),"",G60/H60) -> 0.77665056 | S60: =IF(OR(I60="",J60="",Q60=1),"",I60/J60) -> 2.3297307 | T60: =IF(OR(K60="",L60=""),"",K60/L60*365) -> 76.372952 | U60: =IF(OR(M60="",L60=""),"",M60/L60) -> -0.050479638 | V60: =IF(ISTEXT(C60),"글자 섞임",ROUND(C60*VLOOKUP(N60,'환율_기준일'!$A$4:$E$7,5,FALSE)/'환율_기준일'!$E$4,2)) -> 4980 | W60: =IF(ISNUMBER(V60),IF(V60>F60*10,1,0),"") -> 0 | X60: =IF(Q60=1,COUNTIF($Q$2:Q60,1),"")
A61: B060 | B61: US$ | C61: 0 | D61: 0 | E61: 0 | F61: 10000 | N61: =IFERROR(VLOOKUP(TRIM(B61),'확인표_A'!$A$6:$B$14,2,FALSE),"확인 필요") -> USD | O61: =SUMPRODUCT(--ISTEXT(C61:E61)) -> 0 | P61: =IF(OR(G61="",H61="",I61="",J61="",L61=""),1,0) -> 1 | Q61: =IF(AND(J61<>"",J61<=0),1,0) -> 0 | R61: =IF(OR(G61="",H61=""),"",G61/H61) | S61: =IF(OR(I61="",J61="",Q61=1),"",I61/J61) | T61: =IF(OR(K61="",L61=""),"",K61/L61*365) | U61: =IF(OR(M61="",L61=""),"",M61/L61) | V61: =IF(ISTEXT(C61),"글자 섞임",ROUND(C61*VLOOKUP(N61,'환율_기준일'!$A$4:$E$7,5,FALSE)/'환율_기준일'!$E$4,2)) -> 0 | W61: =IF(ISNUMBER(V61),IF(V61>F61*10,1,0),"") -> 0 | X61: =IF(Q61=1,COUNTIF($Q$2:Q61,1),"")
A62: B061 | B62: USD | C62: 7670 | D62: 7670 | E62: 0 | F62: 10000 | G62: 12831000 | H62: 6178000 | I62: 9947000 | J62: 3869000 | K62: 4774000 | L62: 21218000 | N62: =IFERROR(VLOOKUP(TRIM(B62),'확인표_A'!$A$6:$B$14,2,FALSE),"확인 필요") -> USD | O62: =SUMPRODUCT(--ISTEXT(C62:E62)) -> 0 | P62: =IF(OR(G62="",H62="",I62="",J62="",L62=""),1,0) -> 0 | Q62: =IF(AND(J62<>"",J62<=0),1,0) -> 0 | R62: =IF(OR(G62="",H62=""),"",G62/H62) -> 2.0768857 | S62: =IF(OR(I62="",J62="",Q62=1),"",I62/J62) -> 2.5709486 | T62: =IF(OR(K62="",L62=""),"",K62/L62*365) -> 82.12414 | U62: =IF(OR(M62="",L62=""),"",M62/L62) | V62: =IF(ISTEXT(C62),"글자 섞임",ROUND(C62*VLOOKUP(N62,'환율_기준일'!$A$4:$E$7,5,FALSE)/'환율_기준일'!$E$4,2)) -> 7670 | W62: =IF(ISNUMBER(V62),IF(V62>F62*10,1,0),"") -> 0 | X62: =IF(Q62=1,COUNTIF($Q$2:Q62,1),"")
A63: B062 | B63: usd | C63: 44530 | D63: 36780 | E63: 7750 | F63: 120000 | G63: 39188000 | I63: 32174000 | J63: 22273000 | K63: 20572000 | L63: 105519000 | M63: 9946000 | N63: =IFERROR(VLOOKUP(TRIM(B63),'확인표_A'!$A$6:$B$14,2,FALSE),"확인 필요") -> USD | O63: =SUMPRODUCT(--ISTEXT(C63:E63)) -> 0 | P63: =IF(OR(G63="",H63="",I63="",J63="",L63=""),1,0) -> 1 | Q63: =IF(AND(J63<>"",J63<=0),1,0) -> 0 | R63: =IF(OR(G63="",H63=""),"",G63/H63) | S63: =IF(OR(I63="",J63="",Q63=1),"",I63/J63) -> 1.4445293 | T63: =IF(OR(K63="",L63=""),"",K63/L63*365) -> 71.160455 | U63: =IF(OR(M63="",L63=""),"",M63/L63) -> 0.094257906 | V63: =IF(ISTEXT(C63),"글자 섞임",ROUND(C63*VLOOKUP(N63,'환율_기준일'!$A$4:$E$7,5,FALSE)/'환율_기준일'!$E$4,2)) -> 44530 | W63: =IF(ISNUMBER(V63),IF(V63>F63*10,1,0),"") -> 0 | X63: =IF(Q63=1,COUNTIF($Q$2:Q63,1),"")
A64: B063 | B64: RMB | C64: 0 | D64: 0 | E64: 0 | F64: 10000 | G64: 6081000 | H64: 3984000 | I64: 7716000 | J64: 2059000 | K64: 2611000 | L64: 7780000 | M64: 53000 | N64: =IFERROR(VLOOKUP(TRIM(B64),'확인표_A'!$A$6:$B$14,2,FALSE),"확인 필요") -> CNY | O64: =SUMPRODUCT(--ISTEXT(C64:E64)) -> 0 | P64: =IF(OR(G64="",H64="",I64="",J64="",L64=""),1,0) -> 0 | Q64: =IF(AND(J64<>"",J64<=0),1,0) -> 0 | R64: =IF(OR(G64="",H64=""),"",G64/H64) -> 1.5263554 | S64: =IF(OR(I64="",J64="",Q64=1),"",I64/J64) -> 3.7474502 | T64: =IF(OR(K64="",L64=""),"",K64/L64*365) -> 122.4955 | U64: =IF(OR(M64="",L64=""),"",M64/L64) -> 0.0068123393 | V64: =IF(ISTEXT(C64),"글자 섞임",ROUND(C64*VLOOKUP(N64,'환율_기준일'!$A$4:$E$7,5,FALSE)/'환율_기준일'!$E$4,2)) -> 0 | W64: =IF(ISNUMBER(V64),IF(V64>F64*10,1,0),"") -> 0 | X64: =IF(Q64=1,COUNTIF($Q$2:Q64,1),"")
A65: B064 | B65: USD | C65: 11137 | D65: 11137 | E65: 0 | F65: 70000 | G65: 137605000 | H65: 69712000 | I65: 151442000 | J65: 252633000 | K65: 69910000 | L65: 437380000 | M65: 46440000 | N65: =IFERROR(VLOOKUP(TRIM(B65),'확인표_A'!$A$6:$B$14,2,FALSE),"확인 필요") -> USD | O65: =SUMPRODUCT(--ISTEXT(C65:E65)) -> 0 | P65: =IF(OR(G65="",H65="",I65="",J65="",L65=""),1,0) -> 0 | Q65: =IF(AND(J65<>"",J65<=0),1,0) -> 0 | R65: =IF(OR(G65="",H65=""),"",G65/H65) -> 1.9739069 | S65: =IF(OR(I65="",J65="",Q65=1),"",I65/J65) -> 0.59945454 | T65: =IF(OR(K65="",L65=""),"",K65/L65*365) -> 58.340916 | U65: =IF(OR(M65="",L65=""),"",M65/L65) -> 0.10617769 | V65: =IF(ISTEXT(C65),"글자 섞임",ROUND(C65*VLOOKUP(N65,'환율_기준일'!$A$4:$E$7,5,FALSE)/'환율_기준일'!$E$4,2)) -> 11137 | W65: =IF(ISNUMBER(V65),IF(V65>F65*10,1,0),"") -> 0 | X65: =IF(Q65=1,COUNTIF($Q$2:Q65,1),"")
A66: B065 | B66: usd | C66: 0 | D66: 0 | E66: 0 | F66: 10000 | G66: 65741000 | I66: 78504000 | L66: 218133000 | M66: 23792000 | N66: =IFERROR(VLOOKUP(TRIM(B66),'확인표_A'!$A$6:$B$14,2,FALSE),"확인 필요") -> USD | O66: =SUMPRODUCT(--ISTEXT(C66:E66)) -> 0 | P66: =IF(OR(G66="",H66="",I66="",J66="",L66=""),1,0) -> 1 | Q66: =IF(AND(J66<>"",J66<=0),1,0) -> 0 | R66: =IF(OR(G66="",H66=""),"",G66/H66) | S66: =IF(OR(I66="",J66="",Q66=1),"",I66/J66) | T66: =IF(OR(K66="",L66=""),"",K66/L66*365) | U66: =IF(OR(M66="",L66=""),"",M66/L66) -> 0.10907107 | V66: =IF(ISTEXT(C66),"글자 섞임",ROUND(C66*VLOOKUP(N66,'환율_기준일'!$A$4:$E$7,5,FALSE)/'환율_기준일'!$E$4,2)) -> 0 | W66: =IF(ISNUMBER(V66),IF(V66>F66*10,1,0),"") -> 0 | X66: =IF(Q66=1,COUNTIF($Q$2:Q66,1),"")
A67: B066 | B67: USD | C67: 67070 | D67: 67070 | E67: 0 | F67: 140000 | G67: 48379000 | H67: 40764000 | I67: 72942000 | K67: 17251000 | L67: 166249000 | M67: 11154000 | N67: =IFERROR(VLOOKUP(TRIM(B67),'확인표_A'!$A$6:$B$14,2,FALSE),"확인 필요") -> USD | O67: =SUMPRODUCT(--ISTEXT(C67:E67)) -> 0 | P67: =IF(OR(G67="",H67="",I67="",J67="",L67=""),1,0) -> 1 | Q67: =IF(AND(J67<>"",J67<=0),1,0) -> 0 | R67: =IF(OR(G67="",H67=""),"",G67/H67) -> 1.186807 | S67: =IF(OR(I67="",J67="",Q67=1),"",I67/J67) | T67: =IF(OR(K67="",L67=""),"",K67/L67*365) -> 37.874604 | U67: =IF(OR(M67="",L67=""),"",M67/L67) -> 0.067092133 | V67: =IF(ISTEXT(C67),"글자 섞임",ROUND(C67*VLOOKUP(N67,'환율_기준일'!$A$4:$E$7,5,FALSE)/'환율_기준일'!$E$4,2)) -> 67070 | W67: =IF(ISNUMBER(V67),IF(V67>F67*10,1,0),"") -> 0 | X67: =IF(Q67=1,COUNTIF($Q$2:Q67,1),"")
A68: B067 | B68: USD | C68: 0 | D68: 0 | E68: 0 | F68: 10000 | N68: =IFERROR(VLOOKUP(TRIM(B68),'확인표_A'!$A$6:$B$14,2,FALSE),"확인 필요") -> USD | O68: =SUMPRODUCT(--ISTEXT(C68:E68)) -> 0 | P68: =IF(OR(G68="",H68="",I68="",J68="",L68=""),1,0) -> 1 | Q68: =IF(AND(J68<>"",J68<=0),1,0) -> 0 | R68: =IF(OR(G68="",H68=""),"",G68/H68) | S68: =IF(OR(I68="",J68="",Q68=1),"",I68/J68) | T68: =IF(OR(K68="",L68=""),"",K68/L68*365) | U68: =IF(OR(M68="",L68=""),"",M68/L68) | V68: =IF(ISTEXT(C68),"글자 섞임",ROUND(C68*VLOOKUP(N68,'환율_기준일'!$A$4:$E$7,5,FALSE)/'환율_기준일'!$E$4,2)) -> 0 | W68: =IF(ISNUMBER(V68),IF(V68>F68*10,1,0),"") -> 0 | X68: =IF(Q68=1,COUNTIF($Q$2:Q68,1),"")
A69: B068 | B69: USD | C69: 164860 | D69: 109420 | E69: 55440 | F69: 80000 | G69: 376164000 | I69: 575013000 | J69: 188396000 | K69: 126096000 | L69: 656839000 | M69: 40295000 | N69: =IFERROR(VLOOKUP(TRIM(B69),'확인표_A'!$A$6:$B$14,2,FALSE),"확인 필요") -> USD | O69: =SUMPRODUCT(--ISTEXT(C69:E69)) -> 0 | P69: =IF(OR(G69="",H69="",I69="",J69="",L69=""),1,0) -> 1 | Q69: =IF(AND(J69<>"",J69<=0),1,0) -> 0 | R69: =IF(OR(G69="",H69=""),"",G69/H69) | S69: =IF(OR(I69="",J69="",Q69=1),"",I69/J69) -> 3.0521508 | T69: =IF(OR(K69="",L69=""),"",K69/L69*365) -> 70.070504 | U69: =IF(OR(M69="",L69=""),"",M69/L69) -> 0.061346845 | V69: =IF(ISTEXT(C69),"글자 섞임",ROUND(C69*VLOOKUP(N69,'환율_기준일'!$A$4:$E$7,5,FALSE)/'환율_기준일'!$E$4,2)) -> 164860 | W69: =IF(ISNUMBER(V69),IF(V69>F69*10,1,0),"") -> 0 | X69: =IF(Q69=1,COUNTIF($Q$2:Q69,1),"")
A70: B069 | B70: US$ | C70: 0 | D70: 0 | E70: 0 | F70: 10000 | N70: =IFERROR(VLOOKUP(TRIM(B70),'확인표_A'!$A$6:$B$14,2,FALSE),"확인 필요") -> USD | O70: =SUMPRODUCT(--ISTEXT(C70:E70)) -> 0 | P70: =IF(OR(G70="",H70="",I70="",J70="",L70=""),1,0) -> 1 | Q70: =IF(AND(J70<>"",J70<=0),1,0) -> 0 | R70: =IF(OR(G70="",H70=""),"",G70/H70) | S70: =IF(OR(I70="",J70="",Q70=1),"",I70/J70) | T70: =IF(OR(K70="",L70=""),"",K70/L70*365) | U70: =IF(OR(M70="",L70=""),"",M70/L70) | V70: =IF(ISTEXT(C70),"글자 섞임",ROUND(C70*VLOOKUP(N70,'환율_기준일'!$A$4:$E$7,5,FALSE)/'환율_기준일'!$E$4,2)) -> 0 | W70: =IF(ISNUMBER(V70),IF(V70>F70*10,1,0),"") -> 0 | X70: =IF(Q70=1,COUNTIF($Q$2:Q70,1),"")
A71: B070 | B71: EUR | C71: 7380 | D71: 7380 | E71: 0 | F71: 30000 | G71: 17518000 | H71: 11466000 | I71: 19732000 | J71: 10861000 | K71: 9210000 | L71: 34816000 | M71: 2516000 | N71: =IFERROR(VLOOKUP(TRIM(B71),'확인표_A'!$A$6:$B$14,2,FALSE),"확인 필요") -> EUR | O71: =SUMPRODUCT(--ISTEXT(C71:E71)) -> 0 | P71: =IF(OR(G71="",H71="",I71="",J71="",L71=""),1,0) -> 0 | Q71: =IF(AND(J71<>"",J71<=0),1,0) -> 0 | R71: =IF(OR(G71="",H71=""),"",G71/H71) -> 1.5278214 | S71: =IF(OR(I71="",J71="",Q71=1),"",I71/J71) -> 1.8167756 | T71: =IF(OR(K71="",L71=""),"",K71/L71*365) -> 96.554745 | U71: =IF(OR(M71="",L71=""),"",M71/L71) -> 0.072265625 | V71: =IF(ISTEXT(C71),"글자 섞임",ROUND(C71*VLOOKUP(N71,'환율_기준일'!$A$4:$E$7,5,FALSE)/'환율_기준일'!$E$4,2)) -> 8573.37 | W71: =IF(ISNUMBER(V71),IF(V71>F71*10,1,0),"") -> 0 | X71: =IF(Q71=1,COUNTIF($Q$2:Q71,1),"")
A72: B071 | B72: USD | C72: 65000 | D72: 0 | E72: 0 | F72: 20000 | G72: 37837000 | H72: 50753000 | I72: 106526000 | J72: 52223000 | K72: 17256000 | L72: 51338000 | M72: -2657000 | N72: =IFERROR(VLOOKUP(TRIM(B72),'확인표_A'!$A$6:$B$14,2,FALSE),"확인 필요") -> USD | O72: =SUMPRODUCT(--ISTEXT(C72:E72)) -> 0 | P72: =IF(OR(G72="",H72="",I72="",J72="",L72=""),1,0) -> 0 | Q72: =IF(AND(J72<>"",J72<=0),1,0) -> 0 | R72: =IF(OR(G72="",H72=""),"",G72/H72) -> 0.74551258 | S72: =IF(OR(I72="",J72="",Q72=1),"",I72/J72) -> 2.0398292 | T72: =IF(OR(K72="",L72=""),"",K72/L72*365) -> 122.68573 | U72: =IF(OR(M72="",L72=""),"",M72/L72) -> -0.051755035 | V72: =IF(ISTEXT(C72),"글자 섞임",ROUND(C72*VLOOKUP(N72,'환율_기준일'!$A$4:$E$7,5,FALSE)/'환율_기준일'!$E$4,2)) -> 65000 | W72: =IF(ISNUMBER(V72),IF(V72>F72*10,1,0),"") -> 0 | X72: =IF(Q72=1,COUNTIF($Q$2:Q72,1),"")
A73: B072 | B73: euro | C73: 8320000 | D73: 0 | E73: 8,320 | F73: 10000 | G73: 9343000 | H73: 7731000 | I73: 13382000 | J73: 6122000 | K73: 4148000 | L73: 22733000 | M73: 433000 | N73: =IFERROR(VLOOKUP(TRIM(B73),'확인표_A'!$A$6:$B$14,2,FALSE),"확인 필요") -> EUR | O73: =SUMPRODUCT(--ISTEXT(C73:E73)) -> 1 | P73: =IF(OR(G73="",H73="",I73="",J73="",L73=""),1,0) -> 0 | Q73: =IF(AND(J73<>"",J73<=0),1,0) -> 0 | R73: =IF(OR(G73="",H73=""),"",G73/H73) -> 1.2085112 | S73: =IF(OR(I73="",J73="",Q73=1),"",I73/J73) -> 2.185887 | T73: =IF(OR(K73="",L73=""),"",K73/L73*365) -> 66.600097 | U73: =IF(OR(M73="",L73=""),"",M73/L73) -> 0.0190472 | V73: =IF(ISTEXT(C73),"글자 섞임",ROUND(C73*VLOOKUP(N73,'환율_기준일'!$A$4:$E$7,5,FALSE)/'환율_기준일'!$E$4,2)) -> 9665368.2 | W73: =IF(ISNUMBER(V73),IF(V73>F73*10,1,0),"") -> 1 | X73: =IF(Q73=1,COUNTIF($Q$2:Q73,1),"")
A74: B073 | B74: US$ | C74: 53380 | D74: 48270 | E74: 5110 | F74: 30000 | G74: 34439000 | H74: 23732000 | I74: 30240000 | J74: 16653000 | K74: 11700000 | L74: 61234000 | M74: 2255000 | N74: =IFERROR(VLOOKUP(TRIM(B74),'확인표_A'!$A$6:$B$14,2,FALSE),"확인 필요") -> USD | O74: =SUMPRODUCT(--ISTEXT(C74:E74)) -> 0 | P74: =IF(OR(G74="",H74="",I74="",J74="",L74=""),1,0) -> 0 | Q74: =IF(AND(J74<>"",J74<=0),1,0) -> 0 | R74: =IF(OR(G74="",H74=""),"",G74/H74) -> 1.451163 | S74: =IF(OR(I74="",J74="",Q74=1),"",I74/J74) -> 1.815889 | T74: =IF(OR(K74="",L74=""),"",K74/L74*365) -> 69.740667 | U74: =IF(OR(M74="",L74=""),"",M74/L74) -> 0.036825946 | V74: =IF(ISTEXT(C74),"글자 섞임",ROUND(C74*VLOOKUP(N74,'환율_기준일'!$A$4:$E$7,5,FALSE)/'환율_기준일'!$E$4,2)) -> 53380 | W74: =IF(ISNUMBER(V74),IF(V74>F74*10,1,0),"") -> 0 | X74: =IF(Q74=1,COUNTIF($Q$2:Q74,1),"")
A75: B074 | B75: USD | C75: 5140 | D75: 5140 | E75: 0 | F75: 10000 | G75: 26299000 | H75: 24228000 | I75: 31062000 | J75: 13128000 | K75: 11975000 | L75: 41388000 | M75: 1045000 | N75: =IFERROR(VLOOKUP(TRIM(B75),'확인표_A'!$A$6:$B$14,2,FALSE),"확인 필요") -> USD | O75: =SUMPRODUCT(--ISTEXT(C75:E75)) -> 0 | P75: =IF(OR(G75="",H75="",I75="",J75="",L75=""),1,0) -> 0 | Q75: =IF(AND(J75<>"",J75<=0),1,0) -> 0 | R75: =IF(OR(G75="",H75=""),"",G75/H75) -> 1.0854796 | S75: =IF(OR(I75="",J75="",Q75=1),"",I75/J75) -> 2.3660878 | T75: =IF(OR(K75="",L75=""),"",K75/L75*365) -> 105.6073 | U75: =IF(OR(M75="",L75=""),"",M75/L75) -> 0.025248864 | V75: =IF(ISTEXT(C75),"글자 섞임",ROUND(C75*VLOOKUP(N75,'환율_기준일'!$A$4:$E$7,5,FALSE)/'환율_기준일'!$E$4,2)) -> 5140 | W75: =IF(ISNUMBER(V75),IF(V75>F75*10,1,0),"") -> 0 | X75: =IF(Q75=1,COUNTIF($Q$2:Q75,1),"")
A76: B075 | B76: euro | C76: 4710 | D76: 0 | E76: 0 | F76: 20000 | G76: 11049000 | I76: 16725000 | L76: 39424000 | M76: 4256000 | N76: =IFERROR(VLOOKUP(TRIM(B76),'확인표_A'!$A$6:$B$14,2,FALSE),"확인 필요") -> EUR | O76: =SUMPRODUCT(--ISTEXT(C76:E76)) -> 0 | P76: =IF(OR(G76="",H76="",I76="",J76="",L76=""),1,0) -> 1 | Q76: =IF(AND(J76<>"",J76<=0),1,0) -> 0 | R76: =IF(OR(G76="",H76=""),"",G76/H76) | S76: =IF(OR(I76="",J76="",Q76=1),"",I76/J76) | T76: =IF(OR(K76="",L76=""),"",K76/L76*365) | U76: =IF(OR(M76="",L76=""),"",M76/L76) -> 0.10795455 | V76: =IF(ISTEXT(C76),"글자 섞임",ROUND(C76*VLOOKUP(N76,'환율_기준일'!$A$4:$E$7,5,FALSE)/'환율_기준일'!$E$4,2)) -> 5471.62 | W76: =IF(ISNUMBER(V76),IF(V76>F76*10,1,0),"") -> 0 | X76: =IF(Q76=1,COUNTIF($Q$2:Q76,1),"")
A77: B076 | B77: EUR | C77: 51970 | D77: 51,970 | E77: 0 | F77: 30000 | G77: 2089000 | I77: 1666000 | J77: 3113000 | K77: 938000 | L77: 7585000 | M77: 1174000 | N77: =IFERROR(VLOOKUP(TRIM(B77),'확인표_A'!$A$6:$B$14,2,FALSE),"확인 필요") -> EUR | O77: =SUMPRODUCT(--ISTEXT(C77:E77)) -> 1 | P77: =IF(OR(G77="",H77="",I77="",J77="",L77=""),1,0) -> 1 | Q77: =IF(AND(J77<>"",J77<=0),1,0) -> 0 | R77: =IF(OR(G77="",H77=""),"",G77/H77) | S77: =IF(OR(I77="",J77="",Q77=1),"",I77/J77) -> 0.53517507 | T77: =IF(OR(K77="",L77=""),"",K77/L77*365) -> 45.137772 | U77: =IF(OR(M77="",L77=""),"",M77/L77) -> 0.15477917 | V77: =IF(ISTEXT(C77),"글자 섞임",ROUND(C77*VLOOKUP(N77,'환율_기준일'!$A$4:$E$7,5,FALSE)/'환율_기준일'!$E$4,2)) -> 60373.7 | W77: =IF(ISNUMBER(V77),IF(V77>F77*10,1,0),"") -> 0 | X77: =IF(Q77=1,COUNTIF($Q$2:Q77,1),"")
A78: B077 | B78: USD | C78: 0 | D78: 0 | E78: 0 | F78: 10000 | G78: 10625000 | H78: 11560000 | I78: 24662000 | K78: 5865000 | L78: 14578000 | M78: -264000 | N78: =IFERROR(VLOOKUP(TRIM(B78),'확인표_A'!$A$6:$B$14,2,FALSE),"확인 필요") -> USD | O78: =SUMPRODUCT(--ISTEXT(C78:E78)) -> 0 | P78: =IF(OR(G78="",H78="",I78="",J78="",L78=""),1,0) -> 1 | Q78: =IF(AND(J78<>"",J78<=0),1,0) -> 0 | R78: =IF(OR(G78="",H78=""),"",G78/H78) -> 0.91911765 | S78: =IF(OR(I78="",J78="",Q78=1),"",I78/J78) | T78: =IF(OR(K78="",L78=""),"",K78/L78*365) -> 146.84628 | U78: =IF(OR(M78="",L78=""),"",M78/L78) -> -0.01810948 | V78: =IF(ISTEXT(C78),"글자 섞임",ROUND(C78*VLOOKUP(N78,'환율_기준일'!$A$4:$E$7,5,FALSE)/'환율_기준일'!$E$4,2)) -> 0 | W78: =IF(ISNUMBER(V78),IF(V78>F78*10,1,0),"") -> 0 | X78: =IF(Q78=1,COUNTIF($Q$2:Q78,1),"")
A79: B078 | B79: USD | C79: 0 | D79: 0 | E79: 0 | F79: 10000 | G79: 33947000 | H79: 33033000 | I79: 54209000 | J79: 30894000 | K79: 14880000 | L79: 53852000 | M79: 374000 | N79: =IFERROR(VLOOKUP(TRIM(B79),'확인표_A'!$A$6:$B$14,2,FALSE),"확인 필요") -> USD | O79: =SUMPRODUCT(--ISTEXT(C79:E79)) -> 0 | P79: =IF(OR(G79="",H79="",I79="",J79="",L79=""),1,0) -> 0 | Q79: =IF(AND(J79<>"",J79<=0),1,0) -> 0 | R79: =IF(OR(G79="",H79=""),"",G79/H79) -> 1.0276693 | S79: =IF(OR(I79="",J79="",Q79=1),"",I79/J79) -> 1.7546773 | T79: =IF(OR(K79="",L79=""),"",K79/L79*365) -> 100.85419 | U79: =IF(OR(M79="",L79=""),"",M79/L79) -> 0.0069449603 | V79: =IF(ISTEXT(C79),"글자 섞임",ROUND(C79*VLOOKUP(N79,'환율_기준일'!$A$4:$E$7,5,FALSE)/'환율_기준일'!$E$4,2)) -> 0 | W79: =IF(ISNUMBER(V79),IF(V79>F79*10,1,0),"") -> 0 | X79: =IF(Q79=1,COUNTIF($Q$2:Q79,1),"")
A80: B079 | B80: JPY | C80: 9224000 | D80: 9224000 | E80: 0 | F80: 50000 | G80: 79202000 | H80: 36924000 | I80: 63783000 | J80: 226771000 | K80: 28108000 | L80: 234899000 | M80: 29299000 | N80: =IFERROR(VLOOKUP(TRIM(B80),'확인표_A'!$A$6:$B$14,2,FALSE),"확인 필요") -> JPY | O80: =SUMPRODUCT(--ISTEXT(C80:E80)) -> 0 | P80: =IF(OR(G80="",H80="",I80="",J80="",L80=""),1,0) -> 0 | Q80: =IF(AND(J80<>"",J80<=0),1,0) -> 0 | R80: =IF(OR(G80="",H80=""),"",G80/H80) -> 2.1450005 | S80: =IF(OR(I80="",J80="",Q80=1),"",I80/J80) -> 0.28126612 | T80: =IF(OR(K80="",L80=""),"",K80/L80*365) -> 43.675878 | U80: =IF(OR(M80="",L80=""),"",M80/L80) -> 0.1247302 | V80: =IF(ISTEXT(C80),"글자 섞임",ROUND(C80*VLOOKUP(N80,'환율_기준일'!$A$4:$E$7,5,FALSE)/'환율_기준일'!$E$4,2)) -> 57743.96 | W80: =IF(ISNUMBER(V80),IF(V80>F80*10,1,0),"") -> 0 | X80: =IF(Q80=1,COUNTIF($Q$2:Q80,1),"")
A81: B080 | B81: JPY | C81: 3149000 | D81: 3149000 | E81: 0 | F81: 10000 | G81: 13504000 | H81: 8244000 | I81: 16786000 | J81: 22651000 | K81: 5825000 | L81: 40446000 | M81: 3239000 | N81: =IFERROR(VLOOKUP(TRIM(B81),'확인표_A'!$A$6:$B$14,2,FALSE),"확인 필요") -> JPY | O81: =SUMPRODUCT(--ISTEXT(C81:E81)) -> 0 | P81: =IF(OR(G81="",H81="",I81="",J81="",L81=""),1,0) -> 0 | Q81: =IF(AND(J81<>"",J81<=0),1,0) -> 0 | R81: =IF(OR(G81="",H81=""),"",G81/H81) -> 1.6380398 | S81: =IF(OR(I81="",J81="",Q81=1),"",I81/J81) -> 0.74107103 | T81: =IF(OR(K81="",L81=""),"",K81/L81*365) -> 52.567003 | U81: =IF(OR(M81="",L81=""),"",M81/L81) -> 0.080082085 | V81: =IF(ISTEXT(C81),"글자 섞임",ROUND(C81*VLOOKUP(N81,'환율_기준일'!$A$4:$E$7,5,FALSE)/'환율_기준일'!$E$4,2)) -> 19713.33 | W81: =IF(ISNUMBER(V81),IF(V81>F81*10,1,0),"") -> 0 | X81: =IF(Q81=1,COUNTIF($Q$2:Q81,1),"")
A82: B081 | B82: JPY | C82: 5522000 | D82: 5522000 | E82: 0 | F82: 30000 | N82: =IFERROR(VLOOKUP(TRIM(B82),'확인표_A'!$A$6:$B$14,2,FALSE),"확인 필요") -> JPY | O82: =SUMPRODUCT(--ISTEXT(C82:E82)) -> 0 | P82: =IF(OR(G82="",H82="",I82="",J82="",L82=""),1,0) -> 1 | Q82: =IF(AND(J82<>"",J82<=0),1,0) -> 0 | R82: =IF(OR(G82="",H82=""),"",G82/H82) | S82: =IF(OR(I82="",J82="",Q82=1),"",I82/J82) | T82: =IF(OR(K82="",L82=""),"",K82/L82*365) | U82: =IF(OR(M82="",L82=""),"",M82/L82) | V82: =IF(ISTEXT(C82),"글자 섞임",ROUND(C82*VLOOKUP(N82,'환율_기준일'!$A$4:$E$7,5,FALSE)/'환율_기준일'!$E$4,2)) -> 34568.75 | W82: =IF(ISNUMBER(V82),IF(V82>F82*10,1,0),"") -> 0 | X82: =IF(Q82=1,COUNTIF($Q$2:Q82,1),"")
A83: B082 | B83: yen | C83: 11200000 | D83: 11200000 | E83: 0 | F83: 50000 | G83: 179551000 | H83: 101617000 | I83: 146785000 | J83: 88032000 | K83: 69820000 | L83: 364351000 | M83: 13923000 | N83: =IFERROR(VLOOKUP(TRIM(B83),'확인표_A'!$A$6:$B$14,2,FALSE),"확인 필요") -> JPY | O83: =SUMPRODUCT(--ISTEXT(C83:E83)) -> 0 | P83: =IF(OR(G83="",H83="",I83="",J83="",L83=""),1,0) -> 0 | Q83: =IF(AND(J83<>"",J83<=0),1,0) -> 0 | R83: =IF(OR(G83="",H83=""),"",G83/H83) -> 1.7669386 | S83: =IF(OR(I83="",J83="",Q83=1),"",I83/J83) -> 1.667405 | T83: =IF(OR(K83="",L83=""),"",K83/L83*365) -> 69.944367 | U83: =IF(OR(M83="",L83=""),"",M83/L83) -> 0.038213152 | V83: =IF(ISTEXT(C83),"글자 섞임",ROUND(C83*VLOOKUP(N83,'환율_기준일'!$A$4:$E$7,5,FALSE)/'환율_기준일'!$E$4,2)) -> 70114.09 | W83: =IF(ISNUMBER(V83),IF(V83>F83*10,1,0),"") -> 0 | X83: =IF(Q83=1,COUNTIF($Q$2:Q83,1),"")
A84: B083 | B84: USD | C84: 2,200 | D84: 0 | E84: 0 | F84: 10000 | G84: 2210000 | H84: 2408000 | I84: 4587000 | J84: 1104000 | K84: 1053000 | L84: 4578000 | M84: -195000 | N84: =IFERROR(VLOOKUP(TRIM(B84),'확인표_A'!$A$6:$B$14,2,FALSE),"확인 필요") -> USD | O84: =SUMPRODUCT(--ISTEXT(C84:E84)) -> 1 | P84: =IF(OR(G84="",H84="",I84="",J84="",L84=""),1,0) -> 0 | Q84: =IF(AND(J84<>"",J84<=0),1,0) -> 0 | R84: =IF(OR(G84="",H84=""),"",G84/H84) -> 0.91777409 | S84: =IF(OR(I84="",J84="",Q84=1),"",I84/J84) -> 4.1548913 | T84: =IF(OR(K84="",L84=""),"",K84/L84*365) -> 83.954784 | U84: =IF(OR(M84="",L84=""),"",M84/L84) -> -0.04259502 | V84: =IF(ISTEXT(C84),"글자 섞임",ROUND(C84*VLOOKUP(N84,'환율_기준일'!$A$4:$E$7,5,FALSE)/'환율_기준일'!$E$4,2)) -> 글자 섞임 | W84: =IF(ISNUMBER(V84),IF(V84>F84*10,1,0),"") | X84: =IF(Q84=1,COUNTIF($Q$2:Q84,1),"")
A85: B084 | B85: euro | C85: 23200 | D85: 23200 | E85: 0 | F85: 110000 | G85: 155271000 | H85: 63601000 | I85: 113895000 | J85: 278816000 | K85: 74368000 | L85: 530436000 | M85: 74685000 | N85: =IFERROR(VLOOKUP(TRIM(B85),'확인표_A'!$A$6:$B$14,2,FALSE),"확인 필요") -> EUR | O85: =SUMPRODUCT(--ISTEXT(C85:E85)) -> 0 | P85: =IF(OR(G85="",H85="",I85="",J85="",L85=""),1,0) -> 0 | Q85: =IF(AND(J85<>"",J85<=0),1,0) -> 0 | R85: =IF(OR(G85="",H85=""),"",G85/H85) -> 2.4413295 | S85: =IF(OR(I85="",J85="",Q85=1),"",I85/J85) -> 0.40849521 | T85: =IF(OR(K85="",L85=""),"",K85/L85*365) -> 51.173601 | U85: =IF(OR(M85="",L85=""),"",M85/L85) -> 0.14079927 | V85: =IF(ISTEXT(C85),"글자 섞임",ROUND(C85*VLOOKUP(N85,'환율_기준일'!$A$4:$E$7,5,FALSE)/'환율_기준일'!$E$4,2)) -> 26951.51 | W85: =IF(ISNUMBER(V85),IF(V85>F85*10,1,0),"") -> 0 | X85: =IF(Q85=1,COUNTIF($Q$2:Q85,1),"")
A86: B085 | B86: USD | C86: 103500 | D86: 103500 | E86: 0 | F86: 70000 | G86: 9462000 | H86: 3926000 | I86: 6206000 | J86: 13491000 | K86: 5018000 | L86: 48200000 | M86: 7037000 | N86: =IFERROR(VLOOKUP(TRIM(B86),'확인표_A'!$A$6:$B$14,2,FALSE),"확인 필요") -> USD | O86: =SUMPRODUCT(--ISTEXT(C86:E86)) -> 0 | P86: =IF(OR(G86="",H86="",I86="",J86="",L86=""),1,0) -> 0 | Q86: =IF(AND(J86<>"",J86<=0),1,0) -> 0 | R86: =IF(OR(G86="",H86=""),"",G86/H86) -> 2.4100866 | S86: =IF(OR(I86="",J86="",Q86=1),"",I86/J86) -> 0.46001038 | T86: =IF(OR(K86="",L86=""),"",K86/L86*365) -> 37.999378 | U86: =IF(OR(M86="",L86=""),"",M86/L86) -> 0.14599585 | V86: =IF(ISTEXT(C86),"글자 섞임",ROUND(C86*VLOOKUP(N86,'환율_기준일'!$A$4:$E$7,5,FALSE)/'환율_기준일'!$E$4,2)) -> 103500 | W86: =IF(ISNUMBER(V86),IF(V86>F86*10,1,0),"") -> 0 | X86: =IF(Q86=1,COUNTIF($Q$2:Q86,1),"")
A87: B086 | B87: EUR | C87: EUR 143,620 | D87: 143620 | E87: 0 | F87: 250000 | G87: 147242000 | H87: 60715000 | I87: 76320000 | J87: 71730000 | K87: 65076000 | L87: 412770000 | M87: 71817000 | N87: =IFERROR(VLOOKUP(TRIM(B87),'확인표_A'!$A$6:$B$14,2,FALSE),"확인 필요") -> EUR | O87: =SUMPRODUCT(--ISTEXT(C87:E87)) -> 1 | P87: =IF(OR(G87="",H87="",I87="",J87="",L87=""),1,0) -> 0 | Q87: =IF(AND(J87<>"",J87<=0),1,0) -> 0 | R87: =IF(OR(G87="",H87=""),"",G87/H87) -> 2.4251338 | S87: =IF(OR(I87="",J87="",Q87=1),"",I87/J87) -> 1.06399 | T87: =IF(OR(K87="",L87=""),"",K87/L87*365) -> 57.544734 | U87: =IF(OR(M87="",L87=""),"",M87/L87) -> 0.17398794 | V87: =IF(ISTEXT(C87),"글자 섞임",ROUND(C87*VLOOKUP(N87,'환율_기준일'!$A$4:$E$7,5,FALSE)/'환율_기준일'!$E$4,2)) -> 글자 섞임 | W87: =IF(ISNUMBER(V87),IF(V87>F87*10,1,0),"") | X87: =IF(Q87=1,COUNTIF($Q$2:Q87,1),"")
A88: B087 | B88: USD | C88: 71620 | D88: 31048 | E88: 40572 | F88: 150000 | G88: 168777000 | H88: 216033000 | I88: 306822000 | J88: 75727000 | K88: 89592000 | L88: 417625000 | M88: -31374000 | N88: =IFERROR(VLOOKUP(TRIM(B88),'확인표_A'!$A$6:$B$14,2,FALSE),"확인 필요") -> USD | O88: =SUMPRODUCT(--ISTEXT(C88:E88)) -> 0 | P88: =IF(OR(G88="",H88="",I88="",J88="",L88=""),1,0) -> 0 | Q88: =IF(AND(J88<>"",J88<=0),1,0) -> 0 | R88: =IF(OR(G88="",H88=""),"",G88/H88) -> 0.78125564 | S88: =IF(OR(I88="",J88="",Q88=1),"",I88/J88) -> 4.0516857 | T88: =IF(OR(K88="",L88=""),"",K88/L88*365) -> 78.302496 | U88: =IF(OR(M88="",L88=""),"",M88/L88) -> -0.075124813 | V88: =IF(ISTEXT(C88),"글자 섞임",ROUND(C88*VLOOKUP(N88,'환율_기준일'!$A$4:$E$7,5,FALSE)/'환율_기준일'!$E$4,2)) -> 71620 | W88: =IF(ISNUMBER(V88),IF(V88>F88*10,1,0),"") -> 0 | X88: =IF(Q88=1,COUNTIF($Q$2:Q88,1),"")
A89: B088 | B89: USD | C89: 0 | D89: 0 | E89: 0 | F89: 20000 | G89: 112113000 | H89: 98148000 | I89: 124717000 | J89: 46172000 | L89: 260702000 | M89: 29027000 | N89: =IFERROR(VLOOKUP(TRIM(B89),'확인표_A'!$A$6:$B$14,2,FALSE),"확인 필요") -> USD | O89: =SUMPRODUCT(--ISTEXT(C89:E89)) -> 0 | P89: =IF(OR(G89="",H89="",I89="",J89="",L89=""),1,0) -> 0 | Q89: =IF(AND(J89<>"",J89<=0),1,0) -> 0 | R89: =IF(OR(G89="",H89=""),"",G89/H89) -> 1.1422851 | S89: =IF(OR(I89="",J89="",Q89=1),"",I89/J89) -> 2.7011392 | T89: =IF(OR(K89="",L89=""),"",K89/L89*365) | U89: =IF(OR(M89="",L89=""),"",M89/L89) -> 0.11134169 | V89: =IF(ISTEXT(C89),"글자 섞임",ROUND(C89*VLOOKUP(N89,'환율_기준일'!$A$4:$E$7,5,FALSE)/'환율_기준일'!$E$4,2)) -> 0 | W89: =IF(ISNUMBER(V89),IF(V89>F89*10,1,0),"") -> 0 | X89: =IF(Q89=1,COUNTIF($Q$2:Q89,1),"")
A90: B089 | B90: USD | C90: 0 | D90: 0 | E90: 0 | F90: 10000 | G90: 8289000 | H90: 6290000 | I90: 8796000 | J90: 4978000 | K90: 3931000 | L90: 11100000 | N90: =IFERROR(VLOOKUP(TRIM(B90),'확인표_A'!$A$6:$B$14,2,FALSE),"확인 필요") -> USD | O90: =SUMPRODUCT(--ISTEXT(C90:E90)) -> 0 | P90: =IF(OR(G90="",H90="",I90="",J90="",L90=""),1,0) -> 0 | Q90: =IF(AND(J90<>"",J90<=0),1,0) -> 0 | R90: =IF(OR(G90="",H90=""),"",G90/H90) -> 1.317806 | S90: =IF(OR(I90="",J90="",Q90=1),"",I90/J90) -> 1.7669747 | T90: =IF(OR(K90="",L90=""),"",K90/L90*365) -> 129.26261 | U90: =IF(OR(M90="",L90=""),"",M90/L90) | V90: =IF(ISTEXT(C90),"글자 섞임",ROUND(C90*VLOOKUP(N90,'환율_기준일'!$A$4:$E$7,5,FALSE)/'환율_기준일'!$E$4,2)) -> 0 | W90: =IF(ISNUMBER(V90),IF(V90>F90*10,1,0),"") -> 0 | X90: =IF(Q90=1,COUNTIF($Q$2:Q90,1),"")
A91: B090 | B91: USD | C91: 0 | D91: 0 | E91: 0 | F91: 10000 | G91: 3743000 | H91: 2636000 | I91: 4491000 | J91: 1712000 | K91: 1430000 | L91: 8275000 | M91: 174000 | N91: =IFERROR(VLOOKUP(TRIM(B91),'확인표_A'!$A$6:$B$14,2,FALSE),"확인 필요") -> USD | O91: =SUMPRODUCT(--ISTEXT(C91:E91)) -> 0 | P91: =IF(OR(G91="",H91="",I91="",J91="",L91=""),1,0) -> 0 | Q91: =IF(AND(J91<>"",J91<=0),1,0) -> 0 | R91: =IF(OR(G91="",H91=""),"",G91/H91) -> 1.4199545 | S91: =IF(OR(I91="",J91="",Q91=1),"",I91/J91) -> 2.6232477 | T91: =IF(OR(K91="",L91=""),"",K91/L91*365) -> 63.075529 | U91: =IF(OR(M91="",L91=""),"",M91/L91) -> 0.02102719 | V91: =IF(ISTEXT(C91),"글자 섞임",ROUND(C91*VLOOKUP(N91,'환율_기준일'!$A$4:$E$7,5,FALSE)/'환율_기준일'!$E$4,2)) -> 0 | W91: =IF(ISNUMBER(V91),IF(V91>F91*10,1,0),"") -> 0 | X91: =IF(Q91=1,COUNTIF($Q$2:Q91,1),"")
A92: B091 | B92: EUR | C92: 7980 | D92: 7,980 | E92: 0 | F92: 20000 | G92: 2944000 | H92: 1729000 | I92: 2987000 | J92: 2406000 | K92: 1048000 | L92: 5745000 | M92: 562000 | N92: =IFERROR(VLOOKUP(TRIM(B92),'확인표_A'!$A$6:$B$14,2,FALSE),"확인 필요") -> EUR | O92: =SUMPRODUCT(--ISTEXT(C92:E92)) -> 1 | P92: =IF(OR(G92="",H92="",I92="",J92="",L92=""),1,0) -> 0 | Q92: =IF(AND(J92<>"",J92<=0),1,0) -> 0 | R92: =IF(OR(G92="",H92=""),"",G92/H92) -> 1.7027183 | S92: =IF(OR(I92="",J92="",Q92=1),"",I92/J92) -> 1.2414796 | T92: =IF(OR(K92="",L92=""),"",K92/L92*365) -> 66.583116 | U92: =IF(OR(M92="",L92=""),"",M92/L92) -> 0.097824195 | V92: =IF(ISTEXT(C92),"글자 섞임",ROUND(C92*VLOOKUP(N92,'환율_기준일'!$A$4:$E$7,5,FALSE)/'환율_기준일'!$E$4,2)) -> 9270.39 | W92: =IF(ISNUMBER(V92),IF(V92>F92*10,1,0),"") -> 0 | X92: =IF(Q92=1,COUNTIF($Q$2:Q92,1),"")
A93: B092 | B93: EUR | C93: 2436 | D93: 2436 | E93: 0 | F93: 10000 | G93: 8105000 | H93: 7033000 | I93: 9026000 | J93: 863000 | K93: 2702000 | L93: 7605000 | M93: -269000 | N93: =IFERROR(VLOOKUP(TRIM(B93),'확인표_A'!$A$6:$B$14,2,FALSE),"확인 필요") -> EUR | O93: =SUMPRODUCT(--ISTEXT(C93:E93)) -> 0 | P93: =IF(OR(G93="",H93="",I93="",J93="",L93=""),1,0) -> 0 | Q93: =IF(AND(J93<>"",J93<=0),1,0) -> 0 | R93: =IF(OR(G93="",H93=""),"",G93/H93) -> 1.1524243 | S93: =IF(OR(I93="",J93="",Q93=1),"",I93/J93) -> 10.458864 | T93: =IF(OR(K93="",L93=""),"",K93/L93*365) -> 129.68179 | U93: =IF(OR(M93="",L93=""),"",M93/L93) -> -0.035371466 | V93: =IF(ISTEXT(C93),"글자 섞임",ROUND(C93*VLOOKUP(N93,'환율_기준일'!$A$4:$E$7,5,FALSE)/'환율_기준일'!$E$4,2)) -> 2829.91 | W93: =IF(ISNUMBER(V93),IF(V93>F93*10,1,0),"") -> 0 | X93: =IF(Q93=1,COUNTIF($Q$2:Q93,1),"")
A94: B093 | B94: USD | C94: 0 | D94: 0 | E94: 0 | F94: 80000 | N94: =IFERROR(VLOOKUP(TRIM(B94),'확인표_A'!$A$6:$B$14,2,FALSE),"확인 필요") -> USD | O94: =SUMPRODUCT(--ISTEXT(C94:E94)) -> 0 | P94: =IF(OR(G94="",H94="",I94="",J94="",L94=""),1,0) -> 1 | Q94: =IF(AND(J94<>"",J94<=0),1,0) -> 0 | R94: =IF(OR(G94="",H94=""),"",G94/H94) | S94: =IF(OR(I94="",J94="",Q94=1),"",I94/J94) | T94: =IF(OR(K94="",L94=""),"",K94/L94*365) | U94: =IF(OR(M94="",L94=""),"",M94/L94) | V94: =IF(ISTEXT(C94),"글자 섞임",ROUND(C94*VLOOKUP(N94,'환율_기준일'!$A$4:$E$7,5,FALSE)/'환율_기준일'!$E$4,2)) -> 0 | W94: =IF(ISNUMBER(V94),IF(V94>F94*10,1,0),"") -> 0 | X94: =IF(Q94=1,COUNTIF($Q$2:Q94,1),"")
A95: B094 | B95: USD | C95: 23920 | D95: 23920 | E95: 0 | F95: 20000 | G95: 18645000 | H95: 10071000 | I95: 17187000 | J95: 17740000 | K95: 8087000 | L95: 49932000 | M95: 7972000 | N95: =IFERROR(VLOOKUP(TRIM(B95),'확인표_A'!$A$6:$B$14,2,FALSE),"확인 필요") -> USD | O95: =SUMPRODUCT(--ISTEXT(C95:E95)) -> 0 | P95: =IF(OR(G95="",H95="",I95="",J95="",L95=""),1,0) -> 0 | Q95: =IF(AND(J95<>"",J95<=0),1,0) -> 0 | R95: =IF(OR(G95="",H95=""),"",G95/H95) -> 1.8513554 | S95: =IF(OR(I95="",J95="",Q95=1),"",I95/J95) -> 0.96882751 | T95: =IF(OR(K95="",L95=""),"",K95/L95*365) -> 59.115497 | U95: =IF(OR(M95="",L95=""),"",M95/L95) -> 0.15965713 | V95: =IF(ISTEXT(C95),"글자 섞임",ROUND(C95*VLOOKUP(N95,'환율_기준일'!$A$4:$E$7,5,FALSE)/'환율_기준일'!$E$4,2)) -> 23920 | W95: =IF(ISNUMBER(V95),IF(V95>F95*10,1,0),"") -> 0 | X95: =IF(Q95=1,COUNTIF($Q$2:Q95,1),"")
A96: B095 | B96: USD | C96: 7700 | D96: 1540 | E96: 6160 | F96: 10000 | G96: 11693000 | I96: 9578000 | K96: 4496000 | L96: 20182000 | M96: -636000 | N96: =IFERROR(VLOOKUP(TRIM(B96),'확인표_A'!$A$6:$B$14,2,FALSE),"확인 필요") -> USD | O96: =SUMPRODUCT(--ISTEXT(C96:E96)) -> 0 | P96: =IF(OR(G96="",H96="",I96="",J96="",L96=""),1,0) -> 1 | Q96: =IF(AND(J96<>"",J96<=0),1,0) -> 0 | R96: =IF(OR(G96="",H96=""),"",G96/H96) | S96: =IF(OR(I96="",J96="",Q96=1),"",I96/J96) | T96: =IF(OR(K96="",L96=""),"",K96/L96*365) -> 81.31206 | U96: =IF(OR(M96="",L96=""),"",M96/L96) -> -0.03151323 | V96: =IF(ISTEXT(C96),"글자 섞임",ROUND(C96*VLOOKUP(N96,'환율_기준일'!$A$4:$E$7,5,FALSE)/'환율_기준일'!$E$4,2)) -> 7700 | W96: =IF(ISNUMBER(V96),IF(V96>F96*10,1,0),"") -> 0 | X96: =IF(Q96=1,COUNTIF($Q$2:Q96,1),"")
A97: B096 | B97: USD | C97: 7930 | D97: 7930 | E97: 0 | F97: 60000 | N97: =IFERROR(VLOOKUP(TRIM(B97),'확인표_A'!$A$6:$B$14,2,FALSE),"확인 필요") -> USD | O97: =SUMPRODUCT(--ISTEXT(C97:E97)) -> 0 | P97: =IF(OR(G97="",H97="",I97="",J97="",L97=""),1,0) -> 1 | Q97: =IF(AND(J97<>"",J97<=0),1,0) -> 0 | R97: =IF(OR(G97="",H97=""),"",G97/H97) | S97: =IF(OR(I97="",J97="",Q97=1),"",I97/J97) | T97: =IF(OR(K97="",L97=""),"",K97/L97*365) | U97: =IF(OR(M97="",L97=""),"",M97/L97) | V97: =IF(ISTEXT(C97),"글자 섞임",ROUND(C97*VLOOKUP(N97,'환율_기준일'!$A$4:$E$7,5,FALSE)/'환율_기준일'!$E$4,2)) -> 7930 | W97: =IF(ISNUMBER(V97),IF(V97>F97*10,1,0),"") -> 0 | X97: =IF(Q97=1,COUNTIF($Q$2:Q97,1),"")
A98: B097 | B98: USD | C98: 0 | D98: 0 | E98: 0 | F98: 80000 | G98: 217151000 | H98: 124704000 | I98: 214189000 | J98: 126093000 | K98: 90897000 | L98: 429741000 | N98: =IFERROR(VLOOKUP(TRIM(B98),'확인표_A'!$A$6:$B$14,2,FALSE),"확인 필요") -> USD | O98: =SUMPRODUCT(--ISTEXT(C98:E98)) -> 0 | P98: =IF(OR(G98="",H98="",I98="",J98="",L98=""),1,0) -> 0 | Q98: =IF(AND(J98<>"",J98<=0),1,0) -> 0 | R98: =IF(OR(G98="",H98=""),"",G98/H98) -> 1.7413315 | S98: =IF(OR(I98="",J98="",Q98=1),"",I98/J98) -> 1.6986589 | T98: =IF(OR(K98="",L98=""),"",K98/L98*365) -> 77.203257 | U98: =IF(OR(M98="",L98=""),"",M98/L98) | V98: =IF(ISTEXT(C98),"글자 섞임",ROUND(C98*VLOOKUP(N98,'환율_기준일'!$A$4:$E$7,5,FALSE)/'환율_기준일'!$E$4,2)) -> 0 | W98: =IF(ISNUMBER(V98),IF(V98>F98*10,1,0),"") -> 0 | X98: =IF(Q98=1,COUNTIF($Q$2:Q98,1),"")
A99: B098 | B99: USD | C99: 164660 | D99: 164660 | E99: 0 | F99: 130000 | G99: 210351000 | H99: 239089000 | I99: 439960000 | J99: 117360000 | K99: 73831000 | L99: 249642000 | M99: 1835000 | N99: =IFERROR(VLOOKUP(TRIM(B99),'확인표_A'!$A$6:$B$14,2,FALSE),"확인 필요") -> USD | O99: =SUMPRODUCT(--ISTEXT(C99:E99)) -> 0 | P99: =IF(OR(G99="",H99="",I99="",J99="",L99=""),1,0) -> 0 | Q99: =IF(AND(J99<>"",J99<=0),1,0) -> 0 | R99: =IF(OR(G99="",H99=""),"",G99/H99) -> 0.87980208 | S99: =IF(OR(I99="",J99="",Q99=1),"",I99/J99) -> 3.7488071 | T99: =IF(OR(K99="",L99=""),"",K99/L99*365) -> 107.94784 | U99: =IF(OR(M99="",L99=""),"",M99/L99) -> 0.007350526 | V99: =IF(ISTEXT(C99),"글자 섞임",ROUND(C99*VLOOKUP(N99,'환율_기준일'!$A$4:$E$7,5,FALSE)/'환율_기준일'!$E$4,2)) -> 164660 | W99: =IF(ISNUMBER(V99),IF(V99>F99*10,1,0),"") -> 0 | X99: =IF(Q99=1,COUNTIF($Q$2:Q99,1),"")
A100: B099 | B100: USD | C100: 0 | D100: 0 | E100: 0 | F100: 40000 | N100: =IFERROR(VLOOKUP(TRIM(B100),'확인표_A'!$A$6:$B$14,2,FALSE),"확인 필요") -> USD | O100: =SUMPRODUCT(--ISTEXT(C100:E100)) -> 0 | P100: =IF(OR(G100="",H100="",I100="",J100="",L100=""),1,0) -> 1 | Q100: =IF(AND(J100<>"",J100<=0),1,0) -> 0 | R100: =IF(OR(G100="",H100=""),"",G100/H100) | S100: =IF(OR(I100="",J100="",Q100=1),"",I100/J100) | T100: =IF(OR(K100="",L100=""),"",K100/L100*365) | U100: =IF(OR(M100="",L100=""),"",M100/L100) | V100: =IF(ISTEXT(C100),"글자 섞임",ROUND(C100*VLOOKUP(N100,'환율_기준일'!$A$4:$E$7,5,FALSE)/'환율_기준일'!$E$4,2)) -> 0 | W100: =IF(ISNUMBER(V100),IF(V100>F100*10,1,0),"") -> 0 | X100: =IF(Q100=1,COUNTIF($Q$2:Q100,1),"")
...

Sheet 환율_기준일
A1: 기준일 2026-08-31 환율(원) — d2_start.xlsx의 fx_at_ref 시트에서 그날 4행만
A2: 엔화(JPY100)는 100엔당 값입니다 — 1엔당 원은 노란 칸(÷100)
A3: 통화(표준) | B3: fx_at_ref ccy | C3: 단위 | D3: krw_close | E3: 1단위당 원(수식) | F3: 관측일
A4: USD | B4: USD | C4: KRW per 1 USD | D4: 1368.25 | E4: =IF(B4="JPY100",D4/100,D4) -> 1368.25 | F4: 46265
A5: EUR | B5: EUR | C5: KRW per 1 EUR | D5: 1589.5 | E5: =IF(B5="JPY100",D5/100,D5) -> 1589.5 | F5: 46265
A6: CNY | B6: CNY | C6: KRW per 1 CNY | D6: 203.62 | E6: =IF(B6="JPY100",D6/100,D6) -> 203.62 | F6: 46265
A7: JPY | B7: JPY100 | C7: KRW per 100 JPY | D7: 856.55 | E7: =IF(B7="JPY100",D7/100,D7) -> 8.5655 | F7: 46265

Sheet 뉴스_앞100행
A1: news_id | B1: buyer_id | C1: date | D1: lang | E1: 창_안(수식) | F1: 창_안_첫등장(수식) | G1: 9월(수식)
A2: N01395 | B2: B040 | C2: 46295 | D2: en | E2: =IF(AND(C2>DATE(2026,8,1),C2<=DATE(2026,8,31)),1,0) -> 0 | F2: =IF(E2=1,IF(COUNTIFS($B$2:B2,B2,$E$2:E2,1)=1,1,0),0) -> 0 | G2: =IF(AND(C2>DATE(2026,8,31),C2<=DATE(2026,9,30)),1,0) -> 1
A3: N01396 | B3: B141 | C3: 46295 | D3: ko | E3: =IF(AND(C3>DATE(2026,8,1),C3<=DATE(2026,8,31)),1,0) -> 0 | F3: =IF(E3=1,IF(COUNTIFS($B$2:B3,B3,$E$2:E3,1)=1,1,0),0) -> 0 | G3: =IF(AND(C3>DATE(2026,8,31),C3<=DATE(2026,9,30)),1,0) -> 1
A4: N01393 | B4: B053 | C4: 46291 | D4: en | E4: =IF(AND(C4>DATE(2026,8,1),C4<=DATE(2026,8,31)),1,0) -> 0 | F4: =IF(E4=1,IF(COUNTIFS($B$2:B4,B4,$E$2:E4,1)=1,1,0),0) -> 0 | G4: =IF(AND(C4>DATE(2026,8,31),C4<=DATE(2026,9,30)),1,0) -> 1
A5: N01394 | B5: B134 | C5: 46291 | D5: en | E5: =IF(AND(C5>DATE(2026,8,1),C5<=DATE(2026,8,31)),1,0) -> 0 | F5: =IF(E5=1,IF(COUNTIFS($B$2:B5,B5,$E$2:E5,1)=1,1,0),0) -> 0 | G5: =IF(AND(C5>DATE(2026,8,31),C5<=DATE(2026,9,30)),1,0) -> 1
A6: N01389 | B6: B046 | C6: 46290 | D6: ko | E6: =IF(AND(C6>DATE(2026,8,1),C6<=DATE(2026,8,31)),1,0) -> 0 | F6: =IF(E6=1,IF(COUNTIFS($B$2:B6,B6,$E$2:E6,1)=1,1,0),0) -> 0 | G6: =IF(AND(C6>DATE(2026,8,31),C6<=DATE(2026,9,30)),1,0) -> 1
A7: N01390 | B7: B113 | C7: 46290 | D7: en | E7: =IF(AND(C7>DATE(2026,8,1),C7<=DATE(2026,8,31)),1,0) -> 0 | F7: =IF(E7=1,IF(COUNTIFS($B$2:B7,B7,$E$2:E7,1)=1,1,0),0) -> 0 | G7: =IF(AND(C7>DATE(2026,8,31),C7<=DATE(2026,9,30)),1,0) -> 1
A8: N01391 | B8: B123 | C8: 46290 | D8: en | E8: =IF(AND(C8>DATE(2026,8,1),C8<=DATE(2026,8,31)),1,0) -> 0 | F8: =IF(E8=1,IF(COUNTIFS($B$2:B8,B8,$E$2:E8,1)=1,1,0),0) -> 0 | G8: =IF(AND(C8>DATE(2026,8,31),C8<=DATE(2026,9,30)),1,0) -> 1
A9: N01392 | B9: B131 | C9: 46290 | D9: en | E9: =IF(AND(C9>DATE(2026,8,1),C9<=DATE(2026,8,31)),1,0) -> 0 | F9: =IF(E9=1,IF(COUNTIFS($B$2:B9,B9,$E$2:E9,1)=1,1,0),0) -> 0 | G9: =IF(AND(C9>DATE(2026,8,31),C9<=DATE(2026,9,30)),1,0) -> 1
A10: N01387 | B10: B063 | C10: 46289 | D10: en | E10: =IF(AND(C10>DATE(2026,8,1),C10<=DATE(2026,8,31)),1,0) -> 0 | F10: =IF(E10=1,IF(COUNTIFS($B$2:B10,B10,$E$2:E10,1)=1,1,0),0) -> 0 | G10: =IF(AND(C10>DATE(2026,8,31),C10<=DATE(2026,9,30)),1,0) -> 1
A11: N01388 | B11: B065 | C11: 46289 | D11: ko | E11: =IF(AND(C11>DATE(2026,8,1),C11<=DATE(2026,8,31)),1,0) -> 0 | F11: =IF(E11=1,IF(COUNTIFS($B$2:B11,B11,$E$2:E11,1)=1,1,0),0) -> 0 | G11: =IF(AND(C11>DATE(2026,8,31),C11<=DATE(2026,9,30)),1,0) -> 1
A12: N01386 | B12: B111 | C12: 46288 | D12: ko | E12: =IF(AND(C12>DATE(2026,8,1),C12<=DATE(2026,8,31)),1,0) -> 0 | F12: =IF(E12=1,IF(COUNTIFS($B$2:B12,B12,$E$2:E12,1)=1,1,0),0) -> 0 | G12: =IF(AND(C12>DATE(2026,8,31),C12<=DATE(2026,9,30)),1,0) -> 1
A13: N01385 | B13: B058 | C13: 46286 | D13: en | E13: =IF(AND(C13>DATE(2026,8,1),C13<=DATE(2026,8,31)),1,0) -> 0 | F13: =IF(E13=1,IF(COUNTIFS($B$2:B13,B13,$E$2:E13,1)=1,1,0),0) -> 0 | G13: =IF(AND(C13>DATE(2026,8,31),C13<=DATE(2026,9,30)),1,0) -> 1
... A101: N01245 | B101: B062 | C101: 46195 | D101: en | E101: =IF(AND(C101>DATE(2026,8,1),C101<=DATE(2026,8,31)),1,0) -> 0 | F101: =IF(E101=1,IF(COUNTIFS($B$2:B101,B101,$E$2:E101,1)=1,1,0),0) -> 0 | G101: =IF(AND(C101>DATE(2026,8,31),C101<=DATE(2026,9,30)),1,0) -> 0
