Workbook

Sheet 안내
A1: d1_pivot_check.xlsx — 손 검산 완성 파일
A2: 1일차 실습 B-2 · 02 · 원천을 한 칸도 고치지 않고 결제방식별로 센 표와 막대 차트(정답이 아니라 기준선)
A4: 이 파일 | B4: 1일차 실습 B-2 · 02 '손 검산'용 완성 파일입니다. 엑셀 피벗 · 피벗 차트로 할 계산을 미리 해 두었습니다.
A5: 왜 | B5: AI(노트북)가 코드로 낸 숫자를 코드가 아닌 다른 길로 한 번 더 세어 맞춰 보려고. 실습 시간은 엑셀 조작이 아니라 AI 결과와 이 파일을 비교하고 원인을 찾는 데 씁니다.
A6: 무엇으로 | B6: data/day1/d1_buyers_raw.xlsx(원천)와 data/data_dictionary.xlsx의 결제조건 표기 → 표준 코드 표(42개 표기). 둘 다 과정 파일입니다.
A7: 어떻게 ① | B7: buyers 시트 = 원천을 한 칸도 고치지 않고 옮겼습니다. 원천에 어떤 문제가 있어도 그대로입니다.
A8: 어떻게 ② | B8: buyers 시트 X열 '표준코드' = 결제조건(I열)의 앞뒤 공백을 지우고 코드표 시트에서 찾았습니다. 없으면 '미분류'. 셀을 누르면 수식이 보입니다.
A9: 어떻게 ③ | B9: buyers 시트 Y열 '연체' = 연체일수(L열)가 0보다 크면 1, 0이면 0, 숫자로 읽히지 않으면 빈칸(판정 불가)입니다.
A10: 어떻게 ④ | B10: 결제방식_피벗 시트 = 표준 코드별 행 수 · 판정 불가 · 판정 가능 행 · 연체 바이어 · 비율(연체 ÷ 판정 가능 행). 피벗 테이블과 같은 계산을 COUNTIF · COUNTIFS · SUMIF 수식으로 했고, 오른쪽 막대가 피벗 차트 자리입니다.
A11: 쓰는 법 | B11: 노트북 차트 3(또는 d1_eda_notes.md의 결제방식별 표)에서 결제방식 하나를 골라 이 파일의 같은 줄과 비교합니다. 같으면 '맞았다'와 노트북이 한 처리를, 다르면 어디서 갈렸는지(코드표 · 같은 바이어 반복 · 숫자가 아닌 칸 · '검토 필요' 처리 · 정의)를 '손 검산' 절에 적습니다.
A12: 주의 | B12: 정답이 아니라 '고치지 않고 센 기준선'입니다. 다르면 틀린 것이 아니라 원인을 찾을 차례입니다. 정제한 숫자는 2일차에 만듭니다.
A13: 읽기만 | B13: 이 파일은 고치지 않습니다. 바꿔 보려면 workbench/day1/data/에 복사해서 씁니다. 엑셀로 열면 ~$로 시작하는 잠금 파일이 생기는데, 커밋하지 않습니다.
A14: 더 해 보기 | B14: 사본의 코드표 시트에 내 코드표(실습 B-1 · 03의 CSV)의 '원래 표기 · 표준 코드' 두 열을 붙이면 다시 계산됩니다. 결제방식_피벗 B14가 0인지 보세요.
A15: 다시 계산 | B15: 수식이 셀에 남아 있어 엑셀(2010 이후) · 웹용 Excel이 열 때 다시 계산합니다. AI 도구는 저장된 값을 읽습니다 — 둘은 같습니다.

Sheet 결제방식_피벗
A1: 결제방식별 연체 바이어 — 원천 그대로 단순 집계(피벗과 같은 계산)
A2: 행 = 표준코드(buyers!X) · 값 = 행 수(COUNTIF) · 판정 불가(COUNTIFS 빈칸) · 연체 합계(SUMIF) · 비율 = 연체 ÷ 판정 가능 행
A3: 표준 코드 | B3: 뜻 | C3: 바이어 행 수 | D3: 연체 판정 불가 | E3: 판정 가능 행 | F3: 연체 바이어 | G3: 연체 바이어 비율
A4: TT_ADV | B4: T/T 선수금 — 선적 전에 전액 | C4: =COUNTIF(buyers!$X$2:$X$154,A4) -> 12 | D4: =COUNTIFS(buyers!$X$2:$X$154,A4,buyers!$Y$2:$Y$154,"") -> 0 | E4: =C4-D4 -> 12 | F4: =SUMIF(buyers!$X$2:$X$154,A4,buyers!$Y$2:$Y$154) -> 0 | G4: =IF(E4=0,"",F4/E4) -> 0
A5: TT_SPLIT_30_70 | B5: 선수금 + 잔금 분할 | C5: =COUNTIF(buyers!$X$2:$X$154,A5) -> 8 | D5: =COUNTIFS(buyers!$X$2:$X$154,A5,buyers!$Y$2:$Y$154,"") -> 0 | E5: =C5-D5 -> 8 | F5: =SUMIF(buyers!$X$2:$X$154,A5,buyers!$Y$2:$Y$154) -> 1 | G5: =IF(E5=0,"",F5/E5) -> 0.125
A6: LC_SIGHT | B6: L/C 일람불 | C6: =COUNTIF(buyers!$X$2:$X$154,A6) -> 9 | D6: =COUNTIFS(buyers!$X$2:$X$154,A6,buyers!$Y$2:$Y$154,"") -> 0 | E6: =C6-D6 -> 9 | F6: =SUMIF(buyers!$X$2:$X$154,A6,buyers!$Y$2:$Y$154) -> 0 | G6: =IF(E6=0,"",F6/E6) -> 0
A7: LC_USANCE | B7: L/C 기한부 | C7: =COUNTIF(buyers!$X$2:$X$154,A7) -> 4 | D7: =COUNTIFS(buyers!$X$2:$X$154,A7,buyers!$Y$2:$Y$154,"") -> 0 | E7: =C7-D7 -> 4 | F7: =SUMIF(buyers!$X$2:$X$154,A7,buyers!$Y$2:$Y$154) -> 0 | G7: =IF(E7=0,"",F7/E7) -> 0
A8: DP | B8: D/P 지급인도 추심 | C8: =COUNTIF(buyers!$X$2:$X$154,A8) -> 4 | D8: =COUNTIFS(buyers!$X$2:$X$154,A8,buyers!$Y$2:$Y$154,"") -> 0 | E8: =C8-D8 -> 4 | F8: =SUMIF(buyers!$X$2:$X$154,A8,buyers!$Y$2:$Y$154) -> 0 | G8: =IF(E8=0,"",F8/E8) -> 0
A9: DA | B9: D/A 인수인도 추심 | C9: =COUNTIF(buyers!$X$2:$X$154,A9) -> 22 | D9: =COUNTIFS(buyers!$X$2:$X$154,A9,buyers!$Y$2:$Y$154,"") -> 2 | E9: =C9-D9 -> 20 | F9: =SUMIF(buyers!$X$2:$X$154,A9,buyers!$Y$2:$Y$154) -> 4 | G9: =IF(E9=0,"",F9/E9) -> 0.2
A10: OA | B10: O/A 사후송금(외상) | C10: =COUNTIF(buyers!$X$2:$X$154,A10) -> 81 | D10: =COUNTIFS(buyers!$X$2:$X$154,A10,buyers!$Y$2:$Y$154,"") -> 2 | E10: =C10-D10 -> 79 | F10: =SUMIF(buyers!$X$2:$X$154,A10,buyers!$Y$2:$Y$154) -> 14 | G10: =IF(E10=0,"",F10/E10) -> 0.17721519
A11: 미분류 | B11: 코드표에서 찾지 못한 표기 | C11: =COUNTIF(buyers!$X$2:$X$154,A11) -> 13 | D11: =COUNTIFS(buyers!$X$2:$X$154,A11,buyers!$Y$2:$Y$154,"") -> 0 | E11: =C11-D11 -> 13 | F11: =SUMIF(buyers!$X$2:$X$154,A11,buyers!$Y$2:$Y$154) -> 5 | G11: =IF(E11=0,"",F11/E11) -> 0.38461538
A12: 합계 | C12: =SUM(C4:C11) -> 153 | D12: =SUM(D4:D11) -> 4 | E12: =SUM(E4:E11) -> 149 | F12: =SUM(F4:F11) -> 24 | G12: =IF(E12=0,"",F12/E12) -> 0.16107383
A14: 표준 코드 8칸 밖으로 분류된 행 | B14: =COUNTA(buyers!$A$2:$A$154)-C12 -> 0 | C14: ← 0이어야 합니다. 코드표 시트를 내 코드표로 바꿨을 때 '검토 필요'처럼 8칸에 없는 값이 있으면 여기에 셉니다.
A16: 읽는 법 | B16: 비율의 분모는 '판정 가능 행'(연체일수가 숫자인 행)입니다. 같은 바이어가 두 줄이면 두 번 셉니다 — 원천 그대로 센 값이기 때문입니다.
B17: 노트북 숫자와 다르면 원인을 찾을 차례입니다: 코드표 차이 · 같은 바이어 반복 · 숫자가 아닌 연체일 · '검토 필요' 처리 · 정의(연체일 > 0).

Sheet buyers
A1: buyer_id | B1: buyer_name | C1: country | D1: country_code | E1: region | F1: industry | G1: segment | H1: buyer_type | I1: payment_terms_raw | J1: ar_balance | K1: ar_currency | L1: max_dpd_days | M1: overdue_amount | N1: pay_score | O1: oecd_crc | P1: ksure_insured | Q1: since_date | R1: fin_summary_text | S1: revenue_usd_fy2025 | T1: current_ratio_fy2025 | U1: debt_to_equity_fy2025 | V1: dso_fy2025 | W1: op_margin_fy2025 | X1: 표준코드 | Y1: 연체
A2: B001 | B2: Camano Meettechniek B.V. | C2: Netherlands | D2: NLD | E2: 서유럽 | F2: epc_contractor | G2: private | H2: PRIVATE | I2: T/T 90 DAYS AFTER B/L | J2: 23730 | K2: EUR | L2: 0 | M2: 0 | O2: - | P2: N | Q2: 2013.12.9 | R2: Revenue rose 2% YoY to USD 6.8M; operating margin 11.8%. | S2: 6846000 | T2: 1.631 | U2: 0.6007 | V2: 34.76 | W2: 0.1183 | X2: =IFERROR(INDEX('코드표'!$B$2:$B$500,MATCH(TRIM(I2),'코드표'!$A$2:$A$500,0)),"미분류") -> OA | Y2: =IFERROR(IF(--L2>0,1,0),"") -> 0
A3: B002 | B3: Hefei Belum Machinery Co., Ltd. | C3: China | D3: CHN | E3: 동아시아 | F3: oem_manufacturer | G3: private | H3: PRIVATE | I3: OA90 | J3: USD 10,070 | K3: USD | L3: 0 | M3: 0 | N3: 79 | O3: 2 | P3: N | Q3: 2020-09-14 | R3: Revenue rose 13% YoY to USD 8.2M; operating margin 6.7%. | S3: 8185000 | T3: 1.7722 | U3: 1.0233 | V3: 41.7 | W3: 0.0672 | X3: =IFERROR(INDEX('코드표'!$B$2:$B$500,MATCH(TRIM(I3),'코드표'!$A$2:$A$500,0)),"미분류") -> OA | Y3: =IFERROR(IF(--L3>0,1,0),"") -> 0
A4: B003 | B4: PT Delyn Instrumen Nusantara | C4: Indonesia | D4: IDN | E4: 동남아·남아 | F4: oem_manufacturer | G4: private | H4: PRIVATE | I4: D/A 90 | J4: 0 | K4: USD | L4: 0 | M4: 0 | N4: 78 | O4: 3 | P4: N | Q4: Jun 27 2018 | R4: Revenue fell 2% YoY to USD 5.3M; operating loss (-5.2% margin). Some line items were not disclosed. | S4: 5343000 | T4: 1.446 | V4: 80.68 | W4: -0.052 | X4: =IFERROR(INDEX('코드표'!$B$2:$B$500,MATCH(TRIM(I4),'코드표'!$A$2:$A$500,0)),"미분류") -> DA | Y4: =IFERROR(IF(--L4>0,1,0),"") -> 0
A5: B004 | B5: Eldum Automation S.A.E. | C5: Egypt | D5: EGY | E5: 중동·아프리카 | F5: oem_manufacturer | G5: private | H5: PRIVATE | I5: Confirmed L/C at sight | J5: 0 | K5: USD | L5: 0 | M5: 0 | O5: 6 | P5: N | Q5: Jun 20 2024 | R5: Revenue rose 9% YoY to USD 73.9M; operating margin 7.2%. | S5: 73932000 | T5: 2.1786 | U5: 1.323 | V5: 30.31 | W5: 0.0723 | X5: =IFERROR(INDEX('코드표'!$B$2:$B$500,MATCH(TRIM(I5),'코드표'!$A$2:$A$500,0)),"미분류") -> LC_SIGHT | Y5: =IFERROR(IF(--L5>0,1,0),"") -> 0
A6: B005 | B6: Xanolin Distribution Co., Ltd. | C6: Vietnam | D6: VNM | E6: 동남아·남아 | F6: distributor | G6: private | H6: PRIVATE | I6: T/T 90 days after B/L | J6: 346360 | K6: usd | L6: 13 | M6: 19920 | N6: 71 | O6: 3 | P6: Y | Q6: 2023.7.21 | R6: Revenue rose 11% YoY to USD 204.9M; operating margin 13.4%. Some line items were not disclosed. | S6: 204875000 | U6: 0.9715 | V6: 31.33 | W6: 0.1337 | X6: =IFERROR(INDEX('코드표'!$B$2:$B$500,MATCH(TRIM(I6),'코드표'!$A$2:$A$500,0)),"미분류") -> OA | Y6: =IFERROR(IF(--L6>0,1,0),"") -> 1
A7: B006 | B7: Zarum Machinery Sdn. Bhd. | C7: Malaysia | D7: MYS | E7: 동남아·남아 | F7: oem_manufacturer | G7: private | H7: PRIVATE | I7: O/A 30 | J7: 0 | K7: USD | L7: 0 | M7: 0 | O7: 2 | P7: Y | Q7: 29/04/2014 | R7: FY2025 financial statements not received. | X7: =IFERROR(INDEX('코드표'!$B$2:$B$500,MATCH(TRIM(I7),'코드표'!$A$2:$A$500,0)),"미분류") -> OA | Y7: =IFERROR(IF(--L7>0,1,0),"") -> 0
A8: B007 | B8: Quineth Handel B.V. | C8: Netherlands | D8: NLD | E8: 서유럽 | F8: distributor | G8: private | H8: PRIVATE | I8: O/A 90 | K8: EUR | L8: 0 | M8: 0 | N8: 60 | O8: - | P8: Y | Q8: Jan 20 2017 | R8: Revenue rose 14% YoY to USD 27.5M; operating margin 6.3%. | S8: 27528000 | T8: 2.3736 | U8: 0.4913 | V8: 55.17 | W8: 0.0631 | X8: =IFERROR(INDEX('코드표'!$B$2:$B$500,MATCH(TRIM(I8),'코드표'!$A$2:$A$500,0)),"미분류") -> OA | Y8: =IFERROR(IF(--L8>0,1,0),"") -> 0
A9: B008 | B9: Uleon Anlagenbau GmbH | C9: Germany | D9: DEU | E9: 서유럽 | F9: oem_manufacturer | G9: private | H9: PRIVATE | I9: 60 days O/A | K9: EUR | L9: 31 | M9: 약 7천 | N9: 82 | O9: - | P9: Y | Q9: 13/07/2025 | R9: Revenue rose 8% YoY to USD 14.1M; operating margin 8.4%. | S9: 14083000 | T9: 1.3349 | U9: 1.6475 | V9: 56.58 | W9: 0.0836 | X9: =IFERROR(INDEX('코드표'!$B$2:$B$500,MATCH(TRIM(I9),'코드표'!$A$2:$A$500,0)),"미분류") -> 미분류 | Y9: =IFERROR(IF(--L9>0,1,0),"") -> 1
A10: B009 | B10: Suzhou Delaro Supply Co., Ltd. | C10: China | D10: CHN | E10: 동아시아 | F10: distributor | G10: private | H10: PRIVATE | I10: D/A 90 | J10: 385600 | K10: CNY | L10: 0 | M10: 0 | O10: 2 | P10: Y | Q10: 2014-03-06 | R10: Revenue fell 4% YoY to USD 25.1M; operating margin 2.4%. | S10: 25116000 | T10: 1.0375 | U10: 5.7625 | V10: 82.02 | W10: 0.0236 | X10: =IFERROR(INDEX('코드표'!$B$2:$B$500,MATCH(TRIM(I10),'코드표'!$A$2:$A$500,0)),"미분류") -> DA | Y10: =IFERROR(IF(--L10>0,1,0),"") -> 0
A11: B010 | B11: Gorion Handel Sp. z o.o. | C11: Poland | D11: POL | E11: 중동부유럽 | F11: retail | G11: private | H11: PRIVATE | I11: TT | J11: 0 | K11: EUR | L11: 0 | M11: 0 | O11: - | P11: N | Q11: 2021.7.19 | R11: Revenue rose 1% YoY to USD 5.9M; operating margin 0.4%. | S11: 5926000 | T11: 1.1533 | U11: 2.7635 | V11: 70.89 | W11: 0.0035 | X11: =IFERROR(INDEX('코드표'!$B$2:$B$500,MATCH(TRIM(I11),'코드표'!$A$2:$A$500,0)),"미분류") -> TT_ADV | Y11: =IFERROR(IF(--L11>0,1,0),"") -> 0
A12: B011 | B12: Fenolin Utilities Ltd. | C12: India | D12: IND | E12: 동남아·남아 | F12: utility | G12: private | H12: PRIVATE | I12: Confirmed L/C at sight | J12: 0 | K12: USD | L12: 0 | M12: 0 | O12: 3 | P12: N | Q12: May 29 2017 | R12: Revenue rose 8% YoY to USD 7.7M. Some line items were not disclosed. | S12: 7731000 | T12: 1.1832 | U12: 4.8318 | X12: =IFERROR(INDEX('코드표'!$B$2:$B$500,MATCH(TRIM(I12),'코드표'!$A$2:$A$500,0)),"미분류") -> LC_SIGHT | Y12: =IFERROR(IF(--L12>0,1,0),"") -> 0
A13: B012 | B13: PT Varasta Sarana Industri | C13: Indonesia | D13: IDN | E13: 동남아·남아 | F13: oem_manufacturer | G13: private | H13: PRIVATE | I13: DP sight | J13: 0 | K13: USD | L13: 0 | M13: 0 | N13: 79 | O13: 3 | P13: N | Q13: 2014-08-15 | R13: Revenue fell 5% YoY to USD 10.5M; operating loss (-9.8% margin). Current ratio below 1.0 (0.96). Some line items were not disclosed. | S13: 10451000 | T13: 0.9616 | U13: 2.6465 | W13: -0.0977 | X13: =IFERROR(INDEX('코드표'!$B$2:$B$500,MATCH(TRIM(I13),'코드표'!$A$2:$A$500,0)),"미분류") -> DP | Y13: =IFERROR(IF(--L13>0,1,0),"") -> 0
A14: B013 | B14: Tianjin Wenum Manufacturing Co., Ltd. | C14: China | D14: CHN | E14: 동아시아 | F14: oem_manufacturer | G14: private | H14: PRIVATE | I14: 100% T/T before shipment | J14: 0 | K14: US$ | L14: 0 | M14: 0 | O14: 2 | P14: N | Q14: May 6 2023 | R14: Revenue fell 27% YoY to USD 46.5M; operating loss (-24.9% margin). Shareholders' equity is negative. Auditor flagged going-concern uncertainty. | S14: 46504000 | T14: 0.36 | U14: -7.2235 | V14: 86 | W14: -0.2487 | X14: =IFERROR(INDEX('코드표'!$B$2:$B$500,MATCH(TRIM(I14),'코드표'!$A$2:$A$500,0)),"미분류") -> TT_ADV | Y14: =IFERROR(IF(--L14>0,1,0),"") -> 0
A15: B014 | B15: Briion Projects Corp. | C15: United States | D15: USA | E15: 북미·중남미 | F15: epc_contractor | G15: private | H15: PRIVATE | I15: usance l/c 90 days | J15: 29910 | K15: USD | L15: 0 | M15: 0 | O15: - | P15: N | Q15: 22/07/2017 | R15: Revenue fell 3% YoY to USD 148.0M; operating margin 7.5%. | S15: 148025000 | T15: 1.6759 | U15: 0.5598 | V15: 51.68 | W15: 0.0754 | X15: =IFERROR(INDEX('코드표'!$B$2:$B$500,MATCH(TRIM(I15),'코드표'!$A$2:$A$500,0)),"미분류") -> LC_USANCE | Y15: =IFERROR(IF(--L15>0,1,0),"") -> 0
A16: B015 | B16: Pelant Automation Co., Ltd. | C16: Taiwan | D16: TWN | E16: 동아시아 | F16: oem_manufacturer | G16: private | H16: PRIVATE | I16: D/A 90 | J16: 7680 | K16: USD | L16: 0 | M16: 0 | N16: 74 | O16: 2 | P16: N | Q16: 01/06/2021 | R16: Revenue fell 23% YoY to USD 16.5M; operating margin 3.4%. | S16: 16500000 | T16: 1.4218 | U16: 1.0032 | V16: 48.73 | W16: 0.0342 | X16: =IFERROR(INDEX('코드표'!$B$2:$B$500,MATCH(TRIM(I16),'코드표'!$A$2:$A$500,0)),"미분류") -> DA | Y16: =IFERROR(IF(--L16>0,1,0),"") -> 0
A17: B016 | B17: Galova Machinery Ltd. | C17: India | D17: IND | E17: 동남아·남아 | F17: oem_manufacturer | G17: private | H17: PRIVATE | I17: 신용장 일람불 | J17: 0 | K17: USD | L17: 0 | M17: 0 | O17: 3 | P17: N | Q17: 2014-11-19 | R17: FY2025 financial statements not received. | X17: =IFERROR(INDEX('코드표'!$B$2:$B$500,MATCH(TRIM(I17),'코드표'!$A$2:$A$500,0)),"미분류") -> 미분류 | Y17: =IFERROR(IF(--L17>0,1,0),"") -> 0
A18: B017 | B18: Corasta Instruments S.A.E. | C18: Egypt | D18: EGY | E18: 중동·아프리카 | F18: distributor | G18: private | H18: PRIVATE | I18: o/a 90 | J18: 0 | K18: USD | L18: 0 | M18: 0 | N18: 70 | O18: 6 | P18: N | Q18: 2015-01-29 | R18: Revenue rose 0% YoY to USD 5.5M. Some line items were not disclosed. | S18: 5495000 | T18: 1.1668 | U18: 0.8533 | V18: 66.16 | X18: =IFERROR(INDEX('코드표'!$B$2:$B$500,MATCH(TRIM(I18),'코드표'!$A$2:$A$500,0)),"미분류") -> OA | Y18: =IFERROR(IF(--L18>0,1,0),"") -> 0
A19: B018 | B19: Corari Industrie B.V. | C19: Netherlands | D19: NLD | E19: 서유럽 | F19: oem_manufacturer | G19: private | H19: PRIVATE | I19: O/A 30 | J19: 2220 | K19: EUR | L19: 0 | M19: 0 | N19: 80 | O19: - | P19: Y | Q19: Oct 7 2018 | R19: Revenue rose 15% YoY to USD 31.9M; operating loss (-2.0% margin). | S19: 31866000 | T19: 1.5314 | U19: 1.8108 | V19: 69.85 | W19: -0.0199 | X19: =IFERROR(INDEX('코드표'!$B$2:$B$500,MATCH(TRIM(I19),'코드표'!$A$2:$A$500,0)),"미분류") -> OA | Y19: =IFERROR(IF(--L19>0,1,0),"") -> 0
A20: B019 | B20: Saryn Machinery Inc. | C20: United States | D20: USA | E20: 북미·중남미 | F20: oem_manufacturer | G20: private | H20: PRIVATE | I20: D/A 90 days | J20: 0 | K20: USD | L20: 0 | M20: 0 | N20: 74 | O20: - | P20: Y | Q20: 25/01/2015 | R20: Revenue fell 5% YoY to USD 13.3M; operating margin 12.5%. Some line items were not disclosed. | S20: 13268000 | T20: 1.8875 | U20: 1.2413 | W20: 0.1246 | X20: =IFERROR(INDEX('코드표'!$B$2:$B$500,MATCH(TRIM(I20),'코드표'!$A$2:$A$500,0)),"미분류") -> DA | Y20: =IFERROR(IF(--L20>0,1,0),"") -> 0
A21: B020 | B21: Velida Machinery Est. | C21: Saudi Arabia | D21: SAU | E21: 중동·아프리카 | F21: oem_manufacturer | G21: private | H21: PRIVATE | I21: T/T 30/70 | J21: 0 | K21: USD | L21: 0 | M21: 0 | O21: 2 | P21: Y | Q21: 01/12/2019 | R21: Revenue rose 12% YoY to USD 16.2M; operating loss (-6.3% margin). | S21: 16153000 | T21: 1.1525 | U21: 5.1695 | V21: 106.72 | W21: -0.0632 | X21: =IFERROR(INDEX('코드표'!$B$2:$B$500,MATCH(TRIM(I21),'코드표'!$A$2:$A$500,0)),"미분류") -> TT_SPLIT_30_70 | Y21: =IFERROR(IF(--L21>0,1,0),"") -> 0
A22: B021 | B22: Xiamen Rinant Engineering Co., Ltd. | C22: China | D22: CHN | E22: 동아시아 | F22: epc_contractor | G22: private | H22: PRIVATE | I22: Open account 60 days | J22: 538300 | K22: CNY | L22: 0 | M22: 0 | N22: 83 | O22: 2 | P22: N | Q22: 2016-01-20 | R22: Revenue rose 14% YoY to USD 49.4M; operating margin 4.3%. Some line items were not disclosed. | S22: 49384000 | T22: 1.2798 | U22: 0.8295 | W22: 0.0432 | X22: =IFERROR(INDEX('코드표'!$B$2:$B$500,MATCH(TRIM(I22),'코드표'!$A$2:$A$500,0)),"미분류") -> OA | Y22: =IFERROR(IF(--L22>0,1,0),"") -> 0
A23: B022 | B23: PT Kavrendo Instrumen Nusantara | C23: Indonesia | D23: IDN | E23: 동남아·남아 | G23: private | H23: PRIVATE | I23: open acct 90d | J23: 72,360 | K23: USD | L23: 3 | M23: 4330 | N23: 79 | O23: 3 | P23: Y | Q23: Jan 17 2020 | R23: Revenue of USD 169.3M; operating margin 8.7%. | S23: 169300000 | T23: 1.3591 | U23: 1.252 | V23: 35.86 | W23: 0.0868 | X23: =IFERROR(INDEX('코드표'!$B$2:$B$500,MATCH(TRIM(I23),'코드표'!$A$2:$A$500,0)),"미분류") -> 미분류 | Y23: =IFERROR(IF(--L23>0,1,0),"") -> 1
A24: B023 | B24: PT Morora Teknik Indonesia | C24: Indonesai | D24: IDN | E24: 동남아·남아 | F24: distributor | G24: private | H24: PRIVATE | I24: D/A 90 days | J24: 22410 | K24: USD | L24: 0 | M24: 0 | N24: 78 | O24: 3 | P24: Y | Q24: 2012-03-21 | R24: FY2025 financial statements not received. | X24: =IFERROR(INDEX('코드표'!$B$2:$B$500,MATCH(TRIM(I24),'코드표'!$A$2:$A$500,0)),"미분류") -> DA | Y24: =IFERROR(IF(--L24>0,1,0),"") -> 0
A25: B024 | B25: Praum Outlets Inc. | C25: United States | D25: USA | E25: 북미·중남미 | F25: retail | G25: private | H25: PRIVATE | I25: O/A 30 | J25: 0 | K25: USD | L25: 0 | M25: 0 | N25: 77 | O25: - | P25: Y | Q25: 2012-12-01 | R25: Revenue of USD 10.9M; operating margin 8.7%. | S25: 10854000 | T25: 1.1433 | U25: 2.599 | V25: 80.51 | W25: 0.0866 | X25: =IFERROR(INDEX('코드표'!$B$2:$B$500,MATCH(TRIM(I25),'코드표'!$A$2:$A$500,0)),"미분류") -> OA | Y25: =IFERROR(IF(--L25>0,1,0),"") -> 0
A26: B025 | B26: Junant Anlagenbau AG | C26: Germany | D26: DEU | E26: 서유럽 | F26: epc_contractor | G26: private | H26: PRIVATE | I26: T/T 60 DAYS AFTER B/L | J26: 1370 | K26: EUR | L26: 0 | M26: 0 | N26: 79 | O26: - | P26: Y | Q26: 2022-06-29 | R26: Revenue fell 8% YoY to USD 5.4M. Some line items were not disclosed. | S26: 5387000 | T26: 2.1219 | U26: 0.7072 | V26: 59.08 | X26: =IFERROR(INDEX('코드표'!$B$2:$B$500,MATCH(TRIM(I26),'코드표'!$A$2:$A$500,0)),"미분류") -> OA | Y26: =IFERROR(IF(--L26>0,1,0),"") -> 0
A27: B026 | B27: Nelova Engineering (Thailand) Co., Ltd. | C27: Thailand | D27: THA | E27: 동남아·남아 | F27: epc_contractor | G27: private | H27: PRIVATE | I27: O/A 60 | J27: 4860 | K27: USD | L27: 0 | M27: 0 | N27: 82 | O27: 3 | P27: Y | Q27: 2013-05-09 | R27: FY2025 financial statements not received. | X27: =IFERROR(INDEX('코드표'!$B$2:$B$500,MATCH(TRIM(I27),'코드표'!$A$2:$A$500,0)),"미분류") -> OA | Y27: =IFERROR(IF(--L27>0,1,0),"") -> 0
A28: B027 | B28: Ralant Water Services Co., Ltd. | C28: Vietnma | D28: VNM | E28: 동남아·남아 | F28: utility | G28: private | H28: PRIVATE | I28: T/T in advance | J28: 0 | K28: usd | L28: 0 | M28: 0 | O28: 3 | P28: N | Q28: 2023-05-06 | R28: FY2025 financial statements not received. | X28: =IFERROR(INDEX('코드표'!$B$2:$B$500,MATCH(TRIM(I28),'코드표'!$A$2:$A$500,0)),"미분류") -> TT_ADV | Y28: =IFERROR(IF(--L28>0,1,0),"") -> 0
A29: B028 | B29: Davura Kogyo Co., Ltd. | C29: Japan | D29: JPN | E29: 동아시아 | F29: distributor | G29: private | H29: PRIVATE | I29: Net 90 | J29: 35491000 | K29: JPY | L29: 0 | M29: 0 | N29: 83 | O29: - | P29: Y | Q29: 2018-03-06 | R29: Revenue rose 9% YoY to USD 160.7M; operating margin 13.7%. | S29: 160688000 | T29: 1.738 | U29: 0.5585 | V29: 38.16 | W29: 0.1375 | X29: =IFERROR(INDEX('코드표'!$B$2:$B$500,MATCH(TRIM(I29),'코드표'!$A$2:$A$500,0)),"미분류") -> 미분류 | Y29: =IFERROR(IF(--L29>0,1,0),"") -> 0
A30: B029 | B30: Dongguan Tarella Engineering Co., Ltd. | C30: China | D30: CHN | E30: 동아시아 | F30: epc_contractor | G30: private | H30: PRIVATE | I30: Open account 60 days | J30: 88940 | K30: USD | L30: 0 | M30: 0 | N30: 59 | O30: 2 | P30: Y | Q30: Jun 20 2017 | R30: Revenue fell 20% YoY to USD 437.3M; operating margin 10.2%. | S30: 437297000 | T30: 1.2413 | U30: 2.1817 | V30: 86.79 | W30: 0.1023 | X30: =IFERROR(INDEX('코드표'!$B$2:$B$500,MATCH(TRIM(I30),'코드표'!$A$2:$A$500,0)),"미분류") -> OA | Y30: =IFERROR(IF(--L30>0,1,0),"") -> 0
A31: B030 | B31: Calaro Endüstriyel Ölçüm A.Ş. | C31: Türkiye | D31: TUR | E31: 중동부유럽 | F31: epc_contractor | G31: private | H31: PRIVATE | I31: T/T 60 days after B/L | J31: 0 | K31: usd | L31: 0 | M31: 0 | N31: 80 | O31: 5 | P31: N | Q31: 2012.9.20 | R31: Revenue fell 0% YoY to USD 45.0M; operating loss (-8.2% margin). Current ratio below 1.0 (0.73). Some line items were not disclosed. | S31: 45005000 | T31: 0.728 | V31: 104.29 | W31: -0.0825 | X31: =IFERROR(INDEX('코드표'!$B$2:$B$500,MATCH(TRIM(I31),'코드표'!$A$2:$A$500,0)),"미분류") -> OA | Y31: =IFERROR(IF(--L31>0,1,0),"") -> 0
A32: B031 | B32: Kalaro Industrial S.A. de C.V. | C32: Mexico | D32: MEX | E32: 북미·중남미 | F32: oem_manufacturer | G32: private | H32: PRIVATE | I32: T/T 60days | J32: 70120 | K32: USD | L32: 36 | M32: 19200 | N32: 77 | O32: 3 | P32: Y | Q32: 2024.10.4 | R32: Revenue rose 1% YoY to USD 243.2M; operating margin 7.5%. Some line items were not disclosed. | S32: 243199000 | V32: 60.53 | W32: 0.0755 | X32: =IFERROR(INDEX('코드표'!$B$2:$B$500,MATCH(TRIM(I32),'코드표'!$A$2:$A$500,0)),"미분류") -> OA | Y32: =IFERROR(IF(--L32>0,1,0),"") -> 1
A33: B032 | B33: Nilora Water & Wastewater Authority | C33: Egypt | D33: EGY | E33: 중동·아프리카 | F33: public_agency | G33: public | H33: EM_GOV | I33: Net 30 days after receipt of invoice | J33: 0 | K33: US$ | L33: 0 | M33: 0 | N33: 80 | O33: 6 | P33: Y | Q33: 2019-04-10 | R33: Revenue rose 7% YoY to USD 138.8M. Some line items were not disclosed. | S33: 138829000 | U33: 1.899 | X33: =IFERROR(INDEX('코드표'!$B$2:$B$500,MATCH(TRIM(I33),'코드표'!$A$2:$A$500,0)),"미분류") -> OA | Y33: =IFERROR(IF(--L33>0,1,0),"") -> 0
A34: B033 | B34: Calum Contracting JSC | C34: Vietnam | D34: VNM | E34: 동남아·남아 | F34: epc_contractor | G34: private | H34: PRIVATE | I34: Confirmed L/C at sight | J34: 0 | K34: USD | L34: 0 | M34: 0 | O34: 3 | P34: N | Q34: 2020.10.6 | R34: Revenue rose 6% YoY to USD 21.4M. Some line items were not disclosed. | S34: 21381000 | T34: 2.1223 | X34: =IFERROR(INDEX('코드표'!$B$2:$B$500,MATCH(TRIM(I34),'코드표'!$A$2:$A$500,0)),"미분류") -> LC_SIGHT | Y34: =IFERROR(IF(--L34>0,1,0),"") -> 0
A35: B034 | B35: Helvara Humanitarian Supply Agency | C35: Germany | D35: DEU | E35: 서유럽 | F35: public_agency | G35: public | H35: UN | I35: Net 30 days after receipt of invoice | J35: 10080 | K35: EUR | L35: 0 | M35: 0 | N35: 77 | O35: - | P35: N | Q35: 2025-11-02 | R35: Revenue fell 6% YoY to USD 359.1M; operating margin 11.8%. | S35: 359145000 | T35: 2.1808 | U35: 0.4081 | V35: 43.36 | W35: 0.1184 | X35: =IFERROR(INDEX('코드표'!$B$2:$B$500,MATCH(TRIM(I35),'코드표'!$A$2:$A$500,0)),"미분류") -> OA | Y35: =IFERROR(IF(--L35>0,1,0),"") -> 0
A36: B035 | B36: Rinella Distribution Co., Ltd. | C36: Taiwan | D36: TWN | E36: 동아시아 | F36: distributor | G36: private | H36: PRIVATE | I36: T/T in advance | J36: 17,800 | K36: USD | L36: 0 | M36: 0 | O36: 2 | P36: N | Q36: 10/11/2017 | R36: Revenue rose 16% YoY to USD 18.0M; operating loss (-1.7% margin). Some line items were not disclosed. | S36: 17999000 | U36: 2.1336 | V36: 74.71 | W36: -0.0174 | X36: =IFERROR(INDEX('코드표'!$B$2:$B$500,MATCH(TRIM(I36),'코드표'!$A$2:$A$500,0)),"미분류") -> TT_ADV | Y36: =IFERROR(IF(--L36>0,1,0),"") -> 0
A37: B036 | B37: Quinano Trading JSC | C37: Vietnam | D37: VNM | E37: 동남아·남아 | F37: distributor | G37: private | H37: PRIVATE | I37: TT | J37: 0 | K37: USD | L37: 0 | M37: 0 | N37: 78 | O37: 3 | P37: N | Q37: 2023-06-16 | R37: FY2025 financial statements not received. | X37: =IFERROR(INDEX('코드표'!$B$2:$B$500,MATCH(TRIM(I37),'코드표'!$A$2:$A$500,0)),"미분류") -> TT_ADV | Y37: =IFERROR(IF(--L37>0,1,0),"") -> 0
A38: B037 | B38: Bexova Industries Est. | C38: KSA | D38: SAU | E38: 중동·아프리카 | F38: oem_manufacturer | G38: private | H38: PRIVATE | I38: DA90 | K38: usd | L38: 0 | M38: 0 | N38: 76 | O38: 2 | P38: Y | Q38: 02/10/2016 | R38: Revenue rose 9% YoY to USD 48.0M; operating margin 7.9%. Current ratio below 1.0 (0.73). | S38: 47961000 | T38: 0.7327 | U38: 0.9712 | V38: 49.46 | W38: 0.079 | X38: =IFERROR(INDEX('코드표'!$B$2:$B$500,MATCH(TRIM(I38),'코드표'!$A$2:$A$500,0)),"미분류") -> DA | Y38: =IFERROR(IF(--L38>0,1,0),"") -> 0
A39: B038 | B39: Varix Anlagenbau GmbH | C39: Germany | D39: DEU | E39: 서유럽 | F39: retail | G39: private | H39: PRIVATE | I39: tt | J39: 0 | K39: EUR | L39: 0 | M39: 0 | O39: - | P39: N | Q39: 2023.5.16 | R39: Revenue rose 3% YoY to USD 6.6M; operating loss (-5.3% margin). | S39: 6552000 | T39: 1.0521 | U39: 4.6103 | V39: 98.1 | W39: -0.0534 | X39: =IFERROR(INDEX('코드표'!$B$2:$B$500,MATCH(TRIM(I39),'코드표'!$A$2:$A$500,0)),"미분류") -> TT_ADV | Y39: =IFERROR(IF(--L39>0,1,0),"") -> 0
A40: B039 | B40: Zaryn Industries Est. | C40: Saudi Arabia | D40: SAU | E40: 중동·아프리카 | F40: oem_manufacturer | G40: private | H40: PRIVATE | I40: 30% T/T advance, 70% within 30 days after B/L | J40: 0 | K40: USD | L40: 0 | M40: 0 | N40: 72 | O40: 2 | P40: N | Q40: 2025-11-01 | R40: Revenue fell 7% YoY to USD 7.4M; operating margin 6.8%. Some line items were not disclosed. | S40: 7402000 | T40: 1.2788 | U40: 2.0451 | W40: 0.0675 | X40: =IFERROR(INDEX('코드표'!$B$2:$B$500,MATCH(TRIM(I40),'코드표'!$A$2:$A$500,0)),"미분류") -> TT_SPLIT_30_70 | Y40: =IFERROR(IF(--L40>0,1,0),"") -> 0
A41: B040 | B41: Loreth Environmental Services Ltd. | C41: India | D41: IND | E41: 동남아·남아 | F41: utility | G41: private | H41: PRIVATE | I41: Usance L/C 90 days | J41: 49.2k | K41: USD | L41: 0 | M41: 0 | O41: 3 | P41: N | Q41: 15/08/2014 | R41: Revenue rose 9% YoY to USD 64.7M. Some line items were not disclosed. | S41: 64727000 | T41: 1.4618 | U41: 2.4389 | V41: 93.82 | X41: =IFERROR(INDEX('코드표'!$B$2:$B$500,MATCH(TRIM(I41),'코드표'!$A$2:$A$500,0)),"미분류") -> LC_USANCE | Y41: =IFERROR(IF(--L41>0,1,0),"") -> 0
A42: B041 | B42: Davant Endüstriyel Ölçüm Ltd. Şti. | C42: Türkiye | D42: TUR | E42: 중동부유럽 | F42: oem_manufacturer | G42: private | H42: PRIVATE | I42: 30 DAYS OPEN ACCOUNT | J42: 42560 | K42: USD | L42: 3 | M42: USD 11,210 | N42: 78 | O42: 5 | P42: Y | Q42: 24/05/2017 | R42: Revenue rose 10% YoY to USD 48.1M; operating margin 2.9%. | S42: 48147000 | T42: 1.3482 | U42: 5.0671 | V42: 73.08 | W42: 0.0291 | X42: =IFERROR(INDEX('코드표'!$B$2:$B$500,MATCH(TRIM(I42),'코드표'!$A$2:$A$500,0)),"미분류") -> 미분류 | Y42: =IFERROR(IF(--L42>0,1,0),"") -> 1
A43: B042 | B43: Velix Comércio Ltda. | C43: Brazil | D43: BRA | E43: 북미·중남미 | G43: private | H43: PRIVATE | I43: T/T in advance | J43: 0 | K43: US$ | L43: 0 | M43: 0 | O43: 4 | P43: N | Q43: 15/11/2012 | R43: Revenue fell 15% YoY to USD 5.5M. Some line items were not disclosed. | S43: 5456000 | V43: 97.54 | X43: =IFERROR(INDEX('코드표'!$B$2:$B$500,MATCH(TRIM(I43),'코드표'!$A$2:$A$500,0)),"미분류") -> TT_ADV | Y43: =IFERROR(IF(--L43>0,1,0),"") -> 0
A44: B043 | B44: Changzhou Bexum Environmental Services Co., Ltd. | C44: China | D44: CHN | E44: 동아시아 | F44: utility | G44: private | H44: PRIVATE | I44: t/t 90 days after b/l | J44: 168600 | K44: CNY | L44: 0 | M44: 0 | N44: 69 | O44: 2 | P44: Y | Q44: 2022-10-24 | R44: Revenue rose 18% YoY to USD 7.8M; operating margin 6.6%. | S44: 7825000 | T44: 1.3501 | U44: 0.7503 | V44: 64.51 | W44: 0.0661 | X44: =IFERROR(INDEX('코드표'!$B$2:$B$500,MATCH(TRIM(I44),'코드표'!$A$2:$A$500,0)),"미분류") -> OA | Y44: =IFERROR(IF(--L44>0,1,0),"") -> 0
A45: B044 | B45: Quinasta Manufacturing (Thailand) Co., Ltd. | C45: Thailand | D45: THA | E45: 동남아·남아 | F45: oem_manufacturer | G45: private | H45: PRIVATE | I45: D/A 90 days | J45: 13330 | K45: USD | L45: 355 | M45: 13,330 | O45: 3 | P45: N | Q45: 2020-09-07 | R45: Revenue rose 23% YoY to USD 13.0M; operating margin 0.0%. Some line items were not disclosed. | S45: 12956000 | V45: 123.31 | W45: 0.0004 | X45: =IFERROR(INDEX('코드표'!$B$2:$B$500,MATCH(TRIM(I45),'코드표'!$A$2:$A$500,0)),"미분류") -> DA | Y45: =IFERROR(IF(--L45>0,1,0),"") -> 1
A46: B045 | B46: Wenora General Trading FZCO | C46: United Arab Emirates | D46: ARE | E46: 중동·아프리카 | F46: retail | G46: private | H46: PRIVATE | I46: O/A60 | J46: 0 | K46: USD | L46: 0 | M46: 0 | N46: 75 | O46: 2 | P46: Y | Q46: 2017.1.19 | R46: Revenue rose 4% YoY to USD 14.9M. Some line items were not disclosed. | S46: 14928000 | T46: 1.183 | U46: 1.1107 | V46: 59.12 | X46: =IFERROR(INDEX('코드표'!$B$2:$B$500,MATCH(TRIM(I46),'코드표'!$A$2:$A$500,0)),"미분류") -> OA | Y46: =IFERROR(IF(--L46>0,1,0),"") -> 0
A47: B046 | B47: Interagency Water Relief Office | C47: United States | D47: USA | E47: 북미·중남미 | F47: public_agency | G47: public | H47: UN | I47: Net 30 days after receipt of invoice | J47: 0 | K47: USD | L47: 0 | M47: 0 | N47: 71 | O47: - | P47: N | Q47: Jul 16 2019 | R47: Revenue rose 3% YoY to USD 256.7M; operating margin 9.5%. | S47: 256707000 | T47: 1.5172 | U47: 0.3802 | V47: 37.05 | W47: 0.0954 | X47: =IFERROR(INDEX('코드표'!$B$2:$B$500,MATCH(TRIM(I47),'코드표'!$A$2:$A$500,0)),"미분류") -> OA | Y47: =IFERROR(IF(--L47>0,1,0),"") -> 0
A48: B047 | B48: Corost Comercializadora S.A. de C.V. | C48: Mexico | D48: MEX | E48: 북미·중남미 | F48: retail | G48: private | H48: PRIVATE | I48: O/A 90 | J48: 54540 | K48: USD | L48: 48 | M48: 27300 | N48: 76 | O48: 3 | P48: Y | Q48: 2016.3.10 | R48: FY2025 financial statements not received. | X48: =IFERROR(INDEX('코드표'!$B$2:$B$500,MATCH(TRIM(I48),'코드표'!$A$2:$A$500,0)),"미분류") -> OA | Y48: =IFERROR(IF(--L48>0,1,0),"") -> 1
A49: B048 | B49: Changzhou Wenant Engineering Co., Ltd. | C49: China | D49: CHN | E49: 동아시아 | F49: epc_contractor | G49: private | H49: PRIVATE | I49: O/A30 | J49: 24530 | K49: USD | L49: 90일 | M49: 24,530 | O49: 2 | P49: Y | Q49: Dec 2 2019 | R49: Revenue fell 17% YoY to USD 58.3M; operating loss (-23.6% margin). Shareholders' equity is negative. Auditor flagged going-concern uncertainty. | S49: 58284000 | T49: 0.36 | U49: -4.2645 | V49: 86 | W49: -0.2363 | X49: =IFERROR(INDEX('코드표'!$B$2:$B$500,MATCH(TRIM(I49),'코드표'!$A$2:$A$500,0)),"미분류") -> OA | Y49: =IFERROR(IF(--L49>0,1,0),"")
A50: B049 | B50: Lumasta Engineering LLC | C50: United Arab Emirates | D50: ARE | E50: 중동·아프리카 | F50: epc_contractor | G50: private | H50: PRIVATE | I50: D/A 90 | J50: 50700 | K50: US$ | L50: 61 | M50: 2820 | N50: 70 | O50: 2 | P50: N | Q50: 2020-11-13 | R50: Revenue fell 0% YoY to USD 290.2M; operating margin 3.9%. | S50: 290244000 | T50: 1.3081 | U50: 2.8987 | V50: 66.44 | W50: 0.0387 | X50: =IFERROR(INDEX('코드표'!$B$2:$B$500,MATCH(TRIM(I50),'코드표'!$A$2:$A$500,0)),"미분류") -> DA | Y50: =IFERROR(IF(--L50>0,1,0),"") -> 1
A51: B050 | B51: Korolin Instruments LLC | C51: U.S.A | D51: USA | E51: 북미·중남미 | F51: distributor | G51: private | H51: PRIVATE | I51: T/T 60 days after B/L | J51: 70360 | K51: usd | L51: 0 | M51: 0 | N51: 67 | O51: - | P51: Y | Q51: 2016-06-16 | R51: Revenue rose 6% YoY to USD 36.0M; operating margin 7.0%. | S51: 36022000 | T51: 1.9284 | U51: 1.4149 | V51: 62.9 | W51: 0.0705 | X51: =IFERROR(INDEX('코드표'!$B$2:$B$500,MATCH(TRIM(I51),'코드표'!$A$2:$A$500,0)),"미분류") -> OA | Y51: =IFERROR(IF(--L51>0,1,0),"") -> 0
A52: B051 | B52: Dorora Engineering Inc. | C52: United States | D52: USA | E52: 북미·중남미 | F52: epc_contractor | G52: private | H52: PRIVATE | I52: OA 90 days | J52: 0 | K52: USD | L52: 0 | M52: 0 | N52: 61 | O52: - | P52: N | Q52: Oct 26 2025 | R52: Revenue rose 23% YoY to USD 102.2M; operating margin 7.7%. | S52: 102155000 | T52: 1.5084 | U52: 1.3483 | V52: 65.44 | W52: 0.0771 | X52: =IFERROR(INDEX('코드표'!$B$2:$B$500,MATCH(TRIM(I52),'코드표'!$A$2:$A$500,0)),"미분류") -> OA | Y52: =IFERROR(IF(--L52>0,1,0),"") -> 0
A53: B052 | B53: Mekora Water Infrastructure PMU | C53: Vietnam | D53: VNM | E53: 동남아·남아 | F53: public_agency | G53: public | H53: MDB | I53: LC at sight | J53: 0 | K53: USD | L53: 0 | M53: 0 | O53: 3 | P53: N | Q53: May 16 2013 | R53: Revenue fell 7% YoY to USD 167.2M; operating margin 10.3%. | S53: 167235000 | T53: 1.3405 | U53: 2.2583 | V53: 60.99 | W53: 0.1026 | X53: =IFERROR(INDEX('코드표'!$B$2:$B$500,MATCH(TRIM(I53),'코드표'!$A$2:$A$500,0)),"미분류") -> LC_SIGHT | Y53: =IFERROR(IF(--L53>0,1,0),"") -> 0
A54: B053 | B54: Davix Industrietechnik AG | C54: Germany | D54: DEU | E54: 서유럽 | F54: utility | G54: private | H54: PRIVATE | I54: O/A 60 | J54: 71550 | K54: EUR | L54: 0 | M54: 0 | O54: - | P54: N | Q54: 2019.1.22 | R54: Revenue fell 4% YoY to USD 258.1M; operating margin 3.5%. | S54: 258078000 | T54: 1.4617 | U54: 2.5688 | V54: 81.48 | W54: 0.0348 | X54: =IFERROR(INDEX('코드표'!$B$2:$B$500,MATCH(TRIM(I54),'코드표'!$A$2:$A$500,0)),"미분류") -> OA | Y54: =IFERROR(IF(--L54>0,1,0),"") -> 0
A55: B054 | B55: Waterschap Velmar-Oost | C55: Netherlands | D55: NLD | E55: 서유럽 | F55: public_agency | G55: public | H55: DM_GOV | I55: Net 30 days after receipt of invoice | J55: 0 | K55: EUR | L55: 0 | M55: 0 | O55: - | P55: Y | Q55: 2024-07-17 | R55: Revenue rose 7% YoY to USD 411.7M; operating margin 12.9%. | S55: 411694000 | T55: 1.67 | U55: 0.3774 | V55: 31.63 | W55: 0.129 | X55: =IFERROR(INDEX('코드표'!$B$2:$B$500,MATCH(TRIM(I55),'코드표'!$A$2:$A$500,0)),"미분류") -> OA | Y55: =IFERROR(IF(--L55>0,1,0),"") -> 0
A56: B055 | B56: Tulvarra Water Services LLC | C56: United States | D56: USA | E56: 북미·중남미 | F56: utility | G56: private | H56: PRIVATE | I56: OA 60 days | J56: 0 | K56: USD | L56: 0 | M56: 0 | N56: 25 | O56: - | P56: Y | Q56: 2025-01-29 | R56: FY2025 financial statements not received. | X56: =IFERROR(INDEX('코드표'!$B$2:$B$500,MATCH(TRIM(I56),'코드표'!$A$2:$A$500,0)),"미분류") -> OA | Y56: =IFERROR(IF(--L56>0,1,0),"") -> 0
A57: B056 | B57: Quinari Instruments Inc. | C57: United States | D57: USA | E57: 북미·중남미 | G57: private | H57: PRIVATE | I57: OA90 | J57: 50380 | K57: USD | L57: 0 | M57: 0 | N57: 76 | O57: - | P57: Y | Q57: 2021-07-25 | R57: Revenue rose 8% YoY to USD 8.1M; operating margin 10.0%. | S57: 8052000 | T57: 1.2621 | U57: 0.7235 | V57: 55.48 | W57: 0.1 | X57: =IFERROR(INDEX('코드표'!$B$2:$B$500,MATCH(TRIM(I57),'코드표'!$A$2:$A$500,0)),"미분류") -> OA | Y57: =IFERROR(IF(--L57>0,1,0),"") -> 0
A58: B057 | B58: Calant Projects Co., Ltd. | C58: Vietnam | D58: VNM | E58: 동남아·남아 | F58: epc_contractor | G58: private | H58: PRIVATE | I58: L/C 90 days | J58: 137350 | K58: USD | L58: 0 | M58: 0 | O58: 3 | P58: N | Q58: 2025.9.24 | R58: Revenue rose 15% YoY to USD 46.7M; operating margin 6.8%. | S58: 46739000 | T58: 1.0522 | U58: 1.4712 | V58: 72.2 | W58: 0.0684 | X58: =IFERROR(INDEX('코드표'!$B$2:$B$500,MATCH(TRIM(I58),'코드표'!$A$2:$A$500,0)),"미분류") -> LC_USANCE | Y58: =IFERROR(IF(--L58>0,1,0),"") -> 0
A59: B058 | B59: Jemsolka Supply Sdn. Bhd. | C59: Malaysia | D59: MYS | E59: 동남아·남아 | F59: distributor | G59: private | H59: PRIVATE | I59: OA 30 days | J59: 0 | K59: USD | L59: - | M59: 0 | N59: 82 | O59: 2 | P59: N | Q59: 2024-07-26 | R59: FY2025 financial statements not received. | X59: =IFERROR(INDEX('코드표'!$B$2:$B$500,MATCH(TRIM(I59),'코드표'!$A$2:$A$500,0)),"미분류") -> OA | Y59: =IFERROR(IF(--L59>0,1,0),"")
A60: B059 | B60: PT Sarida Sarana Industri | C60: Indonesia | D60: IDN | E60: 동남아·남아 | F60: oem_manufacturer | G60: private | H60: PRIVATE | I60: O/A 30 | J60: 40560 | K60: USD | L60: 70 | M60: 4980 | N60: 80 | O60: 3 | P60: Y | Q60: 2025-01-30 | R60: Revenue rose 5% YoY to USD 48.9M; operating loss (-5.0% margin). Current ratio below 1.0 (0.78). | S60: 48891000 | T60: 0.7767 | U60: 2.3297 | V60: 76.37 | W60: -0.0505 | X60: =IFERROR(INDEX('코드표'!$B$2:$B$500,MATCH(TRIM(I60),'코드표'!$A$2:$A$500,0)),"미분류") -> OA | Y60: =IFERROR(IF(--L60>0,1,0),"") -> 1
A61: B060 | B61: PT Korida Instrumen Nusantara | C61: Indonesia | D61: IDN | E61: 동남아·남아 | F61: oem_manufacturer | G61: private | H61: PRIVATE | I61: tt | J61: 0 | K61: US$ | L61: 0 | M61: 0 | O61: 3 | P61: N | Q61: May 20 2023 | R61: FY2025 financial statements not received. | X61: =IFERROR(INDEX('코드표'!$B$2:$B$500,MATCH(TRIM(I61),'코드표'!$A$2:$A$500,0)),"미분류") -> TT_ADV | Y61: =IFERROR(IF(--L61>0,1,0),"") -> 0
A62: B061 | B62: Ulia Projects Pvt. Ltd. | C62: India | D62: IND | E62: 동남아·남아 | G62: private | H62: PRIVATE | I62: DA60 | J62: 0 | K62: usd | L62: 0 | M62: 0 | N62: 81 | O62: 3 | P62: N | Q62: Apr 14 2018 | R62: Revenue rose 10% YoY to USD 21.2M. Some line items were not disclosed. | S62: 21218000 | T62: 2.0769 | U62: 2.5709 | V62: 82.12 | X62: =IFERROR(INDEX('코드표'!$B$2:$B$500,MATCH(TRIM(I62),'코드표'!$A$2:$A$500,0)),"미분류") -> DA | Y62: =IFERROR(IF(--L62>0,1,0),"") -> 0
A63: B047 | B63: Corost Comercializadora S.A. de C.V. | C63: Mexico | D63: MEX | E63: 북미·중남미 | F63: retail | G63: private | H63: PRIVATE | I63: O/A 90 | J63: 54540 | K63: USD | L63: 48 | M63: 27300 | N63: 76 | O63: 3 | P63: Y | Q63: 2016.3.10 | R63: FY2025 financial statements not received. | X63: =IFERROR(INDEX('코드표'!$B$2:$B$500,MATCH(TRIM(I63),'코드표'!$A$2:$A$500,0)),"미분류") -> OA | Y63: =IFERROR(IF(--L63>0,1,0),"") -> 1
A64: B062 | B64: Galeth Instruments LLC | C64: United States | D64: USA | E64: 북미·중남미 | F64: distributor | G64: private | H64: PRIVATE | I64: Net 60 | J64: 35660 | K64: USD | L64: 12 | M64: 18310 | N64: 80 | O64: - | P64: Y | Q64: 2024-11-18 | R64: Revenue rose 11% YoY to USD 105.5M; operating margin 9.4%. Some line items were not disclosed. | S64: 105519000 | U64: 1.4445 | V64: 71.16 | W64: 0.0943 | X64: =IFERROR(INDEX('코드표'!$B$2:$B$500,MATCH(TRIM(I64),'코드표'!$A$2:$A$500,0)),"미분류") -> 미분류 | Y64: =IFERROR(IF(--L64>0,1,0),"") -> 1
A65: B063 | B65: Tianjin Corolin Outlets Co., Ltd. | C65: China | D65: CHN | E65: 동아시아 | F65: retail | G65: private | H65: PRIVATE | I65: T/T in advance | J65: 0 | K65: CNY | L65: 0 | M65: 0 | O65: 2 | P65: N | Q65: 11/04/2013 | R65: Revenue rose 9% YoY to USD 7.8M; operating margin 0.7%. | S65: 7780000 | T65: 1.5264 | U65: 3.7475 | V65: 122.5 | W65: 0.0068 | X65: =IFERROR(INDEX('코드표'!$B$2:$B$500,MATCH(TRIM(I65),'코드표'!$A$2:$A$500,0)),"미분류") -> TT_ADV | Y65: =IFERROR(IF(--L65>0,1,0),"") -> 0
A66: B064 | B66: Belost Trading Inc. | C66: United States | D66: USA | E66: 북미·중남미 | F66: distributor | G66: private | H66: PRIVATE | I66: T/T 30/70 | J66: 27216 | K66: USD | L66: 0 | M66: 0 | N66: 78 | O66: - | P66: Y | Q66: 2015.7.9 | R66: Revenue fell 14% YoY to USD 437.4M; operating margin 10.6%. | S66: 437380000 | T66: 1.9739 | U66: 0.5995 | V66: 58.34 | W66: 0.1062 | X66: =IFERROR(INDEX('코드표'!$B$2:$B$500,MATCH(TRIM(I66),'코드표'!$A$2:$A$500,0)),"미분류") -> TT_SPLIT_30_70 | Y66: =IFERROR(IF(--L66>0,1,0),"") -> 0
A67: B065 | B67: Indavara Rural Water Programme PIU | C67: Inida | D67: IND | E67: 동남아·남아 | F67: public_agency | G67: public | H67: MDB | I67: irrevocable l/c at sight | J67: 0 | K67: USD | L67: 0 | M67: 0 | O67: 3 | P67: N | Q67: 2024-04-11 | R67: Revenue of USD 218.1M; operating margin 10.9%. Some line items were not disclosed. | S67: 218133000 | W67: 0.1091 | X67: =IFERROR(INDEX('코드표'!$B$2:$B$500,MATCH(TRIM(I67),'코드표'!$A$2:$A$500,0)),"미분류") -> LC_SIGHT | Y67: =IFERROR(IF(--L67>0,1,0),"") -> 0
A68: B066 | B68: Marano Home & Lab Stores FZE | C68: United Arab Emirates | D68: ARE | E68: 중동·아프리카 | F68: retail | G68: private | H68: PRIVATE | I68: D/A 60 | J68: 80550 | K68: USD | L68: 확인중 | M68: USD 10,610 | N68: 73 | O68: 2 | P68: Y | Q68: 25/07/2015 | R68: Revenue fell 2% YoY to USD 166.2M; operating margin 6.7%. Some line items were not disclosed. | S68: 166249000 | T68: 1.1868 | V68: 37.87 | W68: 0.0671 | X68: =IFERROR(INDEX('코드표'!$B$2:$B$500,MATCH(TRIM(I68),'코드표'!$A$2:$A$500,0)),"미분류") -> DA | Y68: =IFERROR(IF(--L68>0,1,0),"")
A69: B067 | B69: Briano Instrumentação S.A. | C69: Brazil | D69: BRA | E69: 북미·중남미 | F69: retail | G69: private | H69: PRIVATE | I69: D/P | J69: 0 | K69: USD | L69: 0 | M69: 0 | N69: 80 | O69: 4 | P69: N | Q69: 2018-03-25 | R69: FY2025 financial statements not received. | X69: =IFERROR(INDEX('코드표'!$B$2:$B$500,MATCH(TRIM(I69),'코드표'!$A$2:$A$500,0)),"미분류") -> DP | Y69: =IFERROR(IF(--L69>0,1,0),"") -> 0
A70: B068 | B70: Belion Automation (Thailand) Co., Ltd. | C70: Thailand | D70: THA | E70: 동남아·남아 | F70: oem_manufacturer | G70: private | H70: PRIVATE | I70: Net 60 | J70: 약 11만9천 | K70: USD | L70: 0 | M70: 0 | N70: 68 | O70: 3 | P70: N | Q70: 2025.9.10 | R70: Revenue rose 31% YoY to USD 656.8M; operating margin 6.1%. Some line items were not disclosed. | S70: 656839000 | U70: 3.0522 | V70: 70.07 | W70: 0.0613 | X70: =IFERROR(INDEX('코드표'!$B$2:$B$500,MATCH(TRIM(I70),'코드표'!$A$2:$A$500,0)),"미분류") -> 미분류 | Y70: =IFERROR(IF(--L70>0,1,0),"") -> 0
A71: B069 | B71: Vasbrelko Machinery LLC | C71: United Arab Emirates | D71: ARE | E71: 중동·아프리카 | F71: oem_manufacturer | G71: private | H71: PRIVATE | I71: T/T 60days | J71: 0 | K71: USD | L71: 0 | M71: 0 | O71: 2 | P71: N | Q71: 17/08/2023 | R71: FY2025 financial statements not received. | X71: =IFERROR(INDEX('코드표'!$B$2:$B$500,MATCH(TRIM(I71),'코드표'!$A$2:$A$500,0)),"미분류") -> OA | Y71: =IFERROR(IF(--L71>0,1,0),"") -> 0
A72: B070 | B72: Tarolin Przemysł Sp. z o.o. | C72: Poland | D72: POL | E72: 중동부유럽 | F72: oem_manufacturer | G72: private | H72: PRIVATE | I72: T/T 60days | J72: 7380 | K72: EUR | L72: 0 | M72: 0 | N72: 78 | O72: - | P72: Y | Q72: Nov 14 2019 | R72: Revenue fell 19% YoY to USD 34.8M; operating margin 7.2%. | S72: 34816000 | T72: 1.5278 | U72: 1.8168 | V72: 96.55 | W72: 0.0723 | X72: =IFERROR(INDEX('코드표'!$B$2:$B$500,MATCH(TRIM(I72),'코드표'!$A$2:$A$500,0)),"미분류") -> OA | Y72: =IFERROR(IF(--L72>0,1,0),"") -> 0
A73: B071 | B73: Briost Engineering Co., Ltd. | C73: Taiwan | D73: TWN | E73: 동아시아 | F73: epc_contractor | G73: private | H73: PRIVATE | I73: O/A60 | J73: 65000 | K73: USD | L73: 269 | M73: 65000 | O73: 2 | P73: Y | Q73: Jun 27 2020 | R73: Revenue fell 18% YoY to USD 51.3M; operating margin turned negative (-5.2%). Current ratio below 1.0 (0.75). | S73: 51338000 | T73: 0.7455 | U73: 2.0398 | V73: 122.69 | W73: -0.0518 | X73: =IFERROR(INDEX('코드표'!$B$2:$B$500,MATCH(TRIM(I73),'코드표'!$A$2:$A$500,0)),"미분류") -> OA | Y73: =IFERROR(IF(--L73>0,1,0),"") -> 1
A74: B072 | B74: Halano Handelsgesellschaft GmbH | C74: Germany | D74: DEU | E74: 서유럽 | F74: distributor | G74: private | H74: PRIVATE | I74: O/A 30 | J74: 8490 | K74: EUR | L74: 0 | M74: 0 | O74: - | P74: N | Q74: 2025.2.5 | R74: Revenue fell 6% YoY to USD 22.7M; operating margin 1.9%. | S74: 22733000 | T74: 1.2085 | U74: 2.1859 | V74: 66.6 | W74: 0.019 | X74: =IFERROR(INDEX('코드표'!$B$2:$B$500,MATCH(TRIM(I74),'코드표'!$A$2:$A$500,0)),"미분류") -> OA | Y74: =IFERROR(IF(--L74>0,1,0),"") -> 0
A75: B073 | B75: Praix Industrial Ltda. | C75: Brazil | D75: BRA | E75: 북미·중남미 | F75: utility | G75: private | H75: PRIVATE | I75: O/A 30 | J75: 48270 | K75: USD | L75: 19 | M75: 48.3k | N75: 75 | O75: 4 | P75: N | Q75: Feb 24 2022 | R75: Revenue rose 6% YoY to USD 61.2M; operating margin 3.7%. | S75: 61234000 | T75: 1.4512 | U75: 1.8159 | V75: 69.74 | W75: 0.0368 | X75: =IFERROR(INDEX('코드표'!$B$2:$B$500,MATCH(TRIM(I75),'코드표'!$A$2:$A$500,0)),"미분류") -> OA | Y75: =IFERROR(IF(--L75>0,1,0),"") -> 1
A76: B074 | B76: Corant Projects Sdn. Bhd. | C76: Malaysia | D76: MYS | E76: 동남아·남아 | F76: epc_contractor | G76: private | H76: PRIVATE | I76: T/T 30 days after B/L | J76: 0 | K76: USD | L76: 0 | M76: 0 | N76: 80 | O76: 2 | P76: N | Q76: 12/01/2018 | R76: Revenue fell 0% YoY to USD 41.4M; operating margin 2.5%. | S76: 41388000 | T76: 1.0855 | U76: 2.3661 | V76: 105.61 | W76: 0.0252 | X76: =IFERROR(INDEX('코드표'!$B$2:$B$500,MATCH(TRIM(I76),'코드표'!$A$2:$A$500,0)),"미분류") -> OA | Y76: =IFERROR(IF(--L76>0,1,0),"") -> 0
A77: B075 | B77: Tovera Messtechnik GmbH | C77: Germany | D77: DEU | E77: 서유럽 | F77: distributor | G77: private | H77: PRIVATE | I77: OA 60 DAYS | J77: 4710 | K77: EUR | L77: 89 | M77: 4710 | O77: - | P77: Y | Q77: 2022-07-10 | R77: Revenue fell 20% YoY to USD 39.4M; operating margin 10.8%. Some line items were not disclosed. | S77: 39424000 | W77: 0.108 | X77: =IFERROR(INDEX('코드표'!$B$2:$B$500,MATCH(TRIM(I77),'코드표'!$A$2:$A$500,0)),"미분류") -> OA | Y77: =IFERROR(IF(--L77>0,1,0),"") -> 1
A78: B076 | B78: Dorura Handel Sp. z o.o. | C78: Poland | D78: POL | E78: 중동부유럽 | F78: oem_manufacturer | G78: private | H78: PRIVATE | I78: OA 60 days | J78: 0 | K78: EUR | L78: 0 | M78: 0 | N78: 85 | O78: - | P78: Y | Q78: 2021-06-20 | R78: Revenue rose 28% YoY to USD 7.6M; operating margin 15.5%. Some line items were not disclosed. | S78: 7585000 | U78: 0.5352 | V78: 45.14 | W78: 0.1548 | X78: =IFERROR(INDEX('코드표'!$B$2:$B$500,MATCH(TRIM(I78),'코드표'!$A$2:$A$500,0)),"미분류") -> OA | Y78: =IFERROR(IF(--L78>0,1,0),"") -> 0
A79: B077 | B79: Briari Contracting JSC | C79: Vietnam | D79: VNM | E79: 동남아·남아 | F79: epc_contractor | G79: private | H79: PRIVATE | I79: D/P at sight | J79: 0 | K79: USD | L79: 0 | M79: 0 | N79: 76 | O79: 3 | P79: N | Q79: 29/03/2014 | R79: Revenue rose 14% YoY to USD 14.6M; operating loss (-1.8% margin). Current ratio below 1.0 (0.92). Some line items were not disclosed. | S79: 14578000 | T79: 0.9191 | V79: 146.85 | W79: -0.0181 | X79: =IFERROR(INDEX('코드표'!$B$2:$B$500,MATCH(TRIM(I79),'코드표'!$A$2:$A$500,0)),"미분류") -> DP | Y79: =IFERROR(IF(--L79>0,1,0),"") -> 0
A80: B078 | B80: Kalost Manufacturing Co., Ltd. | C80: Vietnam | D80: VNM | E80: 동남아·남아 | F80: oem_manufacturer | G80: private | H80: PRIVATE | I80: T/T 30:70 | J80: 7882 | K80: USD | L80: 0 | M80: 0 | N80: 68 | O80: 3 | P80: N | Q80: Feb 18 2015 | R80: Revenue rose 5% YoY to USD 53.9M; operating margin 0.7%. | S80: 53852000 | T80: 1.0277 | U80: 1.7547 | V80: 100.85 | W80: 0.0069 | X80: =IFERROR(INDEX('코드표'!$B$2:$B$500,MATCH(TRIM(I80),'코드표'!$A$2:$A$500,0)),"미분류") -> TT_SPLIT_30_70 | Y80: =IFERROR(IF(--L80>0,1,0),"") -> 0
A81: B079 | B81: Nelera Kogyo Co., Ltd. | C81: Japan | D81: JPN | E81: 동아시아 | F81: oem_manufacturer | G81: private | H81: PRIVATE | I81: OA 60 days | J81: 6815000 | K81: ¥ | L81: 0 | M81: 0 | N81: 85 | O81: - | P81: Y | Q81: 2025-06-24 | R81: Revenue rose 5% YoY to USD 234.9M; operating margin 12.5%. | S81: 234899000 | T81: 2.145 | U81: 0.2813 | V81: 43.68 | W81: 0.1247 | X81: =IFERROR(INDEX('코드표'!$B$2:$B$500,MATCH(TRIM(I81),'코드표'!$A$2:$A$500,0)),"미분류") -> OA | Y81: =IFERROR(IF(--L81>0,1,0),"") -> 0
A82: B080 | B82: Lorida Shoji K.K. | C82: Japan | D82: JPN | E82: 동아시아 | F82: distributor | G82: private | H82: PRIVATE | I82: O/A 60 | J82: 3149000 | K82: ¥ | L82: 0 | M82: 0 | N82: 82 | O82: - | P82: Y | Q82: 03/11/2012 | R82: Revenue rose 2% YoY to USD 40.4M; operating margin 8.0%. | S82: 40446000 | T82: 1.638 | U82: 0.7411 | V82: 52.57 | W82: 0.0801 | X82: =IFERROR(INDEX('코드표'!$B$2:$B$500,MATCH(TRIM(I82),'코드표'!$A$2:$A$500,0)),"미분류") -> OA | Y82: =IFERROR(IF(--L82>0,1,0),"") -> 0
A83: B081 | B83: Marida Keisoku Co., Ltd. | C83: Japan | D83: JPN | E83: 동아시아 | F83: distributor | G83: private | H83: PRIVATE | I83: L/C 60 days | J83: 0 | K83: JPY | L83: 0 | M83: 0 | O83: - | P83: N | Q83: 2024-12-01 | R83: FY2025 financial statements not received. | X83: =IFERROR(INDEX('코드표'!$B$2:$B$500,MATCH(TRIM(I83),'코드표'!$A$2:$A$500,0)),"미분류") -> LC_USANCE | Y83: =IFERROR(IF(--L83>0,1,0),"") -> 0
A84: B082 | B84: Tesvirel Keisoku K.K. | C84: Japan | D84: JPN | E84: 동아시아 | F84: oem_manufacturer | G84: private | H84: PRIVATE | I84: OA 60 days | J84: 6545000 | K84: JPY | L84: 0 | M84: 0 | N84: 74 | O84: - | P84: Y | Q84: 2020.11.17 | R84: Revenue rose 18% YoY to USD 364.4M; operating margin 3.8%. | S84: 364351000 | T84: 1.7669 | U84: 1.6674 | V84: 69.94 | W84: 0.0382 | X84: =IFERROR(INDEX('코드표'!$B$2:$B$500,MATCH(TRIM(I84),'코드표'!$A$2:$A$500,0)),"미분류") -> OA | Y84: =IFERROR(IF(--L84>0,1,0),"") -> 0
A85: B083 | B85: Oroari Industries LLC | C85: United States | D85: USA | E85: 북미·중남미 | F85: oem_manufacturer | G85: private | H85: PRIVATE | I85: OA 60 days | J85: 2200 | K85: USD | L85: 305 | M85: 2200 | O85: - | P85: Y | Q85: Dec 28 2024 | R85: Revenue fell 39% YoY to USD 4.6M; operating margin turned negative (-4.3%). Current ratio below 1.0 (0.92). | S85: 4578000 | T85: 0.9178 | U85: 4.1549 | V85: 83.95 | W85: -0.0426 | X85: =IFERROR(INDEX('코드표'!$B$2:$B$500,MATCH(TRIM(I85),'코드표'!$A$2:$A$500,0)),"미분류") -> OA | Y85: =IFERROR(IF(--L85>0,1,0),"") -> 1
A86: B084 | B86: Korari Handel Sp. z o.o. | C86: Poland | D86: POL | E86: 중동부유럽 | F86: utility | G86: private | H86: PRIVATE | I86: OA 90 days | J86: 34990 | K86: € | L86: 0 | M86: 0 | O86: - | P86: N | Q86: 2014-02-04 | R86: Revenue rose 8% YoY to USD 530.4M; operating margin 14.1%. | S86: 530436000 | T86: 2.4413 | U86: 0.4085 | V86: 51.17 | W86: 0.1408 | X86: =IFERROR(INDEX('코드표'!$B$2:$B$500,MATCH(TRIM(I86),'코드표'!$A$2:$A$500,0)),"미분류") -> OA | Y86: =IFERROR(IF(--L86>0,1,0),"") -> 0
A87: B085 | B87: Corida Trading LLC | C87: United Arab Emirates | D87: ARE | E87: 중동·아프리카 | F87: distributor | G87: private | H87: PRIVATE | I87: 10% T/T advance + 90% O/A 90 days | J87: 211500 | K87: USD | L87: 22 | M87: 40500 | O87: 2 | P87: Y | Q87: Mar 2 2026 | R87: Revenue of USD 48.2M; operating margin 14.6%. | S87: 48200000 | T87: 2.4101 | U87: 0.46 | V87: 38 | W87: 0.146 | X87: =IFERROR(INDEX('코드표'!$B$2:$B$500,MATCH(TRIM(I87),'코드표'!$A$2:$A$500,0)),"미분류") -> 미분류 | Y87: =IFERROR(IF(--L87>0,1,0),"") -> 1
A88: B086 | B88: Oroasta Handelsgesellschaft AG | C88: Germay | D88: DEU | E88: 서유럽 | F88: oem_manufacturer | G88: private | H88: PRIVATE | I88: T/T 90 days after B/L | J88: 165085 | K88: EUR | L88: 0 | M88: 0 | N88: 77 | O88: - | P88: N | Q88: 2024-06-04 | R88: Revenue rose 17% YoY to USD 412.8M; operating margin 17.4%. | S88: 412770000 | T88: 2.4251 | U88: 1.064 | V88: 57.54 | W88: 0.174 | X88: =IFERROR(INDEX('코드표'!$B$2:$B$500,MATCH(TRIM(I88),'코드표'!$A$2:$A$500,0)),"미분류") -> OA | Y88: =IFERROR(IF(--L88>0,1,0),"") -> 0
A89: B087 | B89: Yorura Outlets Corp. | C89: Taiwan | D89: TWN | E89: 동아시아 | F89: retail | G89: private | H89: PRIVATE | I89: 30% T/T advance, 70% within 30 days after B/L | J89: 113071.61 | K89: USD | L89: 32 | M89: 49854.61 | N89: 78 | O89: 2 | P89: Y | Q89: 22/08/2015 | R89: Revenue rose 8% YoY to USD 417.6M; operating loss (-7.5% margin). Current ratio below 1.0 (0.78). | S89: 417625000 | T89: 0.7813 | U89: 4.0517 | V89: 78.3 | W89: -0.0751 | X89: =IFERROR(INDEX('코드표'!$B$2:$B$500,MATCH(TRIM(I89),'코드표'!$A$2:$A$500,0)),"미분류") -> TT_SPLIT_30_70 | Y89: =IFERROR(IF(--L89>0,1,0),"") -> 1
A90: B088 | B90: Tareon Contracting LLC | C90: United States | D90: USA | E90: 북미·중남미 | F90: epc_contractor | G90: private | H90: PRIVATE | I90: T/T in advance | J90: 0 | K90: usd | L90: 0 | M90: 0 | O90: - | P90: N | Q90: Sep 25 2025 | R90: Revenue rose 4% YoY to USD 260.7M; operating margin 11.1%. Some line items were not disclosed. | S90: 260702000 | T90: 1.1423 | U90: 2.7011 | W90: 0.1113 | X90: =IFERROR(INDEX('코드표'!$B$2:$B$500,MATCH(TRIM(I90),'코드표'!$A$2:$A$500,0)),"미분류") -> TT_ADV | Y90: =IFERROR(IF(--L90>0,1,0),"") -> 0
A91: B089 | B91: Morost Automation Ltd | C91: Nigeria | D91: NGA | E91: 중동·아프리카 | F91: oem_manufacturer | G91: private | H91: PRIVATE | I91: Irrevocable L/C at sight | J91: 760 | K91: USD | L91: 0 | M91: 0 | O91: 6 | P91: N | Q91: 18/03/2016 | R91: Revenue rose 8% YoY to USD 11.1M. Some line items were not disclosed. | S91: 11100000 | T91: 1.3178 | U91: 1.767 | V91: 129.26 | X91: =IFERROR(INDEX('코드표'!$B$2:$B$500,MATCH(TRIM(I91),'코드표'!$A$2:$A$500,0)),"미분류") -> LC_SIGHT | Y91: =IFERROR(IF(--L91>0,1,0),"") -> 0
A92: B090 | B92: Calova Automation Inc. | C92: United States | D92: USA | E92: 북미·중남미 | F92: oem_manufacturer | G92: private | H92: PRIVATE | I92: OA 60 days | J92: 7550 | K92: USD | L92: 0 | M92: 0 | N92: 79 | O92: - | P92: N | Q92: 2013-08-30 | R92: Revenue rose 6% YoY to USD 8.3M; operating margin 2.1%. | S92: 8275000 | T92: 1.42 | U92: 2.6232 | V92: 63.08 | W92: 0.021 | X92: =IFERROR(INDEX('코드표'!$B$2:$B$500,MATCH(TRIM(I92),'코드표'!$A$2:$A$500,0)),"미분류") -> OA | Y92: =IFERROR(IF(--L92>0,1,0),"") -> 0
A93: B091 | B93: Lorion Handel B.V. | C93: Netherlands | D93: NLD | E93: 서유럽 | F93: distributor | G93: private | H93: PRIVATE | I93: D/A 90 | J93: 4.0k | K93: EUR | L93: 0 | M93: 0 | N93: 75 | O93: - | P93: Y | Q93: 03/12/2025 | R93: Revenue rose 15% YoY to USD 5.7M; operating margin 9.8%. | S93: 5745000 | T93: 1.7027 | U93: 1.2415 | V93: 66.58 | W93: 0.0978 | X93: =IFERROR(INDEX('코드표'!$B$2:$B$500,MATCH(TRIM(I93),'코드표'!$A$2:$A$500,0)),"미분류") -> DA | Y93: =IFERROR(IF(--L93>0,1,0),"") -> 0
A94: B092 | B94: Eldolin Przemysł Sp. z o.o. | C94: Poland | D94: POL | E94: 중동부유럽 | F94: distributor | G94: private | H94: PRIVATE | I94: T/T 30/70 | J94: 0 | K94: EUR | L94: 0 | M94: 0 | N94: 82 | O94: - | P94: N | Q94: 2019-07-21 | R94: Revenue rose 16% YoY to USD 7.6M; operating loss (-3.5% margin). | S94: 7605000 | T94: 1.1524 | U94: 10.4589 | V94: 129.68 | W94: -0.0354 | X94: =IFERROR(INDEX('코드표'!$B$2:$B$500,MATCH(TRIM(I94),'코드표'!$A$2:$A$500,0)),"미분류") -> TT_SPLIT_30_70 | Y94: =IFERROR(IF(--L94>0,1,0),"") -> 0
A95: B093 | B95: Orunde State Water Board | C95: Nigeria | D95: NGA | E95: 중동·아프리카 | F95: public_agency | G95: public | H95: EM_GOV | I95: Net 30 days after receipt of invoice | J95: 88060 | K95: USD | L95: 0 | M95: 0 | N95: 69 | O95: 6 | P95: Y | Q95: 2019.1.9 | R95: FY2025 financial statements not received. | X95: =IFERROR(INDEX('코드표'!$B$2:$B$500,MATCH(TRIM(I95),'코드표'!$A$2:$A$500,0)),"미분류") -> OA | Y95: =IFERROR(IF(--L95>0,1,0),"") -> 0
A96: B094 | B96: Korora Manufacturing Co., Ltd. | C96: Vietnam | D96: VNM | E96: 동남아·남아 | F96: oem_manufacturer | G96: private | H96: PRIVATE | I96: O/A 90 | J96: 13030 | K96: USD | L96: 0 | M96: 0 | N96: 83 | O96: 3 | P96: Y | Q96: Feb 11 2015 | R96: Revenue rose 2% YoY to USD 49.9M; operating margin 16.0%. | S96: 49932000 | T96: 1.8514 | U96: 0.9688 | V96: 59.12 | W96: 0.1597 | X96: =IFERROR(INDEX('코드표'!$B$2:$B$500,MATCH(TRIM(I96),'코드표'!$A$2:$A$500,0)),"미분류") -> OA | Y96: =IFERROR(IF(--L96>0,1,0),"") -> 0
A97: B095 | B97: Bexura Industries S.A.E. | C97: Egypt | D97: EGY | E97: 중동·아프리카 | F97: oem_manufacturer | G97: private | H97: PRIVATE | I97: O/A30 | J97: 9150 | K97: USD | L97: 0 | M97: 0 | N97: 59 | O97: 6 | P97: Y | Q97: Mar 30 2015 | R97: Revenue rose 2% YoY to USD 20.2M; operating loss (-3.2% margin). Some line items were not disclosed. | S97: 20182000 | V97: 81.31 | W97: -0.0315 | X97: =IFERROR(INDEX('코드표'!$B$2:$B$500,MATCH(TRIM(I97),'코드표'!$A$2:$A$500,0)),"미분류") -> OA | Y97: =IFERROR(IF(--L97>0,1,0),"") -> 0
A98: B096 | B98: Marova Trading Inc. | C98: United States | D98: USA | E98: 북미·중남미 | F98: distributor | G98: private | H98: PRIVATE | I98: O/A 90 | J98: 25450 | K98: USD | L98: 0 | M98: 0 | N98: 86 | O98: - | P98: Y | Q98: Sep 24 2013 | R98: FY2025 financial statements not received. | X98: =IFERROR(INDEX('코드표'!$B$2:$B$500,MATCH(TRIM(I98),'코드표'!$A$2:$A$500,0)),"미분류") -> OA | Y98: =IFERROR(IF(--L98>0,1,0),"") -> 0
A99: B097 | B99: Tahrava Water Authority | C99: Saudi Arabia | D99: SAU | E99: 중동·아프리카 | F99: public_agency | G99: public | H99: EM_GOV | I99: Net 30 days after receipt of invoice | J99: 0 | K99: USD | L99: 0 | M99: 0 | N99: 80 | O99: 2 | P99: Y | Q99: 2017-01-23 | R99: Revenue rose 12% YoY to USD 429.7M. Some line items were not disclosed. | S99: 429741000 | T99: 1.7413 | U99: 1.6987 | V99: 77.2 | X99: =IFERROR(INDEX('코드표'!$B$2:$B$500,MATCH(TRIM(I99),'코드표'!$A$2:$A$500,0)),"미분류") -> OA | Y99: =IFERROR(IF(--L99>0,1,0),"") -> 0
A100: B098 | B100: Zenyn Outlets Ltd. | C100: India | D100: IND | E100: 동남아·남아 | F100: retail | G100: private | H100: PRIVATE | I100: T/T 30 days after B/L | J100: 70150 | K100: US$ | L100: 0 | M100: 0 | N100: 77 | O100: 3 | P100: Y | Q100: 2025.4.23 | R100: Revenue rose 18% YoY to USD 249.6M; operating margin 0.7%. Current ratio below 1.0 (0.88). | S100: 249642000 | T100: 0.8798 | U100: 3.7488 | V100: 107.95 | W100: 0.0074 | X100: =IFERROR(INDEX('코드표'!$B$2:$B$500,MATCH(TRIM(I100),'코드표'!$A$2:$A$500,0)),"미분류") -> OA | Y100: =IFERROR(IF(--L100>0,1,0),"") -> 0
...

Sheet 코드표
A1: 원래 표기 | B1: 표준 코드 | C1: 메모
A2: T/T in advance | B2: TT_ADV
A3: TT ADVANCE | B3: TT_ADV
A4: 100% T/T before shipment | B4: TT_ADV
A5: T/T | B5: TT_ADV | C5: 표기만으로는 선적 전 · 후를 알 수 없다 — 공개 사전은 TT_ADV로 두었다. 원장(인보이스)에서 확인할 표기
A6: TT | B6: TT_ADV | C6: 표기만으로는 선적 전 · 후를 알 수 없다 — 공개 사전은 TT_ADV로 두었다. 원장(인보이스)에서 확인할 표기
A7: T/T 30/70 | B7: TT_SPLIT_30_70
A8: 30% T/T advance, 70% within 30 days after B/L | B8: TT_SPLIT_30_70
A9: T/T 30:70 | B9: TT_SPLIT_30_70
A10: O/A 30 | B10: OA
A11: OA 30 days | B11: OA
A12: O/A30 | B12: OA
A13: T/T 30 days after B/L | B13: OA
A14: O/A 60 | B14: OA
A15: O/A60 | B15: OA
A16: OA 60 days | B16: OA
A17: T/T 60days | B17: OA
A18: T/T 60 days after B/L | B18: OA
... A43: Usance L/C 90 days | B43: LC_USANCE
A45: 원천: data/data_dictionary.xlsx 시트 payment_terms_map(42개 표기) — 열 순서는 내 코드표 CSV의 앞 두 열(원래 표기 · 표준 코드)과 같습니다
